Workbook
Name ggg: 'Raw Data (2)'!$A$1:$A$4
Name ggg: 'Raw Data (3)'!$A$1:$A$4
Name ggg: 'Raw Data (4)'!$A$1:$A$4
Name ggg: 'Raw Data'!$A$1:$A$4
Name NativeTimeline_Order_Date1: #N/A
Name Slicer_Region1: #N/A

Sheet Raw Data (3)
A1: Order ID | B1: Order Date | C1: Ship Date | D1: Ship Mode | E1: First Name | F1: Last Name | G1: Email | H1: Phone | I1: Segment | J1: Region | K1: State | L1: Category | M1: Sub-Category | N1: Product Name | O1: Quantity | P1: Unit Price (₦) | Q1: Discount (%) | R1: Discount Amount (₦) | S1: Sales (₦) | T1: Profit (₦)
A2: ORD-10858 | B2: 44562 | C2: 44567 | D2: Standard Class | E2: Ayo | F2: Adeleke | G2: ayo.adeleke@gmail.com | H2: 8161000159 | I2: Consumer | J2: East | K2: Onitsha | L2: Office Supplies | M2: Envelopes | N2: Brown Kraft Envelopes | O2: 6 | P2: 18354.33 | Q2: 0 | R2: 0 | S2: 110125.98 | T2: -12981.35 | U2: =VALUE(S2) -> 110125.98
A3: ORD-10268 | B3: 44562 | C3: 44565 | D3: Second Class | E3: Sade | F3: Chukwu | G3: sade.chukwu@hotmail.com | H3: 7037629401 | I3: Corporate | J3: South | K3: Lagos | L3: Clothing | M3: Accessories | N3: Sunglasses UV400 | O3: 3 | P3: 24262.94 | Q3: 0 | R3: 0 | S3: 72788.82 | T3: 13084.2 | U3: =VALUE(S3) -> 72788.82
A4: ORD-10867 | B4: 44563 | C4: 44568 | D4: Second Class | E4: Yemi | F4: Sanusi | G4: email.com | H4: 8066143155 | I4: Home Office | K4: Ilorin | L4: Furniture | M4: Storage | N4: Plastic Drawers | O4: 18 | P4: 149939.9 | Q4: 0 | R4: 0 | S4: 2698918.2 | T4: 1136056.6 | U4: =VALUE(S4) -> 2698918.2
A5: ORD-10470 | B5: 44563 | C5: 44566 | D5: Second Class | E5: Kunle | F5: Chukwu | G5: kunle.chukwu@outlook.com | H5: 8037377917 | I5: Corporate | J5: West | K5: Ado-Ekiti | L5: oFFICE sUPPLIES | M5: Art Supplies | N5: Acrylic Paint Kit | O5: 17 | P5: 14836.4 | Q5: 10 | R5: 25221.88 | S5: 226996.92 | T5: -27854.6 | U5: =VALUE(S5) -> 226996.92
A6: ORD-10631 | B6: 44564 | C6: 44565 | D6: Same Day | E6: Hauwa | F6: Sanusi | G6: hauwa.sanusi@gmail.com | H6: 8031291769 | I6: corporate | J6: North | K6: Katsina | L6: Food & Beverages | M6: Grains | N6: Semolina 5kg | O6: 6 | P6: 4344.57 | Q6: 0 | R6: 0 | S6: 26067.42 | T6: 8215.25 | U6: =VALUE(S6) -> 26067.42
A7: ORD-10377 | B7: 44564 | C7: 44564 | D7: Same Day | E7: Chidinma | F7: Obi | G7: chidinma.obi@outlook.com | H7: 8151548852 | I7: Corporate | J7: West | K7: Ilorin | L7: Office Supplies | M7: Envelopes | N7: Padded Envelopes | O7: 20 | P7: 17602.35 | Q7: 25 | R7: 88011.75 | S7: 264035.25 | T7: 51523.21 | U7: =VALUE(S7) -> 264035.25
A8: ORD-10862 | B8: 44565 | C8: 44565 | D8: Same Day | E8: Kehinde | F8: Gambo | G8: kehinde.gambo@hotmail.com | H8: 8159196133 | I8: Consumer | J8: East | K8: Onitsha | L8: Furniture | M8: Chairs | N8: Visitor Chair | O8: 20 | P8: 70613.98 | Q8: 10 | R8: 141227.96 | S8: 1271051.6 | T8: 157298.35 | U8: =VALUE(S8) -> 1271051.6
A9: ORD-10528 | B9: 44568 | C9: 44573 | D9: Second Class | E9: Chisom | F9: Okonkwo | G9: chisom.okonkwo@outlook.com | H9: 8031767629 | I9: Corporate | J9: West | K9: Ado-Ekiti | L9: Office Supplies | M9: Fasteners | N9: Rubber Bands 100g | O9: 16 | P9: 6222.19 | Q9: 15 | R9: 14933.26 | S9: 84621.78 | T9: 24838.42 | U9: =VALUE(S9) -> 84621.78
A10: ORD-10652 | B10: 44572 | C10: 44576 | D10: Second Class | E10: Chibundo | F10: Danjuma | G10: chibundo.danjuma@gmail.com | H10: 7034108891 | I10: Consumer | J10: North | K10: Kaduna | L10: Food & Beverages | M10: Cooking Oil | N10: Palm Oil 4L | O10: 19 | P10: 6709.5 | Q10: 20 | R10: 25496.1 | S10: 101984.4 | T10: 15349.69 | U10: =VALUE(S10) -> 101984.4
A11: ORD-10441 | B11: 44573 | C11: 44581 | D11: Standard Class | E11: Bola | F11: Okonkwo | G11: bola.okonkwo@yahoo.com | H11: 9079004743 | I11: Corporate | J11: East | K11: Enugu | L11: Clothing | M11: Bags | N11: Crossbody Bag | O11: 10 | P11: 33214.19 | Q11: 10 | R11: 33214.19 | S11: 298927.71 | T11: 79035.7 | U11: =VALUE(S11) -> 298927.71
A12: ORD-10486 | B12: 44575 | C12: 44579 | D12: Second Class | E12: Chidi | F12: Musa | G12: INVALID | H12: 8032932555 | I12: Corporate | J12: West | K12: Ilorin | L12: Furniture | M12: Bookcases | N12: Corner Bookshelf | O12: 19 | P12: 41437.39 | Q12: 10 | R12: 78731.04 | S12: 708579.37 | T12: -87620.87 | U12: =VALUE(S12) -> 708579.37
A13: ORD-10643 | B13: 44575 | C13: 44578 | D13: First Class | E13: Ayo | F13: Obi | G13: ayo.obi@yahoo.com | H13: 8062126456 | I13: Home Office | J13: South | K13: Benin City | L13: Technology | M13: Phones | N13: Xiaomi Redmi 12 | O13: 17 | P13: 397756.09 | Q13: 0 | R13: 0 | S13: 6761853.5 | T13: -11335.22 | U13: =VALUE(S13) -> 6761853.5
A14: ORD-10799 | B14: 44575 | C14: 44577 | D14: First Class | E14: Obinna | F14: Danjuma | G14: obinna.danjuma@gmail.com | H14: 9022191407 | I14: Home Office | J14: West | K14: Ilorin | L14: Food & Beverages | M14: Drinks | N14: Energy Drink 4-Pack | O14: 6 | P14: 3485.58 | Q14: 5 | R14: 1045.67 | S14: $19,867.81 | T14: -14.31 | U14: =VALUE(S14) -> #VALUE!
A15: ORD-10451 | B15: 44575 | C15: 44575 | D15: Same Day | E15: Kunle | F15: Osei | G15: kunle.osei@outlook.com | H15: 8153873296 | I15: Corporate | J15: North | K15: Kaduna | L15: Technology | M15: Tablets | N15: Lenovo Tab M10 | O15: 14 | P15: 326111.89 | Q15: 10 | R15: 456556.65 | S15: 4109009.8 | T15: 935474.6 | U15: =VALUE(S15) -> 4109009.8
A16: ORD-10288 | B16: 44578 | C16: 44578 | D16: Same Day | E16: Sade | F16: Okafor | G16: sade.okafor@gmail.com | H16: 8144643811 | I16: Consumer | J16: East | K16: Aba | L16: Office Supplies | M16: Envelopes | N16: Padded Envelopes | O16: 16 | P16: 19750.27 | Q16: 10 | R16: 31600.43 | S16: 284403.89 | T16: 36463.62 | U16: =VALUE(S16) -> 284403.89
A17: ORD-10568 | B17: 44580 | C17: 44585 | D17: Second Class | E17: Adebayo | F17: Dangote | G17: adebayo.dangote@outlook.com | H17: 8164696630 | I17: Home Office | J17: North | K17: Kaduna | L17: Office Supplies | M17: Fasteners | N17: Binder Clips Asst. | O17: 6 | P17: 14027.7 | Q17: 5 | R17: 4208.31 | S17: 79957.89 | T17: -9805.44 | U17: =VALUE(S17) -> 79957.89
A18: ORD-10538 | B18: 44580 | C18: 44584 | D18: SECOND CLASS | E18: Kehinde | F18: Bello | G18: kehinde.bello@yahoo.com | H18: 7068165734 | I18: Home Office | J18: South | K18: Ibadan | L18: Furniture | M18: Chairs | N18: Executive Chair | O18: 16 | P18: 69160.42 | Q18: 0 | R18: 0 | S18: 1106566.7 | T18: 461480.28 | U18: =VALUE(S18) -> 1106566.7
A19: ORD-10285 | B19: 44580 | C19: 44583 | D19: First Class | E19: Nike | F19: Alakija | G19: nike.alakija@yahoo.com | H19: 9021121097 | I19: Corporate | J19: North | K19: Sokoto | L19: Food & Beverages | M19: Grains | N19: Semolina 5kg | O19: 18 | P19: 3470.37 | Q19: 15 | R19: 9370 | S19: 53096.66 | T19: 4611.51 | U19: =VALUE(S19) -> 53096.66
A20: ORD-10667 | B20: 44580 | C20: 44581 | D20: Same Day | E20: Emeka | F20: Adebayo | G20: emeka.adebayo@hotmail.com | H20: 9074654790 | I20: Consumer | J20: West | K20: Akure | L20: Clothing | M20: Shirts | N20: Ankara Print Shirt | O20: 9 | P20: 42369.87 | Q20: 25 | R20: 95332.21 | S20: 285996.62 | T20: 10986.82 | U20: =VALUE(S20) -> 285996.62
A21: ORD-10701 | B21: 44582 | C21: 44583 | D21: Same Day | G21: chibundo.adeyemi@yahoo.com | H21: 8142124878 | I21: Home Office | J21: South | K21: Ibadan | L21: Technology | M21: Tablets | N21: Samsung Tab A8 | O21: 4 | P21: 101681.42 | Q21: 25 | R21: 101681.42 | S21: 305044.26 | T21: 38178.16 | U21: =VALUE(S21) -> 305044.26
A22: ORD-10505 | B22: 44583 | C22: 44590 | D22: Standard Class | E22: Bola | F22: Obi | G22: bola.obi@yahoo.com | H22: 7038788747 | I22: Corporate | J22: West | K22: Ilorin | L22: Clothing | M22: Bags | N22: Laptop Backpack | O22: 8 | P22: 5549.59 | Q22: 20 | R22: 8879.34 | S22: 35517.38 | T22: -2338.7 | U22: =VALUE(S22) -> 35517.38
A23: ORD-10905 | B23: 44584 | C23: 44587 | D23: Second Class | E23: Seun | F23: Atiku | H23: 8031414120 | I23: Corporate | J23: East | K23: Onitsha | L23: Food & Beverages | M23: Snacks | N23: Plantain Chips 200g | O23: 15 | P23: 3158.75 | Q23: 15 | R23: 7107.19 | S23: 40274.06 | T23: 2030.8 | U23: =VALUE(S23) -> 40274.06
A24: ORD-10616 | B24: 44584 | C24: 44587 | D24: First Class | E24: Ibrahim | F24: Fashola | G24: ibrahim.fashola@outlook.com | H24: 8132111241 | I24: Consumer | J24: East | K24: Enugu | L24: Clothing | M24: Shoes | N24: Sandals | O24: 7 | P24: 11123.53 | Q24: 0 | R24: 0 | S24: 77864.71 | T24: 14527.63 | U24: =VALUE(S24) -> 77864.71
A25: ORD-10139 | B25: 44586 | C25: 44586 | D25: same day | E25: Ronke | F25: Atiku | G25: ronke.atiku@outlook.com | H25: 8155809835 | I25: Home Office | J25: North | K25: Kano | L25: Technology | M25: Printers | N25: Brother HL-L2350DW | O25: 6 | P25: 365682.95 | Q25: 0 | R25: 0 | S25: 2194097.7 | T25: 879458.66 | U25: =VALUE(S25) -> 2194097.7
A26: ORD-10521 | B26: 44587 | C26: 44590 | D26: Second Class | E26: Sade | F26: Tinubu | G26: sade.tinubu@hotmail.com | H26: 7062348021 | I26: Consumer | J26: South | K26: Benin City | L26: Food&Beverages | M26: Snacks | N26: Popcorn 6-Pack | O26: 14 | P26: 1576.84 | Q26: 10 | R26: 2207.58 | S26: 19868.18 | T26: 5267.1 | U26: =VALUE(S26) -> 19868.18
A27: ORD-10842 | B27: 44588 | C27: 44589 | D27: Same Day | E27: Aisha | F27: Osei | G27: aisha.osei@outlook.com | H27: 9078197382 | I27: Corporate | J27: West | K27: Ilorin | L27: Food & Beverages | M27: Drinks | N27: Energy Drink 4-Pack | O27: 10 | P27: 1296.6 | Q27: 10 | R27: 1296.6 | S27: 11669.4 | T27: 3324.08 | U27: =VALUE(S27) -> 11669.4
A28: ORD-10926 | B28: 44591 | C28: 44596 | D28: Second Class | E28: Oluwaseun | F28: Musa | G28: oluwaseun.musa@outlook.com | H28: 9075120422 | I28: Home Office | J28: East | K28: Onitsha | L28: Clothing | M28: Shirts | N28: Men's Polo Shirt | O28: 9 | P28: 7584.73 | Q28: 0 | R28: 0 | S28: 68262.57 | T28: 16688.44 | U28: =VALUE(S28) -> 68262.57
A29: ORD-10982 | B29: 44594 | C29: 44599 | D29: Second Class | E29: Olumide | F29: Chukwu | G29: olumide.chukwu@yahoo.com | H29: 7068058810 | I29: Corporate | J29: North | K29: Abuja | L29: fOOD & bEVERAGES | M29: Condiments | N29: Pepper Mix 200g | O29: 10 | P29: 6995.77 | Q29: 25 | R29: 17489.43 | S29: 52468.27 | T29: 12332.65 | U29: =VALUE(S29) -> 52468.27
A30: ORD-10903 | B30: 44595 | C30: 44598 | D30: Second Class | E30: Olumide | F30: Chukwu | G30: olumide.chukwu@hotmail.com | H30: 7068824038 | I30: Consumer | J30: East | K30: Owerri | L30: Clothing | M30: Shoes | N30: Women's Heels | O30: 14 | P30: 21921.87 | Q30: 0 | R30: 0 | S30: 306906.18 | T30: -853.32 | U30: =VALUE(S30) -> 306906.18
A31: ORD-10925 | B31: 44595 | C31: 44596 | D31: Same Day | E31: Deola | F31: Sowore | G31: deola.sowore@gmail.com | H31: 8144580502 | I31: Home Office | J31: East | K31: Awka | L31: Food & Beverages | M31: Condiments | N31: Soy Sauce 500ml | O31: 8 | P31: 6303.5 | Q31: 15 | R31: 7564.2 | S31: 42863.8 | T31: 7992.08 | U31: =VALUE(S31) -> 42863.8
A32: ORD-10363 | B32: 44595 | C32: 44595 | D32: Same Day | E32: Adaeze | F32: Adeleke | G32: adaeze.adeleke@outlook.com | H32: 9021718308 | I32: Home Office | J32: East | K32: Owerri | L32: Clothing | M32: Shirts | N32: Women's Blouse | O32: 17 | P32: 36705.46 | Q32: 20 | R32: 124798.56 | S32: 499194.26 | T32: 206693.32 | U32: =VALUE(S32) -> 499194.26
A33: ORD-10113 | B33: 44596 | C33: 44597 | D33: Same Day | E33: Adaeze | F33: Sowore | H33: 7066161977 | I33: Corporate | J33: West | K33: Ado-Ekiti | L33: Technology | M33: Printers | N33: Brother HL-L2350DW | O33: 19 | P33: 130505.74 | Q33: 5 | R33: 123980.45 | S33: 2355628.6 | T33: 666266.15 | U33: =VALUE(S33) -> 2355628.6
A34: ORD-10923 | B34: 44598 | C34: 44601 | D34: First Class | E34: Lanre | F34: Tinubu | G34: lanre.tinubu@gmail.com | H34: 8148000211 | I34: Corporate | J34: West | K34: Abeokuta | L34: Clothing | M34: Accessories | N34: Wallet Genuine Leather | O34: 11 | P34: 11930.65 | Q34: 5 | R34: 6561.86 | S34: 124675.29 | T34: 14906.53 | U34: =VALUE(S34) -> 124675.29
A35: ORD-10929 | B35: 44599 | C35: 44601 | D35: First Class | E35: Tunde | F35: Adeyemi | G35: tunde.adeyemi@yahoo.com | H35: 7033690055 | I35: Home Office | J35: West | K35: Ilorin | L35: Food & Beverages | M35: Condiments | N35: Maggi Cubes 100pk | O35: 12 | P35: 3985.92 | Q35: 0 | R35: 0 | S35: 47831.04 | T35: 2588.06 | U35: =VALUE(S35) -> 47831.04
A36: ORD-10618 | B36: 44605 | C36: 44609 | D36: Second Class | E36: Amara | F36: Tinubu | G36: amara.tinubu@gmail.com | H36: 8145770866 | I36: Corporate | J36: East | K36: Awka | L36: Furniture | M36: Storage | N36: 4-Drawer Cabinet | O36: 17 | P36: 162082.68 | Q36: 0 | R36: 0 | S36: 2755405.6 | T36: 144476.72 | U36: =VALUE(S36) -> 2755405.6
A37: ORD-10610 | B37: 44606 | D37: Same Day | E37: Tunde | F37: Sanusi | G37: spaces in@email.com | H37: 8138044872 | I37: Consumer | J37: SOTH | K37: Warri | L37: Clothing | M37: Shoes | N37: Leather Loafers | O37: 6 | P37: 36767.61 | Q37: 10 | R37: 22060.57 | S37: 198545.09 | T37: -28573.78 | U37: =VALUE(S37) -> 198545.09
A38: ORD-10382 | B38: 44607 | C38: 44613 | D38: STANDARD CLASS | E38: Ronke | F38: Tinubu | G38: ronke.tinubu@outlook.com | H38: 7066751103 | I38: Consumer | J38: North | K38: Abuja | L38: Office Supplies | M38: Envelopes | N38: C5 Envelopes | O38: 17 units | P38: 16813.46 | Q38: 25 | R38: 71457.21 | S38: 214371.61 | T38: 25114.44 | U38: =VALUE(S38) -> 214371.61
A39: ORD-10910 | B39: 44607 | C39: 44611 | D39: Second Class | E39: Kunle | F39: Chukwu | G39: kunle.chukwu@outlook.com | H39: 8156042710 | I39: Consumer | J39: East | K39: Awka | L39: Clothing | M39: Bags | N39: Laptop Backpack | O39: 10 | P39: 42940.32 | Q39: 10 | R39: 42940.32 | S39: 386462.88 | T39: -33275.2 | U39: =VALUE(S39) -> 386462.88
A40: ORD-10654 | B40: 44608 | C40: 44610 | D40: First Class | E40: Nike | F40: Gambo | G40: nike.gambo@outlook.com | H40: 7067004652 | I40: Home Office | J40: South | K40: Lagos | L40: Technology | M40: Phones | N40: Tecno Spark 10 | O40: 19 | P40: 47528.05 | Q40: 5 | R40: 45151.65 | S40: 857881.3 | T40: 310481.94 | U40: =VALUE(S40) -> 857881.3
A41: ORD-10832 | B41: 44609 | C41: 44615 | D41: Standard Class | E41: Yemi | F41: Abubakar | G41: yemi.abubakar@gmail.com | H41: 8107264416 | I41: Home Office | K41: Abuja | L41: Technology | M41: Phones | N41: Xiaomi Redmi 12 | O41: 3 | P41: 363633.82 | Q41: 0 | R41: 0 | S41: 1090901.5 | T41: -157322.01 | U41: =VALUE(S41) -> 1090901.5
A42: ORD-10852 | B42: 44611 | C42: 44616 | D42: Standard Class | E42: Zainab | F42: Sanusi | G42: zainab.sanusi@gmail.com | H42: 8034674225 | I42: Consumer | J42: East | K42: Onitsha | L42: Furniture | M42: Tables | N42: Conference Table | O42: 11 | P42: 94100.43 | Q42: 15 | R42: 155265.71 | S42: 879839.02 | T42: 267099.63 | U42: =VALUE(S42) -> 879839.02
A43: ORD-10576 | B43: 44611 | C43: 44614 | D43: Second Class | E43: Oluwaseun | F43: Olawale | G43: oluwaseun.olawale@yahoo.com | H43: 7035812480 | I43: Consumer | J43: West | K43: Ilorin | L43: Furniture | M43: Storage | N43: 4-Drawer Cabinet | O43: 4 | P43: 92593.14 | Q43: 5 | R43: 18518.63 | S43: 351853.93 | T43: -31300.31 | U43: =VALUE(S43) -> 351853.93
A44: ORD-10745 | B44: 44615 | C44: 44617 | D44: First Class | E44: Uchenna | F44: Danjuma | G44: uchenna.danjuma@outlook.com | H44: 9015885832 | I44: Consumer | J44: North | K44: Kaduna | L44: Office Supplies | M44: Fasteners | N44: Paper Clips Box | O44: 10 | P44: 14407.18 | Q44: 20 | R44: 28814.36 | S44: 115257.44 | T44: 32023.97 | U44: =VALUE(S44) -> 115257.44
A45: ORD-10171 | B45: 44616 | C45: 44619 | D45: First Class | E45: Ibrahim | F45: Dangote | H45: 9017572491 | I45: Home Office | J45: South | K45: Port Harcourt | L45: Office Supplies | M45: Fasteners | N45: Stapler + Staples | O45: 8 | P45: 19703.14 | Q45: 20 | R45: 31525.02 | S45: 126100.1 | T45: 10281.11 | U45: =VALUE(S45) -> 126100.1
A46: ORD-10499 | B46: 44616 | C46: 44616 | D46: Same Day | E46: Musa | F46: Musa | G46: musa.musa@hotmail.com | H46: 8164454299 | I46: Home Office | J46: South | K46: Lagos | L46: Furniture | M46: Bookcases | N46: Metal Bookcase | O46: 2 | P46: 20036.46 | Q46: 10 | R46: 4007.29 | S46: 36065.63 | T46: 5810.86 | U46: =VALUE(S46) -> 36065.63
A47: ORD-10798 | B47: 44618 | C47: 44621 | D47: First Class | E47: Oluwaseun | F47: Obi | G47: oluwaseun.obi@yahoo.com | H47: 7064610526 | I47: Home Office | J47: North | K47: Abuja | L47: Clothing | M47: Shoes | N47: Sandals | O47: 10 | P47: 31979.86 | Q47: 10 | R47: 31979.86 | S47: 287818.74 | T47: -3010.98 | U47: =VALUE(S47) -> 287818.74
A48: ORD-10735 | B48: 44622 | C48: 44622 | D48: Same Day | E48: Ayo | F48: Danjuma | G48: ayo.danjuma@yahoo.com | H48: 9056899311 | I48: Home Office | J48: East | K48: Owerri | L48: Food & Beverages | M48: Cooking Oil | N48: Coconut Oil 1L | O48: 1 | P48: 7967.86 | Q48: 10 | R48: 796.79 | S48: 7171.07 | T48: 1318.5 | U48: =VALUE(S48) -> 7171.07
A49: ORD-10959 | B49: 44624 | C49: 44629 | D49: Standard Class | E49: Chisom | F49: Adeyemi | G49: chisom.adeyemi@gmail.com | H49: 8064194751 | I49: Home Office | J49: Norh | K49: Kano | L49: Clothing | M49: Shirts | N49: T-Shirt 3-Pack | O49: 18 | P49: 35696.94 | Q49: 10 | R49: 64254.49 | S49: 578290.43 | T49: -66880.13 | U49: =VALUE(S49) -> 578290.43
A50: ORD-10160 | B50: 44625 | C50: 44631 | D50: Standard Class | E50: Nike | F50: Adeleke | G50: nike.adeleke@outlook.com | H50: 8135843084 | I50: Consumer | J50: West | K50: Akure | L50: Furniture | M50: Storage | N50: Wardrobe 3-Door | O50: 16 | P50: 135713.14 | Q50: 25 | R50: 542852.56 | S50: 1628557.7 | T50: 254842.55 | U50: =VALUE(S50) -> 1628557.7
A51: ORD-10881 | B51: 44625 | C51: 44626 | D51: Same Day | E51: Tunde | F51: Otedola | G51: tunde.otedola@gmail.com | H51: 9013442155 | I51: Consumer | J51: East | K51: Owerri | L51: Technology | M51: Tablets | N51: Lenovo Tab M10 | O51: 15 | P51: 186071.29 | Q51: 10 | R51: 279106.93 | S51: 2511962.4 | T51: 80629.3 | U51: =VALUE(S51) -> 2511962.4
A52: ORD-10953 | B52: 44626 | C52: 44629 | D52: Second Class | E52: Ibrahim | F52: Adebayo | G52: ibrahim.adebayo@outlook.com | H52: 8038244779 | I52: Home Office | J52: West | K52: Ilorin | L52: fURNITURE | M52: Chairs | N52: Mesh Office Chair | O52: 1 | P52: 89481.57 | Q52: 0 | R52: 0 | S52: 89481.57 | T52: 6686.19 | U52: =VALUE(S52) -> 89481.57
A53: ORD-10605 | B53: 44628 | C53: 44628 | D53: Same Day | E53: Amara | F53: Okafor | G53: amara.okafor@outlook.com | H53: 8039706758 | I53: Consumer | J53: West | K53: Ilorin | L53: Food & Beverages | M53: Grains | N53: Garri 10kg | O53: 19 | P53: 1612.16 | Q53: 15 | R53: 4594.66 | S53: 26036.38 | T53: -127.61 | U53: =VALUE(S53) -> 26036.38
A54: ORD-10460 | B54: 44628 | C54: 44628 | D54: Same Day | E54: Taiwo | F54: Adebayo | G54: taiwo.adebayo@gmail.com | H54: 9057855503 | I54: Corporate | J54: North | K54: Kaduna | L54: Technology | M54: Laptops | N54: Dell Inspiron 15 | O54: 2 | P54: 263717.67 | Q54: 25 | R54: 131858.83 | S54: 395576.51 | T54: -22950.28 | U54: =VALUE(S54) -> 395576.51
A55: ORD-10066 | B55: 44629 | C55: 44632 | D55: First Class | E55: Ibrahim | F55: Fashola | G55: ibrahim.fashola@hotmail.com | H55: 8137084862 | I55: Corporate | J55: West | K55: Ado-Ekiti | L55: Technology | M55: Tablets | N55: Amazon Fire HD 10 | O55: 12 | P55: 407237.85 | Q55: 0 | R55: 0 | S55: 4886854.2 | T55: 434362.1 | U55: =VALUE(S55) -> 4886854.2
A56: ORD-10871 | B56: 44632 | C56: 44633 | D56: Same Day | E56: Gbenga | F56: Otedola | G56: gbenga.otedola@hotmail.com | H56: 8137888843 | I56: Home Office | J56: East | K56: Onitsha | L56: Technology | M56: Laptops | N56: Lenovo IdeaPad 3 | O56: 1 | P56: 273141.64 | Q56: 25 | R56: 68285.41 | S56: 204856.23 | T56: 23898.11 | U56: =VALUE(S56) -> 204856.23
A57: ORD-10724 | B57: 44633 | C57: 44634 | D57: Same Day | E57: Chibundo | F57: Adeyemi | G57: chibundo.adeyemi@yahoo.com | H57: 7069679668 | I57: Home Office | J57: East | K57: Owerri | L57: Technology | M57: Accessories | N57: Belt Leather | O57: 4 | P57: 165634.79 | Q57: 15 | R57: 99380.87 | S57: 563158.29 | T57: 187041.85 | U57: =VALUE(S57) -> 563158.29
A58: ORD-10099 | B58: 44633 | C58: 44633 | D58: Same Day | E58: Tunde | F58: Abubakar | G58: tunde.abubakar@outlook.com | H58: 7037423230 | I58: Consumer | J58: South | K58: Lagos | L58: Food & Beverages | M58: Drinks | N58: Energy Drink 4-Pack | O58: 15 | P58: 1481.47 | Q58: 10 | R58: 2222.2 | S58: 19999.85 | T58: 1464.15 | U58: =VALUE(S58) -> 19999.85
A59: ORD-10364 | B59: 44637 | C59: 44643 | D59: Standard Class | E59: Wale | F59: Tinubu | G59: wale.tinubu@gmail.com | H59: 8141768424 | I59: Consumer | J59: South | K59: Port Harcourt | L59: Furniture | M59: Tables | N59: Office Desk 120cm | O59: 2 | P59: 37626.83 | Q59: 10 | R59: 7525.37 | S59: 67728.29 | T59: 23193.11 | U59: =VALUE(S59) -> 67728.29
A60: ORD-10050 | B60: 44637 | C60: 44638 | D60: Same Day | E60: Sade | F60: Osei | G60: sade.osei@outlook.com | H60: 7032944841 | I60: Home Office | J60: West | K60: Osogbo | L60: Clothing | M60: Accessories | N60: Belt Leather | O60: 18 | P60: 30279.4 | Q60: 20 | R60: 109005.84 | S60: 436023.36 | T60: 42707.85 | U60: =VALUE(S60) -> 436023.36
A61: ORD-10513 | B61: 44639 | C61: 44642 | D61: Second Class | E61: Deola | F61: Fashola | G61: deola.fashola@outlook.com | H61: 8105666187 | I61: Corporate | J61: South | K61: Ibadan | L61: Office Supplies | M61: Fasteners | N61: Stapler + Staples | O61: 14 | P61: 13261.39 | Q61: 10 | R61: 18565.95 | S61: 167093.51 | T61: 50183.29 | U61: =VALUE(S61) -> 167093.51
A62: ORD-10243 | B62: 44643 | C62: 44648 | D62: Second Class | E62: Chisom | F62: Olawale | G62: chisom.olawale@gmail.com | H62: 7065304875 | I62: Consumer | J62: East | K62: Owerri | L62: Food & Beverages | M62: Grains | N62: Rice 25kg Bag | O62: 12 | P62: 7317.29 | Q62: 25 | R62: 21951.87 | S62: 65855.61 | T62: 21843.65 | U62: =VALUE(S62) -> 65855.61
A63: ORD-10184 | B63: 44644 | C63: 44646 | D63: First Class | G63: chisom.okafor@gmail.com | H63: 9015164420 | I63: Home Office | J63: North | K63: Kaduna | L63: Office Supplies | M63: Envelopes | N63: C5 Envelopes | O63: 10 | P63: 1699.29 | Q63: 10 | R63: 1699.29 | S63: 15293.61 | T63: 5231.24 | U63: =VALUE(S63) -> 15293.61
A64: ORD-10967 | B64: 44645 | C64: 44646 | D64: Same Day | E64: Nike | F64: Tinubu | G64: nike.tinubu@hotmail.com | H64: 8106950477 | I64: Consumer | J64: east | K64: Aba | L64: Office Supplies | M64: Art Supplies | N64: Sketch Pad A3 | O64: 2 | P64: 21723.7 | Q64: 0 | R64: 0 | S64: 43447.4 | T64: 3995.75 | U64: =VALUE(S64) -> 43447.4
A65: ORD-10161 | B65: 44647 | C65: 44650 | D65: First Class | E65: Bukola | F65: Nwosu | G65: bukola.nwosu@hotmail.com | H65: 8065152891 | I65: Home Office | J65: North | K65: Abuja | L65: Office Supplies | M65: Art Supplies | N65: Watercolour Set | O65: 12 | P65: 11518.44 | Q65: 0 | R65: 0 | S65: 138221.28 | T65: 15680.09 | U65: =VALUE(S65) -> 138221.28
A66: ORD-10203 | B66: 44649 | C66: 44653 | D66: Second Class | E66: Sade | F66: Sowore | G66: sade.sowore@hotmail.com | H66: 8133480985 | I66: Consumer | J66: South | K66: Ibadan | L66: Food & Beverages | M66: Grains | N66: Garri 10kg | O66: 3 | P66: 7313.19 | Q66: 0 | R66: 0 | S66: 21939.57 | T66: 1817.9 | U66: =VALUE(S66) -> 21939.57
A67: ORD-10262 | B67: 44650 | C67: 44653 | D67: First Class | E67: Zainab | F67: Sule | G67: zainab.sule@hotmail.com | H67: 9027396087 | I67: Corporate | J67: West | K67: Ado-Ekiti | L67: Office Supplies | M67: Labels | N67: Colour Coding Dots | O67: 5 units | P67: 2894.06 | Q67: 10 | R67: 1447.03 | S67: 13023.27 | T67: 1774.87 | U67: =VALUE(S67) -> 13023.27
A68: ORD-10003 | B68: 44650 | C68: 44653 | D68: First Class | E68: Bukola | F68: Bello | G68: bukola.bello@hotmail.com | H68: 8065918715 | I68: Corporate | J68: North | K68: Abuja | L68: Food & Beverages | M68: Grains | N68: Beans 5kg | O68: 3 | P68: 1780.62 | Q68: 0 | R68: 0 | S68: 5341.86 | T68: 1318.15 | U68: =VALUE(S68) -> 5341.86
A69: ORD-10296 | B69: 44651 | C69: 44657 | D69: Standard Class | E69: Fatima | F69: Lawal | G69: fatima.lawal@gmail.com | H69: 8132796087 | I69: Home Office | J69: north | K69: Kano | L69: Clothing | M69: Trousers | N69: Men's Chinos | O69: 13 | P69: 3368.14 | Q69: 20 | R69: 8757.16 | S69: 35028.66 | T69: 5796.99 | U69: =VALUE(S69) -> 35028.66
A70: ORD-10815 | B70: 44651 | C70: 44653 | D70: First Class | E70: Seun | F70: Osei | G70: seun.osei@outlook.com | H70: 8106873992 | I70: Home Office | J70: Soth | K70: Ibadan | L70: Clothing | M70: Trousers | N70: Men's Chinos | O70: 5 | P70: 18826.41 | Q70: 10 | R70: 9413.2 | S70: 84718.85 | T70: 12992.21 | U70: =VALUE(S70) -> 84718.85
A71: ORD-10503 | B71: 44651 | C71: 44651 | D71: Same Day | E71: Aisha | F71: Chukwu | G71: aisha.chukwu@outlook.com | H71: 9072119776 | I71: Consumer | J71: South | L71: Furniture | M71: Storage | N71: Storage Box Set | O71: 18 | P71: 178691.03 | Q71: 0 | R71: 0 | S71: $3,216,438.54 | T71: 1438358.6 | U71: =VALUE(S71) -> #VALUE!
A72: ORD-10077 | B72: 44655 | C72: 44657 | D72: First Class | E72: Ikenna | F72: Alakija | G72: ikenna.alakija@gmail.com | H72: 8034429650 | I72: Corporate | J72: East | K72: Awka | L72: Office Supplies | M72: Binders | N72: Lever Arch File | O72: 10 | P72: 19221.94 | Q72: 10 | R72: 19221.94 | S72: 172997.46 | T72: -13495.43 | U72: =VALUE(S72) -> 172997.46
A73: ORD-10166 | B73: 44656 | C73: 44661 | D73: Standard Class | E73: Adebayo | F73: Okonkwo | G73: adebayo.okonkwo@gmail.com | H73: 8033650523 | I73: Home Office | J73: West | K73: Osogbo | L73: Clothing | M73: Bags | N73: Laptop Backpack | O73: 14 | P73: 44649.04 | Q73: 5 | R73: 31254.33 | S73: 593832.23 | T73: 265690.3 | U73: =VALUE(S73) -> 593832.23
A74: ORD-10092 | B74: 44659 | C74: 44665 | D74: Standard Class | G74: chibundo.tinubu@hotmail.com | H74: 8062859886 | I74: Corporate | J74: East | K74: Onitsha | L74: Clothing | M74: Accessories | N74: Wallet Genuine Leather | O74: 17 | P74: 2706.72 | Q74: 5 | R74: 2300.71 | S74: 43713.53 | T74: 12289.04 | U74: =VALUE(S74) -> 43713.53
A75: ORD-10997 | B75: 44659 | C75: 44661 | D75: First Class | E75: Ikenna | F75: Eze | G75: ikenna.eze@gmail.com | H75: 8032585719 | I75: Home Office | J75: North | K75: Kaduna | L75: Clothing | M75: Shoes | N75: Sneakers Unisex | O75: 8 | P75: 44781.94 | Q75: 20 | R75: 71651.1 | S75: 286604.42 | T75: -7757.18 | U75: =VALUE(S75) -> 286604.42
A76: ORD-10971 | B76: 44660 | C76: 44666 | D76: Standard Class | E76: Hauwa | F76: Danjuma | G76: hauwa.danjuma@gmail.com | H76: 9074321723 | I76: Corporate | J76: West | K76: Ado-Ekiti | L76: Clothing | M76: Trousers | N76: Women's Palazzo | O76: 11 | P76: 19414.76 | Q76: 5 | R76: 10678.12 | S76: 202884.24 | T76: -25659.44 | U76: =VALUE(S76) -> 202884.24
A77: ORD-10221 | B77: 44660 | C77: 44665 | D77: Standard Class | E77: Amara | F77: Adeleke | G77: N/A | H77: 7068454356 | I77: Home Office | J77: East | K77: Awka | L77: Clothing | M77: Shirts | N77: Ankara Print Shirt | O77: 5 | P77: 12867.75 | Q77: 5 | R77: 3216.94 | S77: 61121.81 | T77: 16326.57 | U77: =VALUE(S77) -> 61121.81
A78: ORD-10762 | B78: 44660 | C78: 44660 | D78: Same Day | E78: Dayo | F78: Adebayo | G78: dayo.adebayo@gmail.com | H78: 9058335114 | I78: Corporate | J78: West | K78: Akure | L78: Technology | M78: Printers | N78: Epson EcoTank | O78: 16 | P78: 358709.81 | Q78: 10 | R78: 573935.7 | S78: 5165421.3 | T78: 1006685.2 | U78: =VALUE(S78) -> 5165421.3
A79: ORD-10899 | B79: 44661 | C79: 44665 | D79: Second Class | E79: Seun | F79: Lawal | G79: seun.lawal@yahoo.com | H79: 8137160440 | I79: Consumer | J79: north | K79: Sokoto | L79: Food & Beverages | M79: Grains | N79: Oats 1kg | O79: 6 | P79: 2192.57 | Q79: 0 | R79: 0 | S79: 13155.42 | T79: 3657.97 | U79: =VALUE(S79) -> 13155.42
A80: ORD-10872 | B80: 44661 | C80: 44662 | D80: Same Day | E80: Lanre | F80: Bello | G80: lanre.bello@hotmail.com | H80: 8108578703 | I80: Corporate | J80: South | K80: Warri | L80: Office Supplies | M80: Art Supplies | N80: Acrylic Paint Kit | O80: 20 | P80: 1475.5 | Q80: 10 | R80: 2951 | S80: 26559 | T80: 2816.29 | U80: =VALUE(S80) -> 26559
A81: ORD-10992 | B81: 44665 | C81: 44670 | D81: Second Class | E81: Uchenna | F81: Abubakar | G81: uchenna.abubakar@outlook.com | H81: 8161282157 | I81: Home Office | J81: West | K81: Akure | L81: Clothing | M81: Bags | N81: Gym Duffel Bag | O81: 13 | P81: 27749.94 | Q81: 0 | R81: 0 | S81: 360749.22 | T81: -41518.92 | U81: =VALUE(S81) -> 360749.22
A82: ORD-10337 | B82: 44665 | C82: 44665 | D82: Same Day | E82: Chidinma | F82: Adeleke | G82: chidinma.adeleke@gmail.com | H82: 7067575272 | I82: CONSUMER | J82: North | L82: Furniture | M82: Sofas | N82: Recliner Chair | O82: 15 | P82: 116268.96 | Q82: 10 | R82: 174403.44 | S82: 1569631 | T82: 58805.27 | U82: =VALUE(S82) -> 1569631
A83: ORD-10914 | B83: 44667 | C83: 44670 | D83: Second Class | E83: Kunle | F83: Adeyemi | G83: kunle.adeyemi@gmail.com | H83: 8105889267 | I83: Home Office | J83: West | K83: Abeokuta | L83: Office Supplies | M83: Fasteners | N83: Binder Clips Asst. | O83: 3 | P83: 16818.43 | Q83: 0 | R83: 0 | T83: -2566.51 | U83: =VALUE(S83) -> 0
A84: ORD-10606 | B84: 44667 | C84: 44668 | D84: Same Day | E84: Kemi | F84: Tinubu | G84: kemi.tinubu@hotmail.com | H84: 9013914492 | I84: Home Office | J84: West | K84: Ilorin | L84: Clothing | M84: Shoes | N84: Sandals | O84: 8 | P84: 8813.08 | Q84: 0 | R84: 0 | S84: 70504.64 | T84: 19460.33 | U84: =VALUE(S84) -> 70504.64
A85: ORD-10979 | B85: 44668 | C85: 44671 | D85: First Class | E85: Dayo | F85: Otedola | G85: dayo.otedola@yahoo.com | H85: 7062824919 | I85: Corporate | J85: South | K85: Benin City | L85: Clothing | M85: Bags | N85: Gym Duffel Bag | O85: 5 | P85: 34811.24 | Q85: 5 | R85: 8702.81 | S85: 165353.39 | T85: 72813.68 | U85: =VALUE(S85) -> 165353.39
A86: ORD-10621 | B86: 44669 | C86: 44676 | D86: Standard Class | E86: Emeka | F86: Bello | G86: emeka.bello@gmail.com | H86: 8162258998 | I86: Home Office | J86: South | K86: Benin City | L86: Office Supplies | M86: Pens & Pencils | N86: Highlighters Set | O86: 13 | P86: 19894.88 | Q86: 10 | R86: 25863.34 | S86: 232770.1 | T86: 62661.45 | U86: =VALUE(S86) -> 232770.1
A87: ORD-10464 | B87: 44670 | C87: 44675 | D87: Second Class | E87: Ronke | F87: Nwosu | G87: ronke.nwosu@hotmail.com | H87: 8151313131 | I87: Consumer | J87: North | K87: Katsina | L87: Technology | M87: Printers | N87: Canon PIXMA G3411 | O87: 9 | P87: 433633.89 | Q87: 5 | R87: 195135.25 | S87: 3707569.8 | T87: -10484.95 | U87: =VALUE(S87) -> 3707569.8
A88: ORD-10904 | B88: 44670 | C88: 44673 | D88: First Class | E88: Adebayo | F88: Olawale | G88: adebayo.olawale@hotmail.com | H88: 8065931680 | I88: Corporate | J88: South | K88: Lagos | L88: Office Supplies | M88: Art Supplies | N88: Craft Scissors | O88: 2 | P88: 14014.36 | Q88: 20 | R88: 5605.74 | S88: 22422.98 | T88: -2451.88 | U88: =VALUE(S88) -> 22422.98
A89: ORD-10310 | B89: 44670 | C89: 44673 | D89: First Class | E89: Chidi | F89: Musa | G89: chidi.musa@hotmail.com | H89: 9075551832 | I89: Consumer | J89: North | K89: Abuja | L89: Officce Supplies | M89: Art Supplies | N89: Watercolour Set | O89: 13 | P89: 967.42 | Q89: 5 | R89: 628.82 | S89: 11947.64 | T89: 5231.58 | U89: =VALUE(S89) -> 11947.64
A90: ORD-10344 | B90: 44670 | C90: 44672 | D90: First Class | E90: Taiwo | F90: Gambo | G90: taiwo.gambo@outlook.com | H90: 8065734685 | I90: Consumer | J90: South | K90: Benin City | L90: Technology | M90: Phones | N90: Infinix Note 30 | O90: 13 | P90: 320466.52 | Q90: 10 | R90: 416606.48 | S90: 3749458.3 | T90: 1038840.6 | U90: =VALUE(S90) -> 3749458.3
A91: ORD-10641 | B91: 44671 | C91: 44674 | D91: First Class | E91: Kemi | F91: Olawale | G91: kemi.olawale@gmail.com | H91: 8149690736 | I91: Home Office | J91: East | K91: Onitsha | L91: Clothing | M91: Shirts | N91: Men's Polo Shirt | O91: 4 | P91: 4351.79 | Q91: 10 | R91: 1740.72 | S91: 15666.44 | T91: 3236.75 | U91: =VALUE(S91) -> 15666.44
A92: ORD-10274 | B92: 44672 | C92: 44677 | D92: Second Class | E92: Oluwaseun | F92: Sanusi | G92: oluwaseun.sanusi@gmail.com | H92: 8156826541 | I92: Consumer | J92: East | K92: Owerri | L92: Clothing | M92: Trousers | N92: Formal Trousers | O92: 17 | P92: 43989.81 | Q92: 20 | R92: 149565.35 | S92: 598261.42 | T92: 23565.97 | U92: =VALUE(S92) -> 598261.42
A93: ORD-10689 | B93: 44673 | C93: 44676 | D93: First Class | E93: Wale | F93: Atiku | G93: wale.atiku@yahoo.com | H93: 7031765519 | I93: Corporate | J93: West | K93: Akure | L93: Office Supplies | M93: Envelopes | N93: Brown Kraft Envelopes | O93: 6 | P93: 5922.1 | Q93: 25 | R93: 8883.15 | S93: 26649.45 | T93: -700.33 | U93: =VALUE(S93) -> 26649.45
A94: ORD-10480 | B94: 44674 | C94: 44675 | D94: Same Day | E94: Ayo | F94: Tinubu | G94: ayo.tinubu@hotmail.com | H94: 8062708383 | I94: Consumer | J94: North | K94: Kaduna | L94: Technology | M94: Printers | N94: HP DeskJet 2710 | O94: 13 | P94: 143288.8 | Q94: 15 | R94: 279413.16 | S94: 1583341.2 | U94: =VALUE(S94) -> 1583341.2
A95: ORD-10141 | B95: 44676 | C95: 44676 | D95: Same Day | E95: Aisha | F95: Musa | G95: aisha.musa@hotmail.com | H95: 8038279795 | I95: Home Office | J95: West | K95: Akure | M95: Labels | N95: Address Labels A4 | O95: 2 | P95: 22422.38 | Q95: 5 | R95: 2242.24 | S95: 42602.52 | T95: -986.24 | U95: =VALUE(S95) -> 42602.52
A96: ORD-10289 | B96: 44676 | C96: 44673 | D96: Second Class | E96: Ikenna | F96: Musa | G96: ikenna.musa@hotmail.com | H96: 8104224451 | I96: Consumer | J96: North | L96: Office Supplies | M96: Art Supplies | N96: Coloured Pencils 24 | O96: 4 | P96: 20792.18 | Q96: 5 | R96: 4158.44 | S96: 79010.28 | T96: 6390.25 | U96: =VALUE(S96) -> 79010.28
A97: ORD-10267 | B97: 44679 | C97: 44681 | D97: First Class | E97: Wale | F97: Fashola | G97: wale.fashola@gmail.com | H97: 8139693169 | I97: Home Office | J97: West | K97: Ado-Ekiti | L97: Office Supplies | M97: Binders | N97: Ring Binder A4 | O97: 17 | P97: 19707.01 | Q97: 25 | R97: 83754.79 | S97: 251264.38 | T97: 67607.67 | U97: =VALUE(S97) -> 251264.38
A98: ORD-10555 | B98: 44679 | C98: 44680 | D98: Same Day | E98: Chidi | F98: Alakija | G98: chidi.alakija@hotmail.com | H98: 7036005493 | I98: Home Office | J98: North | K98: Sokoto | L98: Office Supplies | M98: Paper | N98: A4 Paper 500 Sheets | O98: 6 | P98: 9068.18 | Q98: 15 | R98: 8161.36 | S98: 46247.72 | T98: 2900.63 | U98: =VALUE(S98) -> 46247.72
A99: ORD-10326 | B99: 44681 | C99: 44684 | D99: Second Class | E99: Kehinde | F99: Atiku | G99: kehinde.atiku@gmail.com | H99: 8145818203 | I99: Consmer | J99: West | K99: Ado-Ekiti | L99: Clothing | M99: Accessories | N99: Wristwatch | O99: 19 | P99: 13165.38 | Q99: 10 | R99: 25014.22 | S99: 225128 | T99: 91461.23 | U99: =VALUE(S99) -> 225128
A100: ORD-10782 | B100: 44683 | C100: 44691 | D100: Standard Class | E100: Kemi | F100: Okafor | G100: kemi.okafor@hotmail.com | H100: 8033688598 | I100: Home Office | J100: South | K100: Port Harcourt | L100: Furniture | M100: Storage | N100: Filing Cabinet | O100: 13 | P100: 119126.56 | Q100: 5 | R100: 77432.26 | S100: 1471213 | T100: -1259.39 | U100: =VALUE(S100) -> 1471213
...

Sheet Raw Data (2)
A1: Order ID | B1: Order Date | C1: Ship Date | D1: Ship Mode | E1: Customer Name | F1: Email | G1: Phone | H1: Segment | I1: Region | J1: State | K1: Category | L1: Sub-Category | M1: Product Name | N1: Quantity | O1: Unit Price (₦) | P1: Discount (%) | Q1: Discount Amount (₦) | R1: Sales (₦) | S1: Profit (₦)
A2: ORD-10001 | B2: 45063 | C2: 45065 | D2: First Class | E2: Kemi Atiku | F2: kemi.atiku@gmail.com | G2: 080 | H2: Home Office | I2: North | J2: Kano | K2: Food & Beverages | L2: Cooking Oil | M2: Vegetable Oil 5L | N2: 7 | O2: 529.44 | P2: 5% | Q2: 185.3 | R2: 3520.78 | S2: 539.43
A3: ORD-10002 | B3: 45013 | C3: 45014 | D3: Same Day | E3: Lanre Chukwu | F3: lanre.chukwu@gmail.com | G3: 9023678638 | H3: Consumer | I3: North | J3: Katsina | K3: clothing | L3: Shoes | M3: Sneakers Unisex | N3: 11 | O3: 8685.62 | P3: 0 | Q3: 0 | R3: 95541.82 | S3: -9014.61
A4: ORD-10003 | B4: 44650 | C4: 44653 | D4: First Class | E4: Bukola Bello | F4: bukola.bello@hotmail.com | G4: 8065918715 | H4: Corporate | I4: North | J4: Abuja | K4: Food & Beverages | L4: Grains | M4: Beans 5kg | N4: 3 | O4: 1780.62 | P4: 0 | Q4: 0 | R4: 5341.86 | S4: 1318.15
A5: ORD-10004 | B5: 45340 | C5: 45347 | D5: Standard Class | E5: Adebayo Tinubu | F5: adebayo.tinubu@outlook.com | G5: 8107210606 | H5: Consumer | I5: East | J5: Enugu | K5: office supplies | L5: Binders | M5: Clipboard | N5: 3 | O5: 17694.6 | P5: 0 | Q5: 0 | R5: 53083.8 | S5: 9049.93
A6: ORD-10005 | B6: 45114 | C6: 45114 | D6: Same Day | E6: Chisom Gambo | F6: chisom.gambo@gmail.com | G6: 00000000000 | H6: corporate | I6: South | J6: Ibadan | K6: Office Supplies | L6: Envelopes | M6: Padded Envelopes | N6: 19 | O6: 2121.62 | P6: 10 | Q6: 4031.08 | R6: 36279.7 | S6: -813.54
A7: ORD-10006 | B7: 44854 | C7: 44855 | D7: Same Day | E7: Kemi Abubakar | F7: kemi.abubakar@outlook.com | G7: 9018187926 | H7: Home Office | I7: West | J7: Akure | K7: Food & Beverages | L7: Cooking Oil | M7: Groundnut Oil 3L | N7: 5 | O7: 1988.77 | P7: 25 | Q7: 2485.96 | R7: 7457.89
A8: ORD-10007 | B8: 45426 | C8: 45431 | D8: Second Class | E8: Tunde Olawale | F8: tunde.olawale@hotmail.com | G8: 9058852574 | H8: Consumer | I8: North | J8: Kano | K8: Food & Beverages | L8: Grains | M8: Beans 5kg | N8: 1 | O8: 6928 | P8: 0 | Q8: 0 | R8: 6928 | S8: 1794.53
A9: ORD-10008 | B9: 45452 | C9: 45454 | D9: First Class | E9: Adebayo Okonkwo | F9: adebayo.okonkwo@outlook.com | G9: 8153997281 | H9: Consumer | I9: East | K9: Food & Beverages | L9: Drinks | M9: Water 5L x6 | N9: 17 | O9: 6780.85 | P9: 5 | Q9: 5763.72 | R9: 109510.73 | S9: -6384.09
A10: ORD-10009 | B10: 45225 | C10: 45233 | D10: Standard Class | E10: Amara Bello | F10: amara.bello@outlook.com | G10: 8036159230 | H10: Home Office | I10: South | J10: Port Harcourt | K10: Furniture | L10: Chairs | M10: Mesh Office Chair | N10: 3 | O10: 159017.65 | P10: 0 | Q10: 0 | R10: 477052.95 | S10: 137937.26
A11: ORD-10010 | B11: 45535 | C11: 45540 | D11: Second Class | E11: Aisha Chukwu | F11: aisha.chukwu@hotmail.com | G11: 8134374754 | H11: Consumer | I11: North | J11: Katsina | K11: Office Supplies | L11: Envelopes | M11: Padded Envelopes | N11: 17 | O11: 11233.45 | P11: 20 | Q11: 38193.73 | R11: 152774.92 | S11: -11824.39
A12: ORD-10011 | B12: 45033 | C12: 45039 | D12: Standard Class | E12: Chidi Musa | F12: chidi.musa@gmail.com | G12: +234 803 123 4567 | H12: Corporate | I12: South | J12: Lagos | K12: Technology | L12: Tablets | M12: iPad 10th Gen | N12: 9 | O12: 238657.91 | P12: 20 | Q12: 429584.24 | R12: 1718336.95 | S12: -36871.93
A13: ORD-10012 | B13: 45059 | C13: 45060 | D13: Same Day | E13: Chibundo Nwosu | F13: chibundo.nwosu@gmail.com | G13: 8068231838 | H13: Home Office | I13: South | J13: Port Harcourt | K13: Office Supplies | L13: Envelopes | M13: Brown Kraft Envelopes | N13: 2 | O13: 11942.1 | P13: 0 | Q13: 0 | R13: 23884.2 | S13: -2714.02
A14: ORD-10013 | B14: 44951 | C14: 44956 | D14: Second Class | E14: Olumide Okafor | F14: olumide.okafor@hotmail.com | G14: 8105673212 | H14: Consumer | I14: East | J14: Enugu | K14: Clothing | L14: Trousers | M14: Men's Chinos | N14: 18 | O14: 21054.62 | P14: 0 | Q14: 0 | R14: 378983.16 | S14: -45344.2
A15: ORD-10014 | B15: 45394 | C15: 45398 | D15: Second Class | E15: Kunle Nwosu | F15: kunle.nwosu@hotmail.com | G15: 8033762152 | H15: Consumer | I15: North | J15: Kano | K15: Clothing | L15: Shirts | M15: T-Shirt 3-Pack | N15: 15 | O15: 13403.73 | P15: 10 | Q15: 20105.59 | R15: 180950.36 | S15: 18783.46
A16: ORD-10015 | B16: 45007 | C16: 45009 | D16: First Class | E16: Lanre Atiku | F16: lanre.atiku@gmail.com | G16: 9016261415 | H16: Consumer | I16: West | J16: Ilorin | K16: Technology | L16: Laptops | M16: Acer Aspire 5 | N16: 17 | O16: 222403 | P16: 0 | Q16: 0 | R16: 3780851 | S16: -438095.72
A17: ORD-10016 | B17: 45043 | C17: 45051 | D17: Standard Class | E17: Bola Danjuma | F17: bola.danjuma@yahoo.com | G17: 9051666754 | H17: CONSUMER | I17: North | J17: Kaduna | K17: Food & Beverages | L17: Drinks | M17: Fruit Juice 1L | N17: 19 | O17: 5361.77 | P17: 25 | Q17: 25468.41 | R17: 76405.22 | S17: 3042.6
A18: ORD-10017 | B18: 45050 | C18: 45053 | D18: First Class | E18: Ikenna Okafor | F18: ikenna.okafor@outlook.com | G18: 8146304573 | H18: Home Office | I18: East | J18: Onitsha | K18: Technolgy | L18: Laptops | M18: Asus VivoBook 14 | N18: 19 | O18: 285204.28 | P18: 0 | Q18: 0 | R18: 5418881.3 | S18: -574637.51
A19: ORD-10018 | B19: 45276 | C19: 45279 | D19: Second Class | E19: Hauwa Adebayo | F19: hauwa.adebayo@outlook.com | G19: 8108351517 | H19: Corporate | I19: South | J19: Port Harcourt | K19: Food & Beverages | L19: Grains | M19: Beans 5kg | N19: 17 | O19: 7875.67 | P19: 0 | Q19: 0 | R19: 133886.39 | S19: 33567.72
A20: ORD-10019 | B20: 44798 | C20: 44800 | D20: First Class | E20: Taiwo Okafor | F20: taiwo.okafor@outlook.com | G20: 8164533779 | H20: Consumer | I20: East | J20: Enugu | K20: Office Supplies | L20: Binders | M20: Clipboard | N20: 9 units | O20: 12882.52 | P20: 0 | Q20: 0 | R20: 115942.68 | S20: -10970.6
A21: ORD-10020 | B21: 45245 | C21: 45251 | D21: Standard Class | E21: Tobi Adeyemi | F21: tobi.adeyemi@hotmail.com | G21: 8158175395 | H21: Consumer | I21: West | J21: Osogbo | K21: Food & Beverages | L21: Drinks | M21: Coca-Cola 24-Pack | N21: 5 | O21: 879.38 | P21: 25 | Q21: 1099.22 | R21: 3297.68 | S21: -423.37
A22: ORD-10021 | B22: 45442 | C22: 45445 | D22: Second Class | E22: Emeka Eze | F22: emeka.eze@outlook.com | G22: 9021669324 | H22: Home Office | I22: East | J22: Awka | K22: Office Supplies | L22: Binders | M22: Lever Arch File | N22: -1 | O22: 16839.87 | P22: 25 | Q22: 50519.61 | R22: 151558.83 | S22: 57665.23
A23: ORD-10022 | B23: 45046 | C23: 45049 | D23: Second Class | E23: Fatima Ogundipe | F23: fatima.ogundipe@gmail.com | G23: 8106573147 | H23: Home Office | I23: WSET | J23: Ado-Ekiti | K23: cLOTHING | L23: Trousers | M23: Joggers | N23: 4 | O23: 8845.51 | P23: 15 | Q23: 5307.31 | R23: 30074.73 | S23: 11226.9
A24: ORD-10023 | B24: 45278 | C24: 45279 | D24: Same Day | E24: Zainab Abubakar | F24: zainab.abubakar@gmail.com | G24: 9074240180 | H24: Consumer | I24: West | J24: Ilorin | K24: Clothing | L24: Shoes | M24: Sneakers Unisex | N24: 9 | O24: 39167.18 | P24: 10% | Q24: 35250.46 | R24: 317254.16 | S24: 74519.53
A25: ORD-10024 | B25: 44798 | C25: 44805 | D25: Standard Class | E25: Fatima Danjuma | F25: fatima.danjuma@outlook.com | G25: 8032818692 | H25: Corporate | I25: West | J25: Ado-Ekiti | K25: Food & Beverages | L25: Cooking Oil | M25: Groundnut Oil 3L | N25: 11 | O25: 5909.8 | P25: 15 | Q25: 9751.17 | R25: 55256.63 | S25: 11809.74
A26: ORD-10025 | B26: 45083 | C26: 45086 | D26: Second Class | E26: Oluwaseun Okonkwo | F26: oluwaseun.okonkwo@yahoo.com | G26: 7038235969 | H26: Home Office | I26: North | J26: Sokoto | K26: Technology | L26: Tablets | M26: Amazon Fire HD 10 | N26: 4 | O26: 151553.31 | P26: 10 | Q26: 60621.32 | S26: 84170.38
A27: ORD-10026 | B27: 44822 | C27: 44824 | D27: First Class | E27: Chibundo Sowore | F27: chibundo.sowore@hotmail.com | G27: 9073919694 | H27: Corporate | I27: West | J27: Osogbo | K27: Food & Beverages | L27: Condiments | M27: Soy Sauce 500ml | N27: 1 | O27: 3426.78 | P27: 10 | Q27: 342.68 | R27: 3084.1 | S27: 68.31
A28: ORD-10027 | B28: 45514 | C28: 45517 | D28: First Class | E28: Olumide Sowore | F28: olumide.sowore@yahoo.com | G28: 8158938746 | H28: Home Office | I28: West | J28: Ado-Ekiti | K28: Furniture | L28: Chairs | M28: Visitor Chair | N28: 20 | O28: 96657.75 | P28: 10 | Q28: 193315.5 | R28: 1739839.5 | S28: -163488.68
A29: ORD-10028 | B29: 44863 | C29: 44866 | D29: Second Class | E29: Emeka Abubakar | F29: emeka.abubakar@hotmail.com | G29: 9052221854 | H29: Consumer | I29: South | J29: Benin City | K29: Clothing | L29: Bags | M29: Crossbody Bag | N29: 13 units | O29: 10360.72 | P29: 20 | Q29: 26937.87 | R29: 107751.49 | S29: 9675.19
A30: ORD-10029 | B30: 45010 | C30: 45010 | D30: Same Day | E30: Ronke Fashola | F30: ronke.fashola@gmail.com | G30: 8155180853 | H30: Consumer | I30: South | J30: Lagos | K30: Technology | L30: Accessories | M30: Sunglasses UV400 | N30: 17 | O30: 363616.22 | P30: 25 | Q30: 1545368.9 | R30: 4636106.8 | S30: 960932.31
A31: ORD-10030 | B31: 45475 | C31: 45475 | D31: Same Day | E31: Kunle Fashola | F31: kunle.fashola@outlook.com | G31: 9025147994 | H31: Home Office | I31: West | J31: Ado-Ekiti | K31: Office Supplies | L31: Art Supplies | M31: Craft Scissors | N31: 8 | O31: 12372.63 | P31: 10% | Q31: 9898.1 | R31: 89082.94 | S31: 10148.65
A32: ORD-10031 | B32: 45216 | C32: 45218 | D32: First Class | E32: Kemi Okafor | F32: kemi.okafor@yahoo.com | G32: 7063563646 | H32: Corporate | I32: East | J32: Onitsha | K32: Furniture | L32: Chairs | M32: Bar Stool | N32: 18 | O32: 78107.09 | P32: 20 | Q32: 281185.52 | R32: 1124742.1 | S32: 111871.96
A33: ORD-10032 | B33: 45341 | C33: 45349 | D33: Standard Class | E33: Chidi Adebayo | F33: chidi.adebayo@outlook.com | G33: 9027542890 | H33: Corporate | I33: South | J33: Warri | K33: Clothing | L33: Accessories | M33: Wallet Genuine Leather | N33: 8 | O33: 36394.33 | P33: 20 | Q33: 58230.93 | R33: 232923.71 | S33: -4273.46
A34: ORD-10033 | B34: 45250 | C34: 45251 | D34: Same Day | E34: Aisha Gambo | F34: aisha.gambo@hotmail.com | G34: 8109961107 | H34: Consumer | I34: West | J34: Akure | K34: Technology | L34: Accessories | M34: Wallet Genuine Leather | N34: 1 | O34: 260510.51 | P34: 0 | Q34: 0 | R34: 260510.51 | S34: 61389.25
A35: ORD-10034 | B35: 45094 | C35: 45102 | D35: STANDARD CLASS | E35: Chisom Nwosu | F35: chisom.nwosu@hotmail.com | G35: 7036662319 | H35: Consumer | I35: South | J35: Warri | K35: Clothing | L35: Shoes | M35: Leather Loafers | N35: 3 | O35: 12847.68 | P35: 20 | Q35: 7708.61 | R35: 30834.43 | S35: -4266.56
A36: ORD-10035 | B36: 03/24/2022 | C36: 44649 | D36: Standard Class | E36: Hauwa Nwosu | F36: hauwa.nwosu@gmail.com | G36: 9053556551 | H36: Consumer | I36: North | J36: Abuja | K36: Furniture | L36: Tables | M36: Dining Table 6-Seater | N36: 19 | O36: 123146.92 | P36: 5 | Q36: 116989.57 | R36: 2222801.9 | S36: 286786.77
A37: ORD-10036 | B37: 44897 | C37: 44904 | D37: Standard Class | E37: Yemi Danjuma | F37: spaces in@email.com | G37: 8167296605 | H37: Consumer | I37: East | J37: Aba | K37: Clothing | L37: Trousers | M37: Men's Chinos | N37: 8 | O37: 27460.21 | P37: 0 | Q37: 0 | R37: 219681.68 | S37: 58944.07
A38: ORD-10037 | B38: 45273 | C38: 45281 | D38: Standard Class | E38: Uchenna Musa | F38: uchenna.musa@outlook.com | G38: 8038047416 | H38: Consumer | I38: East | J38: Awka | K38: Clothing | L38: Shirts | M38: T-Shirt 3-Pack | N38: 15 | O38: 43313.87 | P38: 0 | Q38: 0 | R38: 649708.05 | S38: 72307.49
A39: ORD-10038 | B39: 45514 | C39: 45515 | D39: Same Day | E39: Lanre Chukwu | F39: lanre.chukwu@outlook.com | G39: 8035118725 | H39: Home Office | I39: East | J39: Awka | K39: Technology | L39: Tablets | M39: Huawei MatePad | N39: 15 | O39: 121080.6 | P39: 15 | Q39: 272431.35 | R39: 1543777.6 | S39: 80026.3
A40: ORD-10039 | B40: 44996 | C40: 44997 | D40: Same Day | E40: Tobi Osei | F40: tobi.osei@outlook.com | G40: 9055635017 | H40: Consumer | I40: West | J40: Osogbo | K40: Food & Beverages | L40: Drinks | M40: Energy Drink 4-Pack | N40: 3 | O40: 7600.08 | P40: 5 | Q40: 1140.01 | S40: 6109.16
A41: ORD-10901 | B41: 45076 | C41: 45077 | D41: Same Day | E41: Aisha Dangote | F41: aisha.dangote@hotmail.com | G41: 8101610970 | H41: Home Office | I41: East | J41: Awka | K41: Furniture | L41: Chairs | M41: Gaming Chair | N41: 10 | O41: 179090.91 | P41: 0 | Q41: 0 | R41: 1790909.1 | S41: 380814.35
A42: ORD-10040 | B42: 45567 | C42: 45568 | D42: Same Day | E42: Amara Musa | F42: amara.musa@outlook.com | G42: 8137784725 | H42: Consumer | I42: West | J42: Ado-Ekiti | K42: Furniture | L42: Bookcases | M42: Metal Bookcase | N42: 18 | O42: 71471.52 | P42: 25 | Q42: 321621.84 | R42: 964865.52 | S42: 54277.97
A43: ORD-10041 | B43: 45116 | C43: 45117 | D43: Same Day | E43: Tobi Abubakar | F43: tobi.abubakar@gmail.com | G43: 9014231028 | H43: Home Office | I43: East | J43: Aba | K43: Office Supplies | L43: Paper | M43: Graph Paper Pad | N43: 6 | O43: 23796.5 | P43: 5 | Q43: 7138.95 | R43: 135640.05 | S43: -2735.75
A44: ORD-10042 | B44: 44767 | C44: 44769 | D44: First Class | E44: Nike Abubakar | F44: nike.abubakar@outlook.com | G44: 8106071208 | H44: Home Office | I44: West | J44: Osogbo | K44: Technology | L44: Printers | M44: Canon PIXMA G3411 | N44: 2 | O44: 134325.43 | P44: 25 | Q44: 67162.71 | R44: 201488.15 | S44: 5094.02
A45: ORD-10043 | B45: 45144 | C45: 45152 | D45: Standard Class | E45: Kunle Fashola | F45: kunle.fashola@outlook.com | G45: 8101861958 | H45: Consumer | I45: South | J45: Warri | K45: Office Supplies | L45: Art Supplies | M45: Coloured Pencils 24 | N45: 3 | O45: 3295.13 | P45: 15 | Q45: 1482.81 | R45: 8402.58 | S45: 1218.78
A46: ORD-10044 | B46: 44736 | C46: 44738 | D46: Frist Class | E46: Bola Otedola | F46: bola.otedola@hotmail.com | G46: 9054786401 | H46: Consumer | I46: North | K46: Food & Beverages | L46: Cooking Oil | M46: Coconut Oil 1L | N46: 10 | O46: 7295.48 | P46: 15 | Q46: 10943.22 | R46: 62011.58 | S46: 2060.53
A47: ORD-10045 | B47: 44987 | C47: 44993 | D47: Standard Class | E47: Tobi Sowore | F47: tobi.sowore@gmail.com | G47: 8105024269 | H47: Home Office | I47: North | J47: Katsina | K47: Furniture | L47: Sofas | M47: 3-Seater Sofa | N47: 14 | O47: 34923.61 | P47: 20 | Q47: 97786.11 | R47: 391144.43 | S47: 103114.54
A48: ORD-10046 | B48: 45152 | C48: 45157 | D48: Second Class | E48: Nike Obi | F48: nike.obi@hotmail.com | G48: 8064916201 | H48: Consumer | I48: West | J48: Osogbo | K48: Office Supllies | L48: Art Supplies | M48: Craft Scissors | N48: 7 | O48: 16698.98 | P48: 15 | Q48: 17533.93 | R48: 99358.93 | S48: -8061.41
A49: ORD-10047 | B49: 44708 | C49: 44711 | D49: Second Class | E49: Aisha Sule | F49: aisha.sule@outlook.com | G49: 9055842082 | H49: Corporate | I49: South | J49: Ibadan | K49: Clothing | L49: Shirts | M49: T-Shirt 3-Pack | N49: 13 | O49: 31613.15 | P49: 10 | Q49: 41097.1 | R49: 369873.85 | S49: 55585.87
A50: ORD-10048 | B50: 45446 | C50: 45453 | D50: Standard Class | E50: Deola Chukwu | F50: deola.chukwu@gmail.com | G50: 8064840714 | H50: Consumer | I50: West | J50: Akure | K50: Food & Beverages | L50: Condiments | M50: Tomato Paste 400g | N50: -1 | O50: 7996.71 | P50: 0 | Q50: 0 | R50: 71970.39 | S50: 22157.19
A51: ORD-10049 | B51: 45131 | C51: 45131 | D51: Same Day | E51: Lanre Ogundipe | F51: lanre.ogundipe@hotmail.com | G51: 8068885465 | H51: Home Office | I51: South | J51: Warri | K51: Office Supplies | L51: Envelopes | M51: Padded Envelopes | N51: 4 | O51: ₦8,365.93 | P51: 0 | Q51: 0 | R51: 33463.72 | S51: 1602.32
A52: ORD-10050 | B52: 44637 | C52: 44638 | D52: Same Day | E52: Sade Osei | F52: sade.osei@outlook.com | G52: 7032944841 | H52: Home Office | I52: West | J52: Osogbo | K52: Clothing | L52: Accessories | M52: Belt Leather | N52: 18 | O52: 30279.4 | P52: 20 | Q52: 109005.84 | R52: 436023.36 | S52: 42707.85
A53: ORD-10051 | B53: 45467 | C53: 45467 | D53: Same Day | E53: Ibrahim Chukwu | F53: ibrahim.chukwu@yahoo.com | G53: 8168350368 | H53: Corporate | I53: South | J53: Port Harcourt | K53: Clothing | L53: Shirts | M53: Men's Polo Shirt | N53: 20 | O53: 43845.31 | P53: 5 | Q53: 43845.31 | R53: 833060.89 | S53: 229816.25
A54: ORD-10052 | B54: 44752 | C54: 44752 | D54: Same Day | E54: Bola Fashola | F54: bola.fashola@gmail.com | G54: 9073583206 | H54: Consumer | I54: East | J54: Awka | K54: Clothing | L54: Shoes | M54: Sandals | N54: 14 | O54: 32332.7 | P54: 20 | Q54: 90531.56 | R54: 362126.24 | S54: 158664.45
A55: ORD-10053 | B55: 45347 | C55: 45350 | D55: Second Class | E55: Deola Dangote | F55: deola.dangote@yahoo.com | G55: 8032171218 | H55: Home Office | I55: South | J55: Warri | K55: Office Supplies | L55: Art Supplies | M55: Coloured Pencils 24 | N55: 17 | O55: 8826.94 | P55: 10 | Q55: 15005.8 | R55: 135052.18 | S55: 46232.37
A56: ORD-10054 | B56: 44866 | C56: 44867 | D56: Same Day | E56: Bukola Sanusi | F56: bukola.sanusi@outlook.com | G56: 7037328534 | H56: Home Office | I56: East | J56: Aba | K56: Clothing | L56: Shoes | M56: Women's Heels | N56: 8 | O56: 44173.31 | P56: 15 | Q56: 53007.97 | R56: 300378.51 | S56: -2962.49
A57: ORD-10055 | B57: 45342 | C57: 45343 | D57: Same Day | E57: Seun Sanusi | F57: seun.sanusi@gmail.com | G57: 8109427047 | H57: Corporate | I57: West | J57: Abeokuta | L57: Grains | M57: Rice 25kg Bag | N57: 15 | O57: 7031.27 | P57: 0 | Q57: 0 | R57: 105469.05 | S57: 17462.58
A58: ORD-10056 | B58: 45401 | C58: 45406 | D58: Second Class | E58: Seun Musa | F58: seun.musa@hotmail.com | G58: 9025446344 | H58: Home Office | I58: West | J58: Abeokuta | K58: Office Supplies | L58: Labels | M58: File Folder Labels | N58: 11 | O58: 16421 | P58: 25 | Q58: 45157.75 | R58: 135473.25 | S58: 10567.68
A59: ORD-10057 | B59: 44702 | C59: 44708 | D59: Standard Class | E59: Nike Abubakar | F59: nike.abubakar@gmail.com | G59: 7062651601 | H59: Home Office | I59: East | J59: Owerri | K59: Technology | L59: Accessories | M59: Sunglasses UV400 | N59: 1 units | O59: 316890.51 | P59: 0 | Q59: 0 | R59: 316890.51 | S59: 14141.18
A60: ORD-10058 | B60: 45444 | C60: 45446 | D60: First Class | E60: Hauwa Dangote | F60: hauwa.dangote@hotmail.com | G60: 9054020853 | H60: Corporate | I60: North | J60: Abuja | K60: Furniture | L60: Tables | M60: Office Desk 120cm | N60: 13 | O60: 112832.59 | P60: 5 | Q60: 73341.18 | R60: 1393482.5 | S60: 207071.99
A61: ORD-10059 | B61: 45503 | C61: 45506 | D61: First Class | E61: Chidi Sule | F61: chidi.sule@hotmail.com | G61: 8163650391 | H61: Corporate | I61: South | J61: Ibadan | K61: Technology | L61: Accessories | M61: Wristwatch | N61: 10 | O61: 444628.49 | P61: 15 | Q61: 666942.74 | R61: 3779342.2 | S61: 998457.25
A62: ORD-10060 | B62: 45551 | C62: 45551 | D62: Same Day | E62: Hauwa Olawale | F62: hauwa.olawale@outlook.com | G62: 9055963914 | H62: Consumer | I62: West | J62: Osogbo | K62: Office Supplies | L62: Paper | M62: Cardboard A4 | N62: 19 | O62: 7224.77 | P62: 0 | Q62: 0 | R62: 137270.63 | S62: 54409.98
A63: ORD-10061 | B63: 45010 | C63: 45012 | D63: First Class | E63: Ayo Chukwu | F63: ayo.chukwu@yahoo.com | G63: 9072630140 | H63: Consumer | I63: West | J63: Osogbo | K63: Technology | L63: Tablets | M63: Huawei MatePad | N63: 12 | O63: 29513.57 | P63: 0 | Q63: 0 | R63: 354162.84 | S63: -33971.29
A64: ORD-10062 | B64: 44921 | C64: 44921 | D64: Same Day | E64: Kemi Sule | F64: kemi.sule@outlook.com | G64: 8159418719 | H64: Home Office | I64: East | J64: Aba | K64: Office Supplies | L64: Art Supplies | M64: Acrylic Paint Kit | N64: 16 | O64: 6795.77 | P64: 10 | Q64: 10873.23 | R64: 97859.09 | S64: 29155.71
A65: ORD-10063 | B65: 44850 | C65: 44856 | D65: Standard Class | E65: Ikenna Lawal | F65: ikenna.lawal@outlook.com | G65: 8067619862 | H65: Corporate | I65: East | J65: Enugu | K65: Technology | L65: Tablets | M65: Amazon Fire HD 10 | O65: 68761.1 | P65: 10 | Q65: 82513.32 | R65: 742619.88 | S65: 149070.59
A66: ORD-10064 | B66: 45527 | C66: 45530 | D66: Second Class | E66: Ayo Otedola | F66: ayo.otedola@outlook.com | G66: 9054713925 | H66: Home Office | I66: East | J66: Enugu | K66: Technology | L66: Accessories | M66: Wristwatch | N66: 4 | O66: 297419.16 | P66: 0 | Q66: 0 | R66: 1189676.6 | S66: -146082.67
A67: ORD-10065 | B67: 19 Jul 2022 | C67: 44767 | D67: Standard Class | E67: Bukola Okafor | G67: 8147224540 | H67: Corporate | I67: North | J67: Abuja | K67: Food & Beverages | L67: Cooking Oil | M67: Sunflower Oil 3L | N67: 5 | O67: 6015.47 | P67: 15 | Q67: 4511.6 | R67: 25565.75 | S67: 6211.28
A68: ORD-10066 | B68: 44629 | C68: 44632 | D68: First Class | E68: Ibrahim Fashola | F68: ibrahim.fashola@hotmail.com | G68: 8137084862 | H68: Corporate | I68: West | J68: Ado-Ekiti | K68: Technology | L68: Tablets | M68: Amazon Fire HD 10 | N68: 12 | O68: 407237.85 | P68: 0 | Q68: 0 | R68: 4886854.2 | S68: 434362.1
A69: ORD-10067 | B69: 44996 | C69: 45001 | D69: Standard Class | E69: Ngozi Sule | F69: ngozi.sule@outlook.com | G69: 8133112652 | H69: Corporate | I69: South | J69: Lagos | K69: Food & Beverages | L69: Snacks | M69: Digestive Biscuits | N69: 18 | O69: 6689.6 | P69: 5 | Q69: 6020.64 | R69: 114392.16 | S69: 23087.75
A70: ORD-10068 | B70: 45129 | C70: 45135 | D70: Standard Class | E70: Kemi Otedola | F70: kemi.otedola@outlook.com | G70: 9023927575 | H70: Consumer | I70: South | J70: Benin City | K70: Technology | L70: Laptops | M70: Lenovo IdeaPad 3 | N70: 8 | O70: 21464.24 | P70: 10 | Q70: 17171.39 | R70: 154542.53 | S70: -21718.07
A71: ORD-10069 | B71: 45639 | C71: 45639 | D71: Same Day | E71: Tunde Sanusi | F71: tunde.sanusi@hotmail.com | G71: 9027074006 | H71: Consumer | I71: Eatst | J71: Enugu | K71: Food & Beverages | L71: Condiments | M71: Tomato Paste 400g | N71: 8 | O71: 3780.44 | P71: 0 | Q71: 0 | R71: 30243.52 | S71: 8660.1
A72: ORD-10070 | B72: 44686 | C72: 44694 | D72: Standard Class | E72: Ikenna Ogundipe | F72: ikenna.ogundipe@gmail.com | G72: 8148441741 | H72: Home Office | I72: East | J72: Owerri | K72: Technology | L72: Laptops | M72: Dell Inspiron 15 | N72: 3 | O72: 279609.38 | P72: 0 | Q72: 0 | R72: 838828.14 | S72: 12590.47
A73: ORD-10071 | B73: 45491 | C73: 45494 | D73: First Class | E73: Yemi Sule | F73: @nodomain.com | G73: 8034607488 | H73: Home Office | I73: EAST | J73: Owerri | K73: Clothing | L73: Bags | M73: Tote Bag | N73: 15 | O73: 19793.98 | P73: 15 | Q73: 44536.46 | R73: 252373.24 | S73: 25134.81
A74: ORD-10072 | B74: 45084 | C74: 45087 | D74: First Class | E74: Seun Sowore | F74: seun.sowore@hotmail.com | G74: 8062530497 | H74: Corporate | I74: North | J74: Abuja | K74: Technology | L74: Laptops | M74: Asus VivoBook 14 | N74: 12 | O74: 57005.53 | P74: 0% | Q74: 0 | R74: 684066.36 | S74: 125746.75
A75: ORD-10073 | B75: 45428 | C75: 45430 | D75: First Class | E75: Nike Alakija | F75: nike.alakija@outlook.com | G75: 7032738129 | H75: corporate | I75: East | J75: Enugu | K75: Food & Beverages | L75: Condiments | M75: Maggi Cubes 100pk | N75: 16 | O75: 1491.42 | P75: 5 | Q75: 1193.14 | R75: 22669.58 | S75: 8123.98
A76: ORD-10074 | B76: 45132 | C76: 45138 | D76: Standard Class | E76: Oluwaseun Lawal | F76: oluwaseun.lawal@gmail.com | G76: 9055487028 | H76: Corporate | I76: East | J76: Awka | K76: Technology | L76: Phones | M76: Tecno Spark 10 | N76: 10 | O76: 320673.97 | P76: 10 | Q76: 320673.97 | R76: 2886065.7 | S76: 174936.14
A77: ORD-10075 | B77: 44704 | C77: 44704 | D77: Same Day | E77: Amara Musa | F77: amara.musa@yahoo.com | G77: 7068043620 | H77: Home Office | I77: South | J77: Ibadan | K77: Clothing | L77: Shoes | M77: Women's Heels | N77: 11 | O77: 17912.28 | P77: 0% | Q77: 0 | R77: 197035.08 | S77: 74874.38
A78: ORD-10076 | B78: 44729 | C78: 44736 | D78: Standard Class | E78: Olumide Sowore | F78: olumide.sowore@hotmail.com | G78: 8148416270 | H78: home office | I78: South | J78: Ibadan | K78: Clothing | L78: Shoes | M78: Women's Heels | N78: 4 | O78: 34462.56 | P78: 10 | Q78: 13785.02 | R78: 124065.22 | S78: 13392.61
A79: ORD-10077 | B79: 44655 | C79: 44657 | D79: First Class | E79: Ikenna Alakija | F79: ikenna.alakija@gmail.com | G79: 8034429650 | H79: Corporate | I79: East | J79: Awka | K79: Office Supplies | L79: Binders | M79: Lever Arch File | N79: 10 | O79: 19221.94 | P79: 10 | Q79: 19221.94 | R79: 172997.46 | S79: -13495.43
A80: ORD-10078 | B80: 45340 | C80: 45345 | D80: Second Class | E80: Zainab Dangote | F80: zainab.dangote@outlook.com | G80: 8067661748 | H80: Consumer | I80: West | J80: Akure | K80: Technology | L80: Accessories | M80: Belt Leather | N80: 3 | O80: 214993.1 | P80: 10 | Q80: 64497.93 | R80: 580481.37 | S80: 113458.27
A81: ORD-10079 | B81: 45391 | C81: 45396 | D81: Standard Class | E81: Chisom Adeyemi | F81: chisom.adeyemi@hotmail.com | G81: 8037070880 | H81: Corporate | I81: West | J81: Akure | K81: Technology | L81: Accessories | M81: Belt Leather | N81: 19 | O81: 120842.67 | P81: 15 | Q81: 344401.61 | R81: 1951609.1 | S81: 320800.68
A82: ORD-10080 | B82: 45015 | C82: 45018 | D82: First Class | E82: Aisha Musa | F82: aisha.musa@gmail.com | G82: 8159555575 | H82: Home Office | I82: West | J82: Osogbo | K82: Furniture | L82: Bookcases | M82: Wall-Mounted Shelf | N82: 5 units | O82: 133109.21 | P82: 5 | Q82: 33277.3 | R82: 632268.75 | S82: -55840.26
A83: ORD-10081 | B83: 44716 | C83: 44719 | D83: Second Class | E83: Wale Fashola # | F83: wale.fashola@hotmail.com | G83: 9076422534 | H83: Consumer | I83: East | J83: Onitsha | K83: Office Supplies | L83: Binders | M83: Document Folder | N83: 15 | O83: 2173.01 | P83: 10 | Q83: 3259.51 | R83: 29335.64 | S83: 9616.16
A84: ORD-10082 | B84: 2023/09/28 | C84: 45205 | D84: Standard Class | E84: Olumide Adeleke | F84: olumide.adeleke@gmail.com | G84: 7035816353 | H84: Home Office | I84: north | J84: Abuja | K84: Technology | L84: Laptops | M84: Acer Aspire 5 | N84: 13 | O84: 273424.72 | P84: 20 | Q84: 710904.27 | R84: 2843617.1 | S84: 563598.21
A85: ORD-10083 | B85: 45220 | C85: 45225 | D85: second class | E85: Kunle Dangote | F85: kunle.dangote@yahoo.com | G85: 8038558523 | H85: Home Office | I85: North | K85: Technology | L85: Tablets | M85: iPad 10th Gen | N85: 6 | O85: 234478.82 | P85: 0 | Q85: 0 | R85: 1406872.9 | S85: -1904.58
A86: ORD-10084 | B86: 45307 | D86: Second Class | E86: Nike Olawale | F86: nike.olawale@hotmail.com | G86: N/A | H86: Home Office | I86: West | J86: Akure | K86: Food & Beverages | L86: Drinks | M86: Water 5L x6 | N86: 4 | O86: 807.52 | P86: 25 | Q86: 807.52 | R86: 2422.56 | S86: 622.66
A87: ORD-10085 | B87: 45244 | C87: 45247 | D87: Second Class | E87: Lanre Sowore | F87: lanre.sowore@yahoo.com | G87: +234 803 123 4567 | H87: Home Office | J87: Aba | K87: Clothing | L87: Trousers | M87: Jeans Straight Cut | N87: -5 | O87: 32479.86 | P87: 10 | Q87: 9743.96 | R87: 87695.62 | S87: 16254.67
A88: ORD-10086 | B88: 45429 | C88: 45436 | D88: Standard Class | E88: Amara Adebayo | F88: amara.adebayo@outlook.com | G88: 8104593556 | H88: Home Office | I88: East | J88: Onitsha | K88: Office Supplies | L88: Art Supplies | M88: Coloured Pencils 24 | N88: 5 | O88: 5204.13 | P88: 0 | Q88: 0 | R88: 26020.65 | S88: -2698.37
A89: ORD-10087 | B89: 45251 | C89: 45257 | D89: Standard Class | E89: Deola Olawale | F89: deola.olawale@yahoo.com | G89: 8104034091 | H89: Home Office | I89: North | J89: Katsina | K89: Food & Beverages | L89: Snacks | M89: Popcorn 6-Pack | N89: -2 | O89: 636.43 | P89: 5 | Q89: 381.86 | R89: 7255.3 | S89: 3132.5
A90: ORD-10088 | B90: 45195 | C90: 45199 | D90: second class | E90: Musa Adebayo | F90: musa.adebayo@hotmail.com | G90: 8145727345 | H90: Consumer | I90: East | J90: Owerri | K90: Clothing | L90: Accessories | M90: Wallet Genuine Leather | N90: 6 | O90: 20002.42 | P90: 5 | Q90: 6000.73 | R90: 114013.79 | S90: 37710.69
A91: ORD-10089 | B91: 45322 | C91: 45322 | D91: Same Day | F91: ronke.lawal@gmail.com | G91: 8162407191 | H91: Consumer | I91: South | J91: Benin City | K91: Furniture | L91: Bookcases | M91: Corner Bookshelf | N91: 5 | O91: 163712.67 | P91: 15 | Q91: 122784.5 | R91: 695778.85 | S91: -66079.41
A92: ORD-10090 | B92: 45411 | C92: 45416 | D92: Standard Class | E92: Ikenna Dangote | F92: ikenna.dangote@outlook.com | G92: 080 | H92: Corporate | I92: South | J92: Warri | K92: Technology | L92: Tablets | M92: Samsung Tab A8 | N92: 4 | O92: 27261.58 | P92: 10 | Q92: 10904.63 | S92: 31879.21
A93: ORD-10091 | B93: 44846 | C93: 44847 | D93: Same Day | E93: Olumide Alakija | F93: olumide.alakija@gmail.com | G93: 8061318832 | H93: Corporate | I93: South | J93: Lagos | K93: Office Supplies | L93: Binders | M93: Lever Arch File | N93: 20 | O93: 13945.7 | P93: 25 | Q93: 69728.5 | R93: 209185.5 | S93: 21745.43
A94: ORD-10092 | B94: 44659 | C94: 44665 | D94: Standard Class | F94: chibundo.tinubu@hotmail.com | G94: 8062859886 | H94: Corporate | I94: East | J94: Onitsha | K94: Clothing | L94: Accessories | M94: Wallet Genuine Leather | N94: 17 | O94: 2706.72 | P94: 5 | Q94: 2300.71 | R94: 43713.53 | S94: 12289.04
A95: ORD-10093 | B95: 45054 | C95: 45057 | D95: First Class | E95: Fatima Sowore | F95: fatima.sowore@gmail.com | G95: 8157049927 | H95: Consumer | I95: East | K95: Technology | L95: Printers | M95: HP LaserJet Pro | N95: 17 | O95: 235687.55 | P95: 25 | Q95: 1001672.1 | R95: 3005016.3 | S95: -414089.49
A96: ORD-10094 | B96: 45326 | C96: 45327 | D96: Same Day | E96: Amara Adebayo | F96: amara.adebayo@gmail.com | G96: 7035045421 | H96: Home Office | I96: West | J96: Abeokuta | K96: Technology | L96: Printers | M96: Epson EcoTank | N96: 12 | O96: 73033.17 | P96: 25 | Q96: 219099.51 | R96: 657298.53 | S96: 34921.19
A97: ORD-10095 | B97: 44935 | C97: 44935 | D97: Same Day | E97: Tunde Obi | F97: tunde.obi@hotmail.com | G97: 8035923149 | H97: Home Office | I97: South | J97: Warri | K97: Furniture | L97: Chairs | M97: Mesh Office Chair | N97: 11 | O97: 160355.95 | P97: 10 | Q97: 176391.55 | R97: 1587523.9 | S97: 252781.67
A98: ORD-10096 | B98: 45147 | C98: 45151 | D98: Second Class | E98: Ngozi Lawal | F98: ngozi.lawal@outlook.com | G98: 8163088344 | H98: Consumer | I98: West | J98: Osogbo | K98: Office Supplies | L98: Envelopes | M98: Brown Kraft Envelopes | N98: 13 | O98: 18711.04 | P98: 10 | Q98: 24324.35 | R98: 218919.17 | S98: 95062.18
A99: ORD-10097 | B99: 44731 | C99: 44734 | D99: First Class | E99: Sade Ogundipe | F99: sade.ogundipe@yahoo.com | G99: 8155928582 | H99: Corporate | I99: West | J99: Akure | K99: Office Supplies | L99: Paper | M99: A4 Paper 500 Sheets | N99: 10 | O99: 8534.04 | P99: 10 | Q99: 8534.04 | R99: 76806.36 | S99: 9028.55
A100: ORD-10098 | B100: 45281 | C100: 45282 | D100: Same Day | E100: Emeka Atiku | F100: emeka.atiku@outlook.com | G100: 9058297090 | H100: Home Office | I100: West | J100: Ilorin | K100: Office Supplies | L100: Fasteners | M100: Stapler + Staples | N100: 13 | O100: 2338.51 | P100: 10 | Q100: 3040.06 | R100: 27360.57 | S100: 4318.91
...

Sheet Raw Data (4)
A1: Order ID | B1: Order Date | C1: Ship Date | D1: Ship Mode | E1: First Name | F1: Last Name | G1: Email | H1: Phone | I1: Segment | J1: Region | K1: State | L1: Category | M1: Category Clean | N1: Sub-Category | O1: Product Name | P1: Quantity | Q1: Unit Price (₦) | R1: Discount (%) | S1: Discount Amount (₦) | T1: Sales (₦) | U1: Profit (₦)
A2: ORD-10858 | B2: 44562 | C2: 44567 | D2: Standard Class | E2: Ayo | F2: Adeleke | G2: ayo.adeleke@gmail.com | H2: 8161000159 | I2: Consumer | J2: East | K2: Onitsha | L2: Office Supplies | M2: =TRIM(Table2[[#This Row],[Category]]) -> Office Supplies | N2: Envelopes | O2: Brown Kraft Envelopes | P2: 6 | Q2: 18354.33 | R2: 0 | S2: 0 | T2: 110125.98 | U2: -12981.35
A3: ORD-10441 | B3: 44573 | C3: 44581 | D3: Standard Class | E3: Bola | F3: Okonkwo | G3: bola.okonkwo@yahoo.com | H3: 9079004743 | I3: Corporate | J3: East | K3: Enugu | L3: Clothing | M3: =TRIM(Table2[[#This Row],[Category]]) -> Clothing | N3: Bags | O3: Crossbody Bag | P3: 10 | Q3: 33214.19 | R3: 10 | S3: 33214.19 | T3: 298927.71 | U3: 79035.7
A4: ORD-10505 | B4: 44583 | C4: 44590 | D4: Standard Class | E4: Bola | F4: Obi | G4: bola.obi@yahoo.com | H4: 7038788747 | I4: Corporate | J4: West | K4: Ilorin | L4: Clothing | M4: =TRIM(Table2[[#This Row],[Category]]) -> Clothing | N4: Bags | O4: Laptop Backpack | P4: 8 | Q4: 5549.59 | R4: 20 | S4: 8879.34 | T4: 35517.38 | U4: -2338.7
A5: ORD-10382 | B5: 44607 | C5: 44613 | D5: STANDARD CLASS | E5: Ronke | F5: Tinubu | G5: ronke.tinubu@outlook.com | H5: 7066751103 | I5: Consumer | J5: North | K5: Abuja | L5: Office Supplies | M5: =TRIM(Table2[[#This Row],[Category]]) -> Office Supplies | N5: Envelopes | O5: C5 Envelopes | P5: 17 | Q5: 16813.46 | R5: 25 | S5: 71457.21 | T5: 214371.61 | U5: 25114.44
A6: ORD-10832 | B6: 44609 | C6: 44615 | D6: Standard Class | E6: Yemi | F6: Abubakar | G6: yemi.abubakar@gmail.com | H6: 8107264416 | I6: Home Office | J6: west | K6: Abuja | L6: Technology | M6: =TRIM(Table2[[#This Row],[Category]]) -> Technology | N6: Phones | O6: Xiaomi Redmi 12 | P6: 3 | Q6: 363633.82 | R6: 0 | S6: 0 | T6: 1090901.5 | U6: -157322.01
A7: ORD-10852 | B7: 44611 | C7: 44616 | D7: Standard Class | E7: Zainab | F7: Sanusi | G7: zainab.sanusi@gmail.com | H7: 8034674225 | I7: Consumer | J7: East | K7: Onitsha | L7: Furniture | M7: =TRIM(Table2[[#This Row],[Category]]) -> Furniture | N7: Tables | O7: Conference Table | P7: 11 | Q7: 94100.43 | R7: 15 | S7: 155265.71 | T7: 879839.02 | U7: 267099.63
A8: ORD-10959 | B8: 44624 | C8: 44629 | D8: Standard Class | E8: Chisom | F8: Adeyemi | G8: chisom.adeyemi@gmail.com | H8: 8064194751 | I8: Home Office | J8: North | K8: Kano | L8: Clothing | M8: =TRIM(Table2[[#This Row],[Category]]) -> Clothing | N8: Shirts | O8: T-Shirt 3-Pack | P8: 18 | Q8: 35696.94 | R8: 10 | S8: 64254.49 | T8: 578290.43 | U8: -66880.13
A9: ORD-10160 | B9: 44625 | C9: 44631 | D9: Standard Class | E9: Nike | F9: Adeleke | G9: nike.adeleke@outlook.com | H9: 8135843084 | I9: Consumer | J9: West | K9: Akure | L9: Furniture | M9: =TRIM(Table2[[#This Row],[Category]]) -> Furniture | N9: Storage | O9: Wardrobe 3-Door | P9: 16 | Q9: 135713.14 | R9: 25 | S9: 542852.56 | T9: 1628557.7 | U9: 254842.55
A10: ORD-10364 | B10: 44637 | C10: 44643 | D10: Standard Class | E10: Wale | F10: Tinubu | G10: wale.tinubu@gmail.com | H10: 8141768424 | I10: Consumer | J10: South | K10: Port Harcourt | L10: Furniture | M10: =TRIM(Table2[[#This Row],[Category]]) -> Furniture | N10: Tables | O10: Office Desk 120cm | P10: 2 | Q10: 37626.83 | R10: 10 | S10: 7525.37 | T10: 67728.29 | U10: 23193.11
A11: ORD-10035 | B11: 44644 | C11: 44649 | D11: Standard Class | E11: Hauwa | F11: Nwosu | G11: hauwa.nwosu@gmail.com | H11: 9053556551 | I11: Consumer | J11: North | K11: Abuja | L11: Furniture | M11: =TRIM(Table2[[#This Row],[Category]]) -> Furniture | N11: Tables | O11: Dining Table 6-Seater | P11: 19 | Q11: 123146.92 | R11: 5 | S11: 116989.57 | T11: 2222801.9 | U11: 286786.77
A12: ORD-10296 | B12: 44651 | C12: 44657 | D12: Standard Class | E12: Fatima | F12: Lawal | G12: fatima.lawal@gmail.com | H12: 8132796087 | I12: Home Office | J12: north | K12: Kano | L12: Clothing | M12: =TRIM(Table2[[#This Row],[Category]]) -> Clothing | N12: Trousers | O12: Men's Chinos | P12: 13 | Q12: 3368.14 | R12: 20 | S12: 8757.16 | T12: 35028.66 | U12: 5796.99
A13: ORD-10166 | B13: 44656 | C13: 44661 | D13: Standard Class | E13: Adebayo | F13: Okonkwo | G13: adebayo.okonkwo@gmail.com | H13: 8033650523 | I13: Home Office | J13: West | K13: Osogbo | L13: Clothing | M13: =TRIM(Table2[[#This Row],[Category]]) -> Clothing | N13: Bags | O13: Laptop Backpack | P13: 14 | Q13: 44649.04 | R13: 5 | S13: 31254.33 | T13: 593832.23 | U13: 265690.3
A14: ORD-10092 | B14: 44659 | C14: 44665 | D14: Standard Class | E14: =E15 -> Amara | F14: =F13 -> Okonkwo | G14: chibundo.tinubu@hotmail.com | H14: 8062859886 | I14: Corporate | J14: East | K14: Onitsha | L14: Clothing | M14: =TRIM(Table2[[#This Row],[Category]]) -> Clothing | N14: Accessories | O14: Wallet Genuine Leather | P14: 17 | Q14: 2706.72 | R14: 5 | S14: 2300.71 | T14: 43713.53 | U14: 12289.04
A15: ORD-10221 | B15: 44660 | C15: 44665 | D15: Standard Class | E15: Amara | F15: Adeleke | G15: N/A | H15: 7068454356 | I15: Home Office | J15: East | K15: Awka | L15: Clothing | M15: =TRIM(Table2[[#This Row],[Category]]) -> Clothing | N15: Shirts | O15: Ankara Print Shirt | P15: 5 | Q15: 12867.75 | R15: 5 | S15: 3216.94 | T15: 61121.81 | U15: 16326.57
A16: ORD-10971 | B16: 44660 | C16: 44666 | D16: Standard Class | E16: Hauwa | F16: Danjuma | G16: hauwa.danjuma@gmail.com | H16: 9074321723 | I16: Corporate | J16: West | K16: Ado-Ekiti | L16: Clothing | M16: =TRIM(Table2[[#This Row],[Category]]) -> Clothing | N16: Trousers | O16: Women's Palazzo | P16: 11 | Q16: 19414.76 | R16: 5 | S16: 10678.12 | T16: 202884.24 | U16: -25659.44
A17: ORD-10563 | B17: 44668 | C17: 44675 | D17: Standard Class | E17: Ibrahim | F17: Eze | G17: ibrahim.eze@hotmail.com | H17: 8162690500 | I17: Consumer | J17: North | K17: Kaduna | L17: Clothing | M17: =TRIM(Table2[[#This Row],[Category]]) -> Clothing | N17: Trousers | O17: Joggers | P17: 12 | Q17: 42778.11 | R17: 10 | S17: 51333.73 | T17: 462003.59 | U17: 15067.79
A18: ORD-10621 | B18: 44669 | C18: 44676 | D18: Standard Class | E18: Emeka | F18: Bello | G18: emeka.bello@gmail.com | H18: 8162258998 | I18: Home Office | J18: South | K18: Benin City | L18: Office Supplies | M18: =TRIM(Table2[[#This Row],[Category]]) -> Office Supplies | N18: Pens & Pencils | O18: Highlighters Set | P18: 13 | Q18: 19894.88 | R18: 10 | S18: 25863.34 | T18: 232770.1 | U18: 62661.45
A19: ORD-10127 | B19: 44685 | C19: 44690 | D19: STANDARD CLASS | E19: Kunle | F19: Adeleke | G19: kunle.adeleke@outlook.com | H19: 7064019585 | I19: Corporate | J19: North | K19: Sokoto | L19: Furniture | M19: =TRIM(Table2[[#This Row],[Category]]) -> Furniture | N19: Storage | O19: Plastic Drawers | P19: 13 | Q19: 178771.33 | R19: 20 | S19: 464805.46 | T19: 1859221.8 | U19: 691206.94
A20: ORD-10456 | B20: 44684 | C20: 44691 | D20: Standard Class | E20: Tobi | F20: Tinubu | G20: tobi.tinubu@outlook.com | H20: 8061800824 | I20: Home Office | J20: East | K20: Abia | L20: Technology | M20: =TRIM(Table2[[#This Row],[Category]]) -> Technology | N20: Accessories | O20: Wristwatch | P20: 1 | Q20: 264009.35 | R20: 20 | S20: 52801.87 | T20: 211207.48 | U20: 11275.98
A21: ORD-10782 | B21: 44683 | C21: 44691 | D21: Standard Class | E21: Kemi | F21: Okafor | G21: kemi.okafor@hotmail.com | H21: 8033688598 | I21: Home Office | J21: South | K21: Port Harcourt | L21: Furniture | M21: =TRIM(Table2[[#This Row],[Category]]) -> Furniture | N21: Storage | O21: Filing Cabinet | P21: 13 | Q21: 119126.56 | R21: 5 | S21: 77432.26 | T21: 1471213 | U21: -1259.39
A22: ORD-10567 | B22: 44686 | C22: 44692 | D22: Standard Class | E22: Ikenna | F22: Sanusi | G22: ikenna.sanusi@gmail.com | H22: 8108344141 | I22: Corporate | J22: East | K22: Onitsha | L22: Food & Beverages | M22: =TRIM(Table2[[#This Row],[Category]]) -> Food & Beverages | N22: Cooking Oil | O22: Sunflower Oil 3L | P22: -1 | Q22: 6301.17 | R22: 10 | S22: 8191.52 | T22: 73723.69 | U22: -1905.41
A23: ORD-10173 | B23: 44685 | C23: 44693 | D23: Standard Class | E23: Dayo | F23: Eze | G23: dayo.eze@hotmail.com | H23: 7067749095 | I23: Consumer | J23: North | K23: Abuja | L23: Technology | M23: =TRIM(Table2[[#This Row],[Category]]) -> Technology | N23: Printers | O23: HP LaserJet Pro | P23: 9 | Q23: 282980.47 | R23: 0 | S23: 0 | T23: 2546824.2 | U23: 91543.38
A24: ORD-10070 | B24: 44686 | C24: 44694 | D24: Standard Class | E24: Ikenna | F24: Ogundipe | G24: ikenna.ogundipe@gmail.com | H24: 8148441741 | I24: Home Office | J24: East | K24: Owerri | L24: Technology | M24: =TRIM(Table2[[#This Row],[Category]]) -> Technology | N24: Laptops | O24: Dell Inspiron 15 | P24: 3 | Q24: 279609.38 | R24: 0 | S24: 0 | T24: 838828.14 | U24: 12590.47
A25: ORD-10587 | B25: 44695 | C25: 44701 | D25: Standard Class | E25: Deola | F25: Okonkwo | G25: deola.okonkwo@outlook.com | H25: 8134384399 | I25: Home Office | J25: East | K25: Onitsha | L25: Technology | M25: =TRIM(Table2[[#This Row],[Category]]) -> Technology | N25: Phones | O25: Tecno Spark 10 | P25: 19 | Q25: 51992.12 | R25: 0 | S25: 0 | T25: 987850.28 | U25: 185956.49
A26: ORD-10886 | B26: 44698 | C26: 44704 | D26: Standard Class | E26: Tobi | F26: Sanusi | G26: tobi.sanusi@hotmail.com | H26: 8155648826 | I26: Corporate | J26: WEST | K26: Ado-Ekiti | L26: Food & Beverages | M26: =TRIM(Table2[[#This Row],[Category]]) -> Food & Beverages | N26: Condiments | O26: Pepper Mix 200g | P26: 2 | Q26: 1833.76 | R26: 15 | S26: 550.13 | T26: 3117.39 | U26: 707.23
A27: ORD-10057 | B27: 44702 | C27: 44708 | D27: Standard Class | E27: Nike | F27: Abubakar | G27: nike.abubakar@gmail.com | H27: 7062651601 | I27: Home Office | J27: East | K27: Owerri | L27: Technology | M27: =TRIM(Table2[[#This Row],[Category]]) -> Technology | N27: Accessories | O27: Sunglasses UV400 | P27: 1 | Q27: 316890.51 | R27: 0 | S27: 0 | T27: 316890.51 | U27: 14141.18
A28: ORD-10298 | B28: 44706 | C28: 44713 | D28: Standard Class | E28: Tunde | F28: Nwosu | G28: tunde.nwosu@gmail.com | H28: 8064875838 | I28: Corporate | J28: North | K28: Katsina | L28: Food & Beverages | M28: =TRIM(Table2[[#This Row],[Category]]) -> Food & Beverages | N28: Cooking Oil | O28: Palm Oil 4L | P28: 8 | Q28: 1787.02 | R28: 0 | S28: 0 | T28: 14296.16 | U28: 2645.56
A29: ORD-10523 | B29: 44705 | C29: 44713 | D29: Standard Class | E29: Ronke | F29: Ogundipe | G29: ronke.ogundipe@outlook.com | H29: 9018230134 | I29: Consumer | J29: South | K29: Warri | L29: Furniture | M29: =TRIM(Table2[[#This Row],[Category]]) -> Furniture | N29: Tables | O29: Study Table | P29: 5 | Q29: 40060.81 | R29: 5 | S29: 10015.2 | T29: 190288.85 | U29: 26998.71
A30: ORD-10435 | B30: 44706 | C30: 44714 | D30: Standard Class | E30: Sade | F30: Olawale | G30: sade.olawale@outlook.com | H30: 8105027876 | I30: Corporate | J30: North | K30: Abuja | L30: Clothing | M30: =TRIM(Table2[[#This Row],[Category]]) -> Clothing | N30: Shirts | O30: Men's Polo Shirt | P30: 6 | Q30: 38650.87 | R30: 15 | S30: 34785.78 | T30: 197119.44 | U30: 62623.96
A31: ORD-10494 | B31: 44708 | C31: 44715 | D31: Standard Class | E31: Emeka | F31: Otedola | G31: emeka.otedola@yahoo.com | H31: 7034299177 | I31: Consumer | J31: East | K31: Onitsha | L31: Office Supplies | M31: =TRIM(Table2[[#This Row],[Category]]) -> Office Supplies | N31: Pens & Pencils | O31: Pilot G2 Gel Pens | P31: 9 | Q31: 18757.68 | R31: 5 | S31: 8440.96 | T31: 160378.16 | U31: 43845.08
A32: ORD-10273 | B32: 44722 | C32: 44730 | D32: Standard Class | E32: Ayo | F32: Okonkwo | G32: ayo.okonkwo@gmail.com | H32: 8039091518 | I32: Consumer | J32: East | K32: Onitsha | L32: Office Supplies | M32: =TRIM(Table2[[#This Row],[Category]]) -> Office Supplies | N32: Labels | O32: Price Tag Labels | P32: 19 | Q32: 12562.34 | R32: 10 | S32: 23868.45 | T32: 214816.01 | U32: 31037.31
A33: ORD-10417 | B33: 44733 | C33: 44730 | D33: Standard Class | E33: Deola | F33: Eze | G33: deola.eze@gmail.com | H33: 7067097414 | I33: Consumer | J33: North | K33: Sokoto | L33: Technology | M33: =TRIM(Table2[[#This Row],[Category]]) -> Technology | N33: Accessories | O33: Sunglasses UV400 | P33: 19 | Q33: 117677.9 | R33: 25 | S33: 558970.03 | T33: 1676910.1 | U33: 687132.8
A34: ORD-10835 | B34: 44724 | C34: 44730 | D34: Standard Class | E34: Musa | F34: Chukwu | G34: musa.chukwu@yahoo.com | H34: 8154176691 | I34: Consumer | J34: North | K34: Sokoto | L34: Technology | M34: =TRIM(Table2[[#This Row],[Category]]) -> Technology | N34: Laptops | O34: Lenovo IdeaPad 3 | P34: 11 | Q34: 96365.9 | R34: 5 | S34: 53001.25 | T34: 1007023.7 | U34: -52914.92
A35: ORD-10915 | B35: 44730 | C35: 44735 | D35: Standard Class | E35: Ayo | F35: Okonkwo | G35: ayo.okonkwo@yahoo.com | H35: 9023851025 | I35: Consumer | J35: East | K35: Aba | L35: Clothing | M35: =TRIM(Table2[[#This Row],[Category]]) -> Clothing | N35: Bags | O35: Laptop Backpack | P35: 10 | Q35: 13495.2 | R35: 25 | S35: 33738 | T35: 101214 | U35: -10828.89
A36: ORD-10076 | B36: 44729 | C36: 44736 | D36: Standard Class | E36: Olumide | F36: Sowore | G36: olumide.sowore@hotmail.com | H36: 8148416270 | I36: home office | J36: South | K36: Ibadan | L36: Clothing | M36: =TRIM(Table2[[#This Row],[Category]]) -> Clothing | N36: Shoes | O36: Women's Heels | P36: 4 | Q36: 34462.56 | R36: 10 | S36: 13785.02 | T36: 124065.22 | U36: 13392.61
A37: ORD-10434 | B37: 44728 | C37: 44736 | D37: Standard Class | E37: Kunle | F37: Fashola | G37: kunle.fashola@outlook.com | H37: 9051097397 | I37: Consumer | J37: North | K37: Abuja | L37: Office Supplies | M37: =TRIM(Table2[[#This Row],[Category]]) -> Office Supplies | N37: Paper | O37: Graph Paper Pad | P37: 11 | Q37: 23796.95 | R37: 0 | S37: 0 | T37: 261766.45 | U37: -6067.72
A38: ORD-10972 | B38: 44733 | C38: 44741 | D38: Standard Class | E38: Chisom | F38: Olawale | G38: chisom.olawale@gmail.com | H38: 8149400075 | I38: Home Office | J38: west | K38: Abeokuta | L38: Clothing | M38: =TRIM(Table2[[#This Row],[Category]]) -> Clothing | N38: Accessories | O38: Wallet Genuine Leather | P38: 1 | Q38: 40348.43 | R38: 0 | S38: 0 | T38: 40348.43 | U38: -999.75
A39: ORD-10266 | B39: 44748 | C39: 44754 | D39: Standard Class | E39: Kunle_Alakija | F39: =F38 -> Olawale | G39: kunle.alakija@hotmail.com | H39: 8062075091 | I39: Corporate | J39: North | K39: Kaduna | L39: office supplies | M39: =TRIM(Table2[[#This Row],[Category]]) -> office supplies | N39: Binders | O39: Clipboard | P39: 2 | Q39: 2460.97 | R39: 15 | S39: 738.29 | T39: 4183.65 | U39: 1708.65
A40: ORD-10502 | B40: 44748 | C40: 44755 | D40: Standard Class | E40: =E41 -> Yemi | F40: =F39 -> Olawale | G40: adebayo.adebayo@outlook.com | H40: 7063938131 | I40: Corporate | J40: West | K40: Akure | L40: Clothing | M40: =TRIM(Table2[[#This Row],[Category]]) -> Clothing | N40: Trousers | O40: Women's Palazzo | P40: 14 | Q40: 40698.48 | R40: 20 | S40: 113955.74 | T40: 455822.98 | U40: 36830.04
A41: ORD-10936 | B41: 44755 | C41: 44760 | D41: Standard Class | E41: Yemi | F41: Sanusi | G41: yemi.sanusi@gmail.com | H41: 8147058725 | I41: Consumer | J41: East | K41: Enugu | L41: Clothing | M41: =TRIM(Table2[[#This Row],[Category]]) -> Clothing | N41: Accessories | O41: Belt Leather | P41: 19 | Q41: 13364.14 | R41: 25 | S41: 63479.66 | T41: 190439 | U41: 73702.69
A42: ORD-10225 | B42: 44756 | C42: 44761 | D42: Standard Class | E42: Chidi | F42: Lawal | G42: chidi.lawal@yahoo.com | H42: 9073860721 | I42: Home Office | J42: East | K42: Owerri | L42: Office Supplies | M42: =TRIM(Table2[[#This Row],[Category]]) -> Office Supplies | N42: Pens & Pencils | O42: Whiteboard Markers | P42: 9 | Q42: 23899.68 | R42: 0% | S42: 0 | T42: 215097.12 | U42: 15825.4
A43: ORD-10065 | B43: 45126 | C43: 44767 | D43: Standard Class | E43: Bukola | F43: Okafor | G43: unknown | H43: 8147224540 | I43: Corporate | J43: North | K43: Abuja | L43: Food & Beverages | M43: =TRIM(Table2[[#This Row],[Category]]) -> Food & Beverages | N43: Cooking Oil | O43: Sunflower Oil 3L | P43: 5 | Q43: 6015.47 | R43: 15 | S43: 4511.6 | T43: 25565.75 | U43: 6211.28
A44: ORD-10506 | B44: 44767 | C44: 44773 | D44: Standard Class | E44: Nike | F44: Bello | G44: nike.bello@hotmail.com | H44: 8102301665 | I44: Consumer | J44: East | K44: Onitsha | L44: Technology | M44: =TRIM(Table2[[#This Row],[Category]]) -> Technology | N44: Tablets | O44: Samsung Tab A8 | P44: 6 | Q44: ₦206,686.23 | R44: 5 | S44: 62005.87 | T44: 1178111.5 | U44: 328277.67
A45: ORD-10224 | B45: 44769 | C45: 44776 | D45: Standard Class | E45: Zainab | F45: Fashola | G45: zainab.fashola@outlook.com | H45: 8168789281 | I45: Consumer | J45: West | K45: Ilorin | L45: Technology | M45: =TRIM(Table2[[#This Row],[Category]]) -> Technology | N45: Laptops | O45: Lenovo IdeaPad 3 | P45: 10 | Q45: 395251.1 | R45: 10 | S45: 395251.1 | T45: 3557259.9 | U45: 1177302.4
A46: ORD-10609 | B46: 44773 | C46: 44778 | D46: Standard Class | E46: Adebayo | F46: Alakija | G46: adebayo.alakija@gmail.com | H46: 8063379602 | I46: Consumer | J46: East | K46: Enugu | L46: Office Supplies | M46: =TRIM(Table2[[#This Row],[Category]]) -> Office Supplies | N46: Pens & Pencils | O46: Staedtler HB Pencils | P46: 16 | Q46: 2773.04 | R46: 10 | S46: 4436.86 | T46: 39931.78 | U46: 15878.13
A47: ORD-10169 | B47: 44773 | C47: 44780 | D47: STANDARD CLASS | E47: Uchenna | F47: Eze | G47: unknown | H47: 7063233823 | I47: Consumer | J47: South | K47: Warri | L47: Furniture | M47: =TRIM(Table2[[#This Row],[Category]]) -> Furniture | N47: Chairs | O47: Gaming Chair | P47: 20 | Q47: 104886.09 | R47: 0 | S47: 0 | T47: 2097721.8 | U47: 239265.42
A48: ORD-10444 | B48: 44772 | C48: 44780 | D48: Standard Class | E48: Chibundo | F48: Lawal | G48: chibundo.lawal@hotmail.com | H48: 9015878387 | I48: Corporate | J48: West | K48: Abeokuta | L48: Technology | M48: =TRIM(Table2[[#This Row],[Category]]) -> Technology | N48: Accessories | O48: Silk Scarf | P48: 19 | Q48: 226453.92 | R48: 20 | S48: 860524.9 | T48: 3442099.6 | U48: -37369.25
A49: ORD-10351 | B49: 44790 | C49: 44796 | D49: Standard Class | E49: Lanre | F49: Atiku | G49: lanre.atiku@yahoo.com | H49: 9078493596 | I49: Corporate | J49: East | K49: Aba | L49: Office Supplies | M49: =TRIM(Table2[[#This Row],[Category]]) -> Office Supplies | N49: Art Supplies | O49: Acrylic Paint Kit | P49: 8 | Q49: 6900.69 | R49: 20 | S49: 11041.1 | T49: 44164.42 | U49: -1833.46
A50: ORD-10655 | B50: 44789 | C50: 44797 | D50: Standard Class | E50: Tobi | F50: Tinubu | G50: tobi.tinubu@gmail.com | H50: 8036671458 | I50: Home Office | J50: East | K50: Owerri | L50: =L49 -> Office Supplies | M50: =TRIM(Table2[[#This Row],[Category]]) -> Office Supplies | N50: Shoes | O50: Women's Heels | P50: 2 | Q50: 16385.27 | R50: 0 | S50: 0 | T50: 32770.54 | U50: -899.88
A51: ORD-10860 | B51: 44792 | C51: 44797 | D51: Standard Class | E51: Hauwa | F51: Fashola | G51: hauwa.fashola@outlook.com | H51: 8161378476 | I51: Consumer | J51: North | K51: Sokoto | L51: Food & Beverages | M51: =TRIM(Table2[[#This Row],[Category]]) -> Food & Beverages | N51: Cooking Oil | O51: Vegetable Oil 5L | P51: 5 | Q51: 5932.04 | R51: 5 | S51: 1483.01 | T51: 28177.19 | U51: -3125
A52: ORD-10763 | B52: 44792 | C52: 44798 | D52: STANDARD CLASS | E52: Dayo | F52: Lawal | G52: dayo.lawal@gmail.com | H52: 9058859233 | I52: Home Office | J52: North | K52: Kano | L52: Food & Beverages | M52: =TRIM(Table2[[#This Row],[Category]]) -> Food & Beverages | N52: Snacks | O52: Digestive Biscuits | P52: 14 | Q52: 6206.79 | R52: 10 | S52: 8689.51 | T52: 78205.55 | U52: 10122.07
A53: ORD-10956 | B53: 44798 | C53: 44804 | D53: Standard Class | E53: Ngozi | F53: Abubakar | G53: ngozi.abubakar@gmail.com | H53: 8159041683 | I53: Corporate | J53: West | K53: Ado-Ekiti | L53: Clothing | M53: =TRIM(Table2[[#This Row],[Category]]) -> Clothing | N53: Accessories | O53: Sunglasses UV400 | P53: 6 | Q53: 4271.76 | R53: 25 | S53: 6407.64 | T53: 19222.92 | U53: 7217.81
A54: ORD-10024 | B54: 44798 | C54: 44805 | D54: Standard Class | E54: Fatima | F54: Danjuma | G54: fatima.danjuma@outlook.com | H54: 8032818692 | I54: Corporate | J54: West | K54: Ado-Ekiti | L54: Food & Beverages | M54: =TRIM(Table2[[#This Row],[Category]]) -> Food & Beverages | N54: Cooking Oil | O54: Groundnut Oil 3L | P54: 11 | Q54: 5909.8 | R54: 15 | S54: 9751.17 | T54: 55256.63 | U54: 11809.74
A55: ORD-10980 | B55: 44799 | C55: 44805 | D55: Standard Class | E55: Gbenga | F55: Otedola | G55: gbenga.otedola@gmail.com | H55: 9029855180 | I55: Home Office | J55: East | K55: Aba | L55: Clothing | M55: =TRIM(Table2[[#This Row],[Category]]) -> Clothing | N55: Trousers | O55: Joggers | P55: 16 | Q55: 14832.93 | R55: 25 | S55: 59331.72 | T55: 177995.16 | U55: 51973.67
A56: ORD-10611 | B56: 44802 | C56: 44809 | D56: Standard Class | E56: Obinna | F56: Sanusi | G56: obinna.sanusi@gmail.com | H56: 8109753488 | I56: Home Office | J56: South | K56: Port Harcourt | L56: OFFICE SUPPLIES | M56: =TRIM(Table2[[#This Row],[Category]]) -> OFFICE SUPPLIES | N56: Paper | O56: A3 Paper Ream | P56: 18 | Q56: 15349.71 | R56: 0 | S56: 0 | T56: 276294.78 | U56: 44427.36
A57: ORD-10804 | B57: 44808 | C57: 44815 | D57: Standard Class | E57: Nike | F57: Bello | G57: nike.bello@outlook.com | H57: 9074026890 | I57: Home Office | J57: West | K57: Abeokuta | L57: Food & Beverages | M57: =TRIM(Table2[[#This Row],[Category]]) -> Food & Beverages | N57: Condiments | O57: Maggi Cubes 100pk | P57: 16 | Q57: 7231.78 | R57: 5 | S57: 5785.42 | T57: 109923.06 | U57: 23314.9
A58: ORD-10729 | B58: 44820 | C58: 44826 | D58: Standard Class | E58: Wale | F58: Ogundipe | G58: wale.ogundipe@outlook.com | H58: 7038684482 | I58: Consumer | J58: South | K58: Ibadan | L58: Food & Beverages | M58: =TRIM(Table2[[#This Row],[Category]]) -> Food & Beverages | N58: Snacks | O58: Plantain Chips 200g | P58: 2 | Q58: 4681.83 | R58: 0 | S58: 0 | T58: 9363.66 | U58: 430.29
A59: ORD-10622 | B59: 44820 | C59: 44827 | D59: Standard Class | E59: Seun | F59: Buhari | G59: seun.buhari@hotmail.com | H59: 9078495720 | I59: Corporate | J59: South | K59: Port Harcourt | L59: Technology | M59: =TRIM(Table2[[#This Row],[Category]]) -> Technology | N59: Printers | O59: HP LaserJet Pro | P59: 16 | Q59: ₦119,627.70 | R59: 20 | S59: 382808.64 | T59: 1531234.6 | U59: 667326.83
A60: ORD-10766 | B60: 44822 | C60: 44829 | D60: Standard Class | E60: Tunde | F60: Osei | G60: tunde.osei@outlook.com | H60: 8134503204 | I60: Home Office | J60: North | K60: Katsina | L60: Furniture | M60: =TRIM(Table2[[#This Row],[Category]]) -> Furniture | N60: Bookcases | O60: 3-Shelf Display | P60: 9 | Q60: 80976.79 | R60: 5 | S60: 36439.56 | T60: 692351.55 | U60: 285097.46
A61: ORD-10537 | B61: 44830 | C61: 44837 | D61: Standard Class | E61: Lanre | F61: Lawal | G61: lanre.lawal@gmail.com | H61: 8036101515 | I61: Corporate | J61: South | K61: Port Harcourt | L61: Clothing | M61: =TRIM(Table2[[#This Row],[Category]]) -> Clothing | N61: Trousers | O61: Jeans Straight Cut | P61: 16 | Q61: 7915.12 | R61: 10 | S61: 12664.19 | T61: 113977.73 | U61: 44261.07
A62: ORD-10608 | B62: 44829 | C62: 44837 | D62: Standard Class | E62: Obinna | F62: Adeyemi | G62: obinna.adeyemi@yahoo.com | H62: 9074720435 | I62: Corporate | J62: North | K62: Katsina | L62: Office Supplies | M62: =TRIM(Table2[[#This Row],[Category]]) -> Office Supplies | N62: Binders | O62: Expanding File | P62: 13 | Q62: 21091.19 | R62: 10 | S62: 27418.55 | T62: 246766.92 | U62: 60594.76
A63: ORD-10492 | B63: 44837 | C63: 44842 | D63: Standard Class | E63: Nike | F63: Fashola | G63: nike.fashola@outlook.com | H63: 8131690263 | I63: Home Office | J63: East | K63: Aba | L63: Clothing | M63: =TRIM(Table2[[#This Row],[Category]]) -> Clothing | N63: Accessories | O63: Wallet Genuine Leather | P63: 15 | Q63: 16464.08 | R63: 20 | S63: 49392.24 | T63: 197568.96 | U63: 21634.47
A64: ORD-10932 | B64: 44840 | C64: 44848 | D64: Standard Class | E64: Wale | F64: Otedola | G64: wale.otedola@outlook.com | H64: 8061544925 | I64: Home Office | J64: North | K64: Katsina | L64: Office Supplies | M64: =TRIM(Table2[[#This Row],[Category]]) -> Office Supplies | N64: Binders | O64: Clipboard | P64: 14 | Q64: 13658.5 | R64: 10 | S64: 19121.9 | T64: 172097.1 | U64: -21793.81
A65: ORD-10063 | B65: 44850 | C65: 44856 | D65: Standard Class | E65: Ikenna | F65: Lawal | G65: ikenna.lawal@outlook.com | H65: 8067619862 | I65: Corporate | J65: East | K65: Enugu | L65: Technology | M65: =TRIM(Table2[[#This Row],[Category]]) -> Technology | N65: Tablets | O65: Amazon Fire HD 10 | P65: =P64 -> 14 | Q65: 68761.1 | R65: 10 | S65: 82513.32 | T65: 742619.88 | U65: 149070.59
A66: ORD-10515 | B66: 44851 | C66: 44857 | D66: Standard Class | E66: Kemi | F66: Musa!! | G66: kemi.musa@yahoo.com | H66: 9054428815 | I66: Consumer | J66: West | K66: Abeokuta | L66: Furniture | M66: =TRIM(Table2[[#This Row],[Category]]) -> Furniture | N66: Sofas | O66: 3-Seater Sofa | P66: 15 | Q66: 81313.25 | R66: 10 | S66: 121969.88 | T66: 1097728.9 | U66: -56538.21
A67: ORD-10181 | B67: 44853 | C67: 44860 | D67: Standard Class | E67: Sade | F67: Adeleke | G67: sade.adeleke@yahoo.com | H67: 8039720112 | I67: Corporate | J67: South | K67: Warri | L67: Clothing | M67: =TRIM(Table2[[#This Row],[Category]]) -> Clothing | N67: Shoes | O67: Leather Loafers | P67: 3 | Q67: 43905.86 | R67: 0 | S67: 0 | T67: 131717.58 | U67: 20186.6
A68: ORD-10633 | B68: 44864 | C68: 44872 | D68: Standard Class | E68: Zainab | F68: Sowore | G68: zainab.sowore@yahoo.com | H68: 7039352238 | I68: Corporate | J68: West | K68: Abeokuta | L68: Technology | M68: =TRIM(Table2[[#This Row],[Category]]) -> Technology | N68: Phones | O68: Xiaomi Redmi 12 | P68: 14 | Q68: 337340.41 | R68: 10 | S68: 472276.57 | T68: 4250489.17 | U68: -111428.65
A69: ORD-10672 | B69: 44869 | C69: 44877 | D69: Standard Class | E69: Sade | F69: Musa | G69: sade.musa@yahoo.com | H69: 9059447259 | I69: Corporate | J69: East | K69: Onitsha | L69: Food & Beverages | M69: =TRIM(Table2[[#This Row],[Category]]) -> Food & Beverages | N69: Condiments | O69: Pepper Mix 200g | P69: 4 | Q69: 4450.05 | R69: -10 | S69: 4450.05 | T69: 13350.15 | U69: 4391.18
A70: ORD-10391 | B70: 44877 | C70: 44884 | D70: Standard Class | E70: Gbenga_Tinubu | F70: =F69 -> Musa | G70: gbenga.tinubu@hotmail.com | H70: 8065826621 | I70: Consumer | J70: West | K70: Ilorin | L70: Clothing | M70: =TRIM(Table2[[#This Row],[Category]]) -> Clothing | N70: Trousers | O70: Formal Trousers | P70: 8 | Q70: 40992.11 | R70: 0 | S70: 0 | T70: 327936.88 | U70: -25706.05
A71: ORD-10833 | B71: 44881 | C71: 44889 | D71: Standard Class | E71: Adaeze | F71: Sule | G71: user@@domain.com | H71: 9053046457 | I71: Home Office | J71: North | K71: Abuja | L71: Technology | M71: =TRIM(Table2[[#This Row],[Category]]) -> Technology | N71: Phones | O71: iPhone 13 | P71: 3 | Q71: 414330.94 | R71: 0 | S71: 0 | T71: 1242992.8 | U71: -118056.56
A72: ORD-10954 | B72: 44884 | C72: 44890 | D72: Standard Class | E72: Tunde | F72: Okafor | G72: tunde.okafor@hotmail.com | H72: 8068291687 | I72: Consumer | J72: South | K72: Warri | L72: Furniture | M72: =TRIM(Table2[[#This Row],[Category]]) -> Furniture | N72: Tables | O72: Study Table | P72: 18 | Q72: 130755.89 | R72: 25 | S72: 588401.51 | T72: 1765204.5 | U72: 741350.81
A73: ORD-10671 | B73: 44890 | C73: 44897 | D73: Standard Class | E73: Emeka | F73: Eze | G73: emeka.eze@yahoo.com | H73: 9051428411 | I73: Corporate | J73: East | K73: Owerri | L73: Technology | M73: =TRIM(Table2[[#This Row],[Category]]) -> Technology | N73: Printers | O73: Canon PIXMA G3411 | P73: 17 | Q73: 366494.88 | R73: 25 | S73: 1557603.2 | T73: 4672809.7 | U73: 1495674.3
A74: ORD-10768 | B74: 44895 | C74: 44901 | D74: Standard Class | E74: Bola | F74: Sanusi | G74: bola.sanusi@outlook.com | H74: 9016316357 | I74: Consumer | J74: North | K74: Kano | L74: Clothing | M74: =TRIM(Table2[[#This Row],[Category]]) -> Clothing | N74: Trousers | O74: Women's Palazzo | P74: 17 | Q74: 44361.54 | R74: 10 | S74: 75414.62 | T74: 678731.56 | U74: 92841.91
A75: ORD-10036 | B75: 44897 | C75: 44904 | D75: Standard Class | E75: Yemi | F75: Danjuma | G75: spaces in@email.com | H75: 8167296605 | I75: Consumer | J75: East | K75: Aba | L75: Clothing | M75: =TRIM(Table2[[#This Row],[Category]]) -> Clothing | N75: Trousers | O75: Men's Chinos | P75: 8 | Q75: 27460.21 | R75: 0 | S75: 0 | T75: 219681.68 | U75: 58944.07
A76: ORD-10630 | B76: 44903 | C76: 44909 | D76: Standard Class | E76: Adaeze | F76: Fashola | G76: adaeze.fashola@yahoo.com | H76: 8038962478 | I76: Corporate | J76: South | K76: Ibadan | L76: Clothing | M76: =TRIM(Table2[[#This Row],[Category]]) -> Clothing | N76: Shoes | O76: Men's Oxford Shoes | P76: 9 | Q76: 9633.15 | R76: 0 | S76: 0 | T76: 86698.35 | U76: -4123.8
A77: ORD-10208 | B77: 44917 | C77: 44923 | D77: Standard Class | E77: Musa | F77: Gambo | G77: musa.gambo@gmail.com | H77: 8131554840 | I77: Home Office | J77: West | K77: Ilorin | L77: Clothing | M77: =TRIM(Table2[[#This Row],[Category]]) -> Clothing | N77: Shirts | O77: Corporate Shirt | P77: 9 | Q77: 32299.26 | R77: 10 | S77: 29069.33 | T77: 261624.01 | U77: 90025.81
A78: ORD-10261 | B78: 44925 | C78: 44933 | D78: Standard Class | E78: Ayo | F78: Alakija | G78: ayo.alakija@gmail.com | H78: 9029915915 | I78: Home Office | J78: West | K78: Ilorin | L78: Food & Beverages | M78: =TRIM(Table2[[#This Row],[Category]]) -> Food & Beverages | N78: Drinks | O78: Coca-Cola 24-Pack | P78: 5 | Q78: 4013.26 | R78: 25 | S78: 5016.58 | T78: 15049.72 | U78: 5214.92
A79: ORD-10405 | B79: 44928 | C79: 44936 | D79: Standard Class | E79: Deola | F79: Sowore | G79: deola.sowore@outlook.com | H79: 8106079345 | I79: Corporate | J79: North | K79: Kano | L79: Food & Beverages | M79: =TRIM(Table2[[#This Row],[Category]]) -> Food & Beverages | N79: Condiments | O79: Tomato Paste 400g | P79: 17 | Q79: 6153.32 | R79: 20 | S79: 20921.29 | T79: 83685.15 | U79: 27251.14
A80: ORD-10368 | B80: 44930 | C80: 44938 | D80: Standard Class | E80: Ayo | F80: Musa | G80: ayo.musa@outlook.com | H80: 7038026061 | I80: Home Office | J80: South | K80: Ibadan | L80: Technology | M80: =TRIM(Table2[[#This Row],[Category]]) -> Technology | N80: Printers | O80: Canon PIXMA G3411 | P80: 17 | Q80: 98477.74 | R80: 0 | S80: 0 | T80: 1674121.6 | U80: 370571.1
A81: ORD-10984 | B81: 44940 | C81: 44946 | D81: Standard Class | E81: Nike | F81: Buhari | G81: nike.buhari@yahoo.com | H81: 9028212098 | I81: CONSUMER | J81: South | K81: Ibadan | L81: Technology | M81: =TRIM(Table2[[#This Row],[Category]]) -> Technology | N81: Accessories | O81: Wallet Genuine Leather | P81: 2 | Q81: 43307.01 | R81: 15 | S81: 12992.1 | T81: 73621.92 | U81: 16442.04
A82: ORD-10311 | B82: 44943 | C82: 44949 | D82: Standard Class | E82: Dayo | F82: Fashola | G82: dayo.fashola@gmail.com | H82: 8035150551 | I82: Corporate | J82: North | K82: Abuja | L82: Food & Beverages | M82: =TRIM(Table2[[#This Row],[Category]]) -> Food & Beverages | N82: Grains | O82: Garri 10kg | P82: 6 | Q82: 4072.48 | R82: 0 | S82: 0 | T82: 24434.88 | U82: 1418.88
... A90: ORD-10450 | B90: 44982 | C90: 44989 | D90: Standard Class | E90: Aisha | F90: Atiku | G90: missing@ | H90: 9018407441 | I90: Home Office | J90: North | K90: Kaduna | L90: Food & Beverages | M90: =TRIM(Table2[[#This Row],[Category]]) -> Food & Beverages | N90: Cooking Oil | O90: Vegetable Oil 5L | P90: 12 | Q90: 1488.08 | R90: 10 | S90: 1785.7 | T90: 16071.26 | U90: 5488.28
A91: ORD-10542 | B91: 44986 | C91: 44991 | D91: Standard Class | E91: Fatima | F91: Lawal | G91: fatima.lawal@yahoo.com | H91: 8038503322 | I91: Home Office | J91: West | K91: Abeokuta | L91: Office Supplies | M91: =TRIM(Table2[[#This Row],[Category]]) -> Office Supplies | N91: Paper | O91: A4 Paper 500 Sheets | P91: 7 | Q91: 3655.99 | R91: 0% | S91: 0 | T91: 25591.93 | U91: -2490.29
A92: ORD-10336 | B92: 44985 | C92: 44992 | D92: Standard Class | E92: Taiwo | F92: Osei | G92: taiwo.osei@outlook.com | H92: 8105752443 | I92: Home Office | J92: North | K92: Kano | L92: Food & Beverages | M92: =TRIM(Table2[[#This Row],[Category]]) -> Food & Beverages | N92: Snacks | O92: Pringles Multipack | P92: 20 | Q92: 848.57 | R92: 10 | S92: 1697.14 | T92: 15274.26 | U92: 2663.01
A93: ORD-10045 | B93: 44987 | C93: 44993 | D93: Standard Class | E93: Tobi | F93: Sowore | G93: tobi.sowore@gmail.com | H93: 8105024269 | I93: Home Office | J93: North | K93: Katsina | L93: Furniture | M93: =TRIM(Table2[[#This Row],[Category]]) -> Furniture | N93: Sofas | O93: 3-Seater Sofa | P93: 14 | Q93: 34923.61 | R93: 20 | S93: 97786.11 | T93: 391144.43 | U93: 103114.54
A94: ORD-10067 | B94: 44996 | C94: 45001 | D94: Standard Class | E94: Ngozi | F94: Sule | G94: ngozi.sule@outlook.com | H94: 8133112652 | I94: Corporate | J94: South | K94: Lagos | L94: Food & Beverages | M94: =TRIM(Table2[[#This Row],[Category]]) -> Food & Beverages | N94: Snacks | O94: Digestive Biscuits | P94: 18 | Q94: 6689.6 | R94: 5 | S94: 6020.64 | T94: 114392.16 | U94: 23087.75
A95: ORD-10680 | B95: 44993 | C95: 45001 | D95: Standard Class | E95: Ronke | F95: Chukwu | G95: ronke.chukwu@outlook.com | H95: 8066827492 | I95: Consumer | J95: East | K95: Onitsha | L95: Office Supplies | M95: =TRIM(Table2[[#This Row],[Category]]) -> Office Supplies | N95: Binders | O95: Ring Binder A4 | P95: 16 | Q95: 7552.16 | R95: 20 | S95: 24166.91 | T95: 96667.65 | U95: -1529.28
A96: ORD-10809 | B96: 45001 | C96: 45006 | D96: Standard Class | E96: Adebayo | F96: Adeyemi | G96: adebayo.adeyemi@yahoo.com | H96: 9016373918 | I96: Corporate | J96: South | K96: Port Harcourt | L96: Technology | M96: =TRIM(Table2[[#This Row],[Category]]) -> Technology | N96: Phones | O96: Infinix Note 30 | P96: 20 | Q96: 104930.57 | R96: 0 | S96: 0 | T96: 2098611.4 | U96: -257834.71
A97: ORD-10612 | B97: 45006 | C97: 45011 | D97: Standard Class | E97: Chisom | F97: Okafor | G97: chisom.okafor@yahoo.com | H97: 8063123664 | I97: Corporate | J97: South | K97: Ibadan | L97: Office Supplies | M97: =TRIM(Table2[[#This Row],[Category]]) -> Office Supplies | N97: Pens & Pencils | O97: Whiteboard Markers | P97: 3 | Q97: 5381.32 | R97: 10 | S97: 1614.4 | T97: 14529.56 | U97: 3993.45
A98: ORD-10232 | B98: 45016 | C98: 45021 | D98: Standard Class | E98: Adaeze | F98: Adebayo | G98: adaeze.adebayo@outlook.com | H98: 8159757456 | I98: Consumer | J98: East | K98: Owerri | L98: Office Supplies | M98: =TRIM(Table2[[#This Row],[Category]]) -> Office Supplies | N98: Fasteners | O98: Stapler + Staples | P98: 6 | Q98: 1621.56 | R98: 20 | S98: 1945.87 | T98: 7783.49 | U98: =U97 -> 3993.45
A99: ORD-10818 | B99: 45021 | C99: 45026 | D99: Standard Class | E99: Kehinde | F99: Otedola | G99: kehinde.otedola@gmail.com | H99: 8038993139 | I99: Home Office | J99: North | K99: Sokoto | L99: Food & Beverages | M99: =TRIM(Table2[[#This Row],[Category]]) -> Food & Beverages | N99: Cooking Oil | O99: Groundnut Oil 3L | P99: 13 | Q99: 5579.2 | R99: 20 | S99: 14505.92 | T99: 58023.68 | U99: 22985.77
A100: ORD-10669 | B100: 45028 | C100: 45033 | D100: Standard Class | E100: Tobi | F100: Chukwu | G100: tobi.chukwu@gmail.com | H100: 9076927978 | I100: Corporate | J100: West | K100: Ado-Ekiti | L100: Food & Beverages | M100: =TRIM(Table2[[#This Row],[Category]]) -> Food & Beverages | N100: Drinks | O100: Energy Drink 4-Pack | P100: 4 | Q100: 2107.17 | R100: 0 | S100: 0 | T100: 8428.68 | U100: 1299.39
A101: ORD-10177 | B101: 45029 | C101: 45034 | D101: Standard Class | E101: Emeka | F101: Lawal | G101: unknown | H101: 8131771442 | I101: Home Office | J101: East | K101: Enugu | L101: Clothing | M101: =TRIM(Table2[[#This Row],[Category]]) -> Clothing | N101: Shoes | O101: Leather Loafers | P101: 6 | Q101: 41569.74 | R101: 0 | S101: 0 | T101: 249418.44 | U101: 45324.04
A102: ORD-10659 | B102: 45027 | C102: 45035 | D102: STANDARD CLASS | E102: Bukola | F102: Danjuma | G102: bukola.danjuma@gmail.com | H102: 9021249956 | I102: Consumer | J102: South | K102: Ibadan | L102: Furniture | M102: =TRIM(Table2[[#This Row],[Category]]) -> Furniture | N102: Chairs | O102: Executive Chair | P102: 15 | Q102: 17744.59 | R102: 0 | S102: 0 | T102: 266168.85 | U102: 5205.62
A103: ORD-10011 | B103: 45033 | C103: 45039 | D103: Standard Class | E103: Chidi | F103: Musa | G103: chidi.musa@gmail.com | H103: +234 803 123 4567 | I103: Corporate | J103: South | K103: Lagos | L103: Technology | M103: =TRIM(Table2[[#This Row],[Category]]) -> Technology | N103: Tablets | O103: iPad 10th Gen | P103: 9 | Q103: 238657.91 | R103: 20 | S103: 429584.24 | T103: 1718336.95 | U103: -36871.93
A104: ORD-10940 | B104: 45034 | C104: 45040 | D104: Standard Class | E104: Emeka | F104: Atiku | G104: emeka.atiku@gmail.com | H104: 9077622282 | I104: Consumer | J104: North | K104: Kaduna | L104: Furniture | M104: =TRIM(Table2[[#This Row],[Category]]) -> Furniture | N104: Tables | O104: Study Table | P104: 19 | Q104: 173016.77 | R104: 0 | S104: 0 | T104: 3287318.6 | U104: 792611.31
A105: ORD-10512 | B105: 45038 | C105: 45043 | D105: Standard Class | E105: Ayo | F105: Buhari | G105: ayo.buhari@gmail.com | H105: 8164966072 | I105: Home Office | J105: South | K105: Port Harcourt | L105: Clothing | M105: =TRIM(Table2[[#This Row],[Category]]) -> Clothing | N105: Trousers | O105: Jeans Straight Cut | P105: 5 | Q105: 5413.75 | R105: 10 | S105: 2706.88 | T105: 24361.87 | U105: 3635.67
A106: ORD-10681 | B106: 45036 | C106: 45043 | D106: Standard Class | E106: Seun | F106: Bello | G106: seun.bello@yahoo.com | H106: 8159534539 | I106: Corporate | J106: South | K106: Benin City | L106: Furniture | M106: =TRIM(Table2[[#This Row],[Category]]) -> Furniture | N106: Chairs | O106: Gaming Chair | P106: 18 | Q106: 163237.1 | R106: 25 | S106: 734566.95 | T106: 2203700.9 | U106: 725888.48
A107: ORD-10016 | B107: 45043 | C107: 45051 | D107: Standard Class | E107: Bola | F107: Danjuma | G107: bola.danjuma@yahoo.com | H107: 9051666754 | I107: CONSUMER | J107: North | K107: Kaduna | L107: Food & Beverages | M107: =TRIM(Table2[[#This Row],[Category]]) -> Food & Beverages | N107: Drinks | O107: Fruit Juice 1L | P107: 19 | Q107: 5361.77 | R107: 25 | S107: 25468.41 | T107: 76405.22 | U107: 3042.6
...

Sheet Raw Data
A1: Order ID | B1: Order Date | C1: Ship Date | D1: Ship Mode | E1: First Name | F1: Last Name | G1: Email | H1: Phone | I1: Segment | J1: Region | K1: State | L1: Category | M1: Sub-Category | N1: Product Name | O1: Quantity | P1: Unit Price (₦) | Q1: Discount (%) | R1: Discount Amount (₦) | S1: Sales (₦) | T1: Profit (₦) | U1: Category_titleCase | V1: ABS(Absolute Value) | W1: Order Classification | X1: Nested If Condition | Y1: Discount Decision
A2: ORD-10858 | B2: 44562 | C2: 44567 | D2: Standard Class | E2: Ayo | F2: Adeleke | G2: ayo.adeleke@gmail.com | H2: 8161000159 | I2: Consumer | J2: East | K2: Onitsha | L2: Office Supplies | M2: Envelopes | N2: Brown Kraft Envelopes | O2: 6 | P2: 18354.33 | Q2: 0 | R2: 0 | S2: 110125.98 | T2: -12981.35 | U2: =PROPER(L2) -> Office Supplies | V2: =ABS(T2) -> 12981.35 | W2: =IF(Sales[[#This Row],[Quantity]]>=15, "Large","Small") -> Small | X2: =IF(Sales[[#This Row],[Quantity]]>=15,"Large",IF(Sales[[#This Row],[Quantity]]=14,"Medium","Small")) -> Small | Y2: =IF(AND(Sales[[#This Row],[Unit Price (₦)]]>68000,Sales[[#This Row],[Quantity]]>15),"Offer Discount", "No Discount") -> No Discount
A3: ORD-10441 | B3: 44573 | C3: 44581 | D3: Standard Class | E3: Bola | F3: Okonkwo | G3: bola.okonkwo@yahoo.com | H3: 9079004743 | I3: Corporate | J3: East | K3: Enugu | L3: Clothing | M3: Bags | N3: Crossbody Bag | O3: 10 | P3: 33214.19 | Q3: 10 | R3: 33214.19 | S3: 298927.71 | T3: 79035.7 | U3: =PROPER(L3) -> Clothing | V3: =ABS(T3) -> 79035.7 | W3: =IF(Sales[[#This Row],[Quantity]]>=15, "Large","Small") -> Small | X3: =IF(Sales[[#This Row],[Quantity]]>=15,"Large",IF(Sales[[#This Row],[Quantity]]=14,"Medium","Small")) -> Small | Y3: =IF(AND(Sales[[#This Row],[Unit Price (₦)]]>68000,Sales[[#This Row],[Quantity]]>15),"Offer Discount", "No Discount") -> No Discount
A4: ORD-10505 | B4: 44583 | C4: 44590 | D4: Standard Class | E4: Bola | F4: Obi | G4: bola.obi@yahoo.com | H4: 7038788747 | I4: Corporate | J4: West | K4: Ilorin | L4: Clothing | M4: Bags | N4: Laptop Backpack | O4: 8 | P4: 5549.59 | Q4: 20 | R4: 8879.34 | S4: 35517.38 | T4: -2338.7 | U4: =PROPER(L4) -> Clothing | V4: =ABS(T4) -> 2338.7 | W4: =IF(Sales[[#This Row],[Quantity]]>=15, "Large","Small") -> Small | X4: =IF(Sales[[#This Row],[Quantity]]>=15,"Large",IF(Sales[[#This Row],[Quantity]]=14,"Medium","Small")) -> Small | Y4: =IF(AND(Sales[[#This Row],[Unit Price (₦)]]>68000,Sales[[#This Row],[Quantity]]>15),"Offer Discount", "No Discount") -> No Discount
A5: ORD-10382 | B5: 44607 | C5: 44613 | D5: Standard Class | E5: Ronke | F5: Tinubu | G5: ronke.tinubu@outlook.com | H5: 7066751103 | I5: Consumer | J5: North | K5: Abuja | L5: Office Supplies | M5: Envelopes | N5: C5 Envelopes | O5: 17 | P5: 16813.46 | Q5: 25 | R5: 71457.21 | S5: 214371.61 | T5: 25114.44 | U5: =PROPER(L5) -> Office Supplies | V5: =ABS(T5) -> 25114.44 | W5: =IF(Sales[[#This Row],[Quantity]]>=15, "Large","Small") -> Large | X5: =IF(Sales[[#This Row],[Quantity]]>=15,"Large",IF(Sales[[#This Row],[Quantity]]=14,"Medium","Small")) -> Large | Y5: =IF(AND(Sales[[#This Row],[Unit Price (₦)]]>68000,Sales[[#This Row],[Quantity]]>15),"Offer Discount", "No Discount") -> No Discount
A6: ORD-10832 | B6: 44609 | C6: 44615 | D6: Standard Class | E6: Yemi | F6: Abubakar | G6: yemi.abubakar@gmail.com | H6: 8107264416 | I6: Home Office | J6: West | K6: Abuja | L6: Technology | M6: Phones | N6: Xiaomi Redmi 12 | O6: 3 | P6: 363633.82 | Q6: 0 | R6: 0 | S6: 1090901.5 | T6: -157322.01 | U6: =PROPER(L6) -> Technology | V6: =ABS(T6) -> 157322.01 | W6: =IF(Sales[[#This Row],[Quantity]]>=15, "Large","Small") -> Small | X6: =IF(Sales[[#This Row],[Quantity]]>=15,"Large",IF(Sales[[#This Row],[Quantity]]=14,"Medium","Small")) -> Small | Y6: =IF(AND(Sales[[#This Row],[Unit Price (₦)]]>68000,Sales[[#This Row],[Quantity]]>15),"Offer Discount", "No Discount") -> No Discount
A7: ORD-10852 | B7: 44611 | C7: 44616 | D7: Standard Class | E7: Zainab | F7: Sanusi | G7: zainab.sanusi@gmail.com | H7: 8034674225 | I7: Consumer | J7: East | K7: Onitsha | L7: Furniture | M7: Tables | N7: Conference Table | O7: 11 | P7: 94100.43 | Q7: 15 | R7: 155265.71 | S7: 879839.02 | T7: 267099.63 | U7: =PROPER(L7) -> Furniture | V7: =ABS(T7) -> 267099.63 | W7: =IF(Sales[[#This Row],[Quantity]]>=15, "Large","Small") -> Small | X7: =IF(Sales[[#This Row],[Quantity]]>=15,"Large",IF(Sales[[#This Row],[Quantity]]=14,"Medium","Small")) -> Small | Y7: =IF(AND(Sales[[#This Row],[Unit Price (₦)]]>68000,Sales[[#This Row],[Quantity]]>15),"Offer Discount", "No Discount") -> No Discount
A8: ORD-10959 | B8: 44624 | C8: 44629 | D8: Standard Class | E8: Chisom | F8: Adeyemi | G8: chisom.adeyemi@gmail.com | H8: 8064194751 | I8: Home Office | J8: North | K8: Kano | L8: Clothing | M8: Shirts | N8: T-Shirt 3-Pack | O8: 18 | P8: 35696.94 | Q8: 10 | R8: 64254.49 | S8: 578290.43 | T8: -66880.13 | U8: =PROPER(L8) -> Clothing | V8: =ABS(T8) -> 66880.13 | W8: =IF(Sales[[#This Row],[Quantity]]>=15, "Large","Small") -> Large | X8: =IF(Sales[[#This Row],[Quantity]]>=15,"Large",IF(Sales[[#This Row],[Quantity]]=14,"Medium","Small")) -> Large | Y8: =IF(AND(Sales[[#This Row],[Unit Price (₦)]]>68000,Sales[[#This Row],[Quantity]]>15),"Offer Discount", "No Discount") -> No Discount
A9: ORD-10160 | B9: 44625 | C9: 44631 | D9: Standard Class | E9: Nike | F9: Adeleke | G9: nike.adeleke@outlook.com | H9: 8135843084 | I9: Consumer | J9: West | K9: Akure | L9: Furniture | M9: Storage | N9: Wardrobe 3-Door | O9: 16 | P9: 135713.14 | Q9: 25 | R9: 542852.56 | S9: 1628557.7 | T9: 254842.55 | U9: =PROPER(L9) -> Furniture | V9: =ABS(T9) -> 254842.55 | W9: =IF(Sales[[#This Row],[Quantity]]>=15, "Large","Small") -> Large | X9: =IF(Sales[[#This Row],[Quantity]]>=15,"Large",IF(Sales[[#This Row],[Quantity]]=14,"Medium","Small")) -> Large | Y9: =IF(AND(Sales[[#This Row],[Unit Price (₦)]]>68000,Sales[[#This Row],[Quantity]]>15),"Offer Discount", "No Discount") -> Offer Discount
A10: ORD-10364 | B10: 44637 | C10: 44643 | D10: Standard Class | E10: Wale | F10: Tinubu | G10: wale.tinubu@gmail.com | H10: 8141768424 | I10: Consumer | J10: South | K10: Port Harcourt | L10: Furniture | M10: Tables | N10: Office Desk 120cm | O10: 2 | P10: 37626.83 | Q10: 10 | R10: 7525.37 | S10: 67728.29 | T10: 23193.11 | U10: =PROPER(L10) -> Furniture | V10: =ABS(T10) -> 23193.11 | W10: =IF(Sales[[#This Row],[Quantity]]>=15, "Large","Small") -> Small | X10: =IF(Sales[[#This Row],[Quantity]]>=15,"Large",IF(Sales[[#This Row],[Quantity]]=14,"Medium","Small")) -> Small | Y10: =IF(AND(Sales[[#This Row],[Unit Price (₦)]]>68000,Sales[[#This Row],[Quantity]]>15),"Offer Discount", "No Discount") -> No Discount
A11: ORD-10035 | B11: 44644 | C11: 44649 | D11: Standard Class | E11: Hauwa | F11: Nwosu | G11: hauwa.nwosu@gmail.com | H11: 9053556551 | I11: Consumer | J11: North | K11: Abuja | L11: Furniture | M11: Tables | N11: Dining Table 6-Seater | O11: 19 | P11: 123146.92 | Q11: 5 | R11: 116989.57 | S11: 2222801.9 | T11: 286786.77 | U11: =PROPER(L11) -> Furniture | V11: =ABS(T11) -> 286786.77 | W11: =IF(Sales[[#This Row],[Quantity]]>=15, "Large","Small") -> Large | X11: =IF(Sales[[#This Row],[Quantity]]>=15,"Large",IF(Sales[[#This Row],[Quantity]]=14,"Medium","Small")) -> Large | Y11: =IF(AND(Sales[[#This Row],[Unit Price (₦)]]>68000,Sales[[#This Row],[Quantity]]>15),"Offer Discount", "No Discount") -> Offer Discount
A12: ORD-10296 | B12: 44651 | C12: 44657 | D12: Standard Class | E12: Fatima | F12: Lawal | G12: fatima.lawal@gmail.com | H12: 8132796087 | I12: Home Office | J12: North | K12: Kano | L12: Clothing | M12: Trousers | N12: Men's Chinos | O12: 13 | P12: 3368.14 | Q12: 20 | R12: 8757.16 | S12: 35028.66 | T12: 5796.99 | U12: =PROPER(L12) -> Clothing | V12: =ABS(T12) -> 5796.99 | W12: =IF(Sales[[#This Row],[Quantity]]>=15, "Large","Small") -> Small | X12: =IF(Sales[[#This Row],[Quantity]]>=15,"Large",IF(Sales[[#This Row],[Quantity]]=14,"Medium","Small")) -> Small | Y12: =IF(AND(Sales[[#This Row],[Unit Price (₦)]]>68000,Sales[[#This Row],[Quantity]]>15),"Offer Discount", "No Discount") -> No Discount
A13: ORD-10166 | B13: 44656 | C13: 44661 | D13: Standard Class | E13: Adebayo | F13: Okonkwo | G13: adebayo.okonkwo@gmail.com | H13: 8033650523 | I13: Home Office | J13: West | K13: Osogbo | L13: Clothing | M13: Bags | N13: Laptop Backpack | O13: 14 | P13: 44649.04 | Q13: 5 | R13: 31254.33 | S13: 593832.23 | T13: 265690.3 | U13: =PROPER(L13) -> Clothing | V13: =ABS(T13) -> 265690.3 | W13: =IF(Sales[[#This Row],[Quantity]]>=15, "Large","Small") -> Small | X13: =IF(Sales[[#This Row],[Quantity]]>=15,"Large",IF(Sales[[#This Row],[Quantity]]=14,"Medium","Small")) -> Medium | Y13: =IF(AND(Sales[[#This Row],[Unit Price (₦)]]>68000,Sales[[#This Row],[Quantity]]>15),"Offer Discount", "No Discount") -> No Discount
A14: ORD-10092 | B14: 44659 | C14: 44665 | D14: Standard Class | E14: =E15 -> Amara | F14: =F13 -> Okonkwo | G14: chibundo.tinubu@hotmail.com | H14: 8062859886 | I14: Corporate | J14: East | K14: Onitsha | L14: Clothing | M14: Accessories | N14: Wallet Genuine Leather | O14: 17 | P14: 2706.72 | Q14: 5 | R14: 2300.71 | S14: 43713.53 | T14: 12289.04 | U14: =PROPER(L14) -> Clothing | V14: =ABS(T14) -> 12289.04 | W14: =IF(Sales[[#This Row],[Quantity]]>=15, "Large","Small") -> Large | X14: =IF(Sales[[#This Row],[Quantity]]>=15,"Large",IF(Sales[[#This Row],[Quantity]]=14,"Medium","Small")) -> Large | Y14: =IF(AND(Sales[[#This Row],[Unit Price (₦)]]>68000,Sales[[#This Row],[Quantity]]>15),"Offer Discount", "No Discount") -> No Discount
A15: ORD-10221 | B15: 44660 | C15: 44665 | D15: Standard Class | E15: Amara | F15: Adeleke | G15: N/A | H15: 7068454356 | I15: Home Office | J15: East | K15: Awka | L15: Clothing | M15: Shirts | N15: Ankara Print Shirt | O15: 5 | P15: 12867.75 | Q15: 5 | R15: 3216.94 | S15: 61121.81 | T15: 16326.57 | U15: =PROPER(L15) -> Clothing | V15: =ABS(T15) -> 16326.57 | W15: =IF(Sales[[#This Row],[Quantity]]>=15, "Large","Small") -> Small | X15: =IF(Sales[[#This Row],[Quantity]]>=15,"Large",IF(Sales[[#This Row],[Quantity]]=14,"Medium","Small")) -> Small | Y15: =IF(AND(Sales[[#This Row],[Unit Price (₦)]]>68000,Sales[[#This Row],[Quantity]]>15),"Offer Discount", "No Discount") -> No Discount
A16: ORD-10971 | B16: 44660 | C16: 44666 | D16: Standard Class | E16: Hauwa | F16: Danjuma | G16: hauwa.danjuma@gmail.com | H16: 9074321723 | I16: Corporate | J16: West | K16: Ado-Ekiti | L16: Clothing | M16: Trousers | N16: Women's Palazzo | O16: 11 | P16: 19414.76 | Q16: 5 | R16: 10678.12 | S16: 202884.24 | T16: -25659.44 | U16: =PROPER(L16) -> Clothing | V16: =ABS(T16) -> 25659.44 | W16: =IF(Sales[[#This Row],[Quantity]]>=15, "Large","Small") -> Small | X16: =IF(Sales[[#This Row],[Quantity]]>=15,"Large",IF(Sales[[#This Row],[Quantity]]=14,"Medium","Small")) -> Small | Y16: =IF(AND(Sales[[#This Row],[Unit Price (₦)]]>68000,Sales[[#This Row],[Quantity]]>15),"Offer Discount", "No Discount") -> No Discount
A17: ORD-10563 | B17: 44668 | C17: 44675 | D17: Standard Class | E17: Ibrahim | F17: Eze | G17: ibrahim.eze@hotmail.com | H17: 8162690500 | I17: Consumer | J17: North | K17: Kaduna | L17: Clothing | M17: Trousers | N17: Joggers | O17: 12 | P17: 42778.11 | Q17: 10 | R17: 51333.73 | S17: 462003.59 | T17: 15067.79 | U17: =PROPER(L17) -> Clothing | V17: =ABS(T17) -> 15067.79 | W17: =IF(Sales[[#This Row],[Quantity]]>=15, "Large","Small") -> Small | X17: =IF(Sales[[#This Row],[Quantity]]>=15,"Large",IF(Sales[[#This Row],[Quantity]]=14,"Medium","Small")) -> Small | Y17: =IF(AND(Sales[[#This Row],[Unit Price (₦)]]>68000,Sales[[#This Row],[Quantity]]>15),"Offer Discount", "No Discount") -> No Discount
A18: ORD-10621 | B18: 44669 | C18: 44676 | D18: Standard Class | E18: Emeka | F18: Bello | G18: emeka.bello@gmail.com | H18: 8162258998 | I18: Home Office | J18: South | K18: Benin City | L18: Office Supplies | M18: Pens & Pencils | N18: Highlighters Set | O18: 13 | P18: 19894.88 | Q18: 10 | R18: 25863.34 | S18: 232770.1 | T18: 62661.45 | U18: =PROPER(L18) -> Office Supplies | V18: =ABS(T18) -> 62661.45 | W18: =IF(Sales[[#This Row],[Quantity]]>=15, "Large","Small") -> Small | X18: =IF(Sales[[#This Row],[Quantity]]>=15,"Large",IF(Sales[[#This Row],[Quantity]]=14,"Medium","Small")) -> Small | Y18: =IF(AND(Sales[[#This Row],[Unit Price (₦)]]>68000,Sales[[#This Row],[Quantity]]>15),"Offer Discount", "No Discount") -> No Discount
A19: ORD-10127 | B19: 44685 | C19: 44690 | D19: Standard Class | E19: Kunle | F19: Adeleke | G19: kunle.adeleke@outlook.com | H19: 7064019585 | I19: Corporate | J19: North | K19: Sokoto | L19: Furniture | M19: Storage | N19: Plastic Drawers | O19: 13 | P19: 178771.33 | Q19: 20 | R19: 464805.46 | S19: 1859221.8 | T19: 691206.94 | U19: =PROPER(L19) -> Furniture | V19: =ABS(T19) -> 691206.94 | W19: =IF(Sales[[#This Row],[Quantity]]>=15, "Large","Small") -> Small | X19: =IF(Sales[[#This Row],[Quantity]]>=15,"Large",IF(Sales[[#This Row],[Quantity]]=14,"Medium","Small")) -> Small | Y19: =IF(AND(Sales[[#This Row],[Unit Price (₦)]]>68000,Sales[[#This Row],[Quantity]]>15),"Offer Discount", "No Discount") -> No Discount
A20: ORD-10456 | B20: 44684 | C20: 44691 | D20: Standard Class | E20: Tobi | F20: Tinubu | G20: tobi.tinubu@outlook.com | H20: 8061800824 | I20: Home Office | J20: East | K20: Abia | L20: Technology | M20: Accessories | N20: Wristwatch | O20: 1 | P20: 264009.35 | Q20: 20 | R20: 52801.87 | S20: 211207.48 | T20: 11275.98 | U20: =PROPER(L20) -> Technology | V20: =ABS(T20) -> 11275.98 | W20: =IF(Sales[[#This Row],[Quantity]]>=15, "Large","Small") -> Small | X20: =IF(Sales[[#This Row],[Quantity]]>=15,"Large",IF(Sales[[#This Row],[Quantity]]=14,"Medium","Small")) -> Small | Y20: =IF(AND(Sales[[#This Row],[Unit Price (₦)]]>68000,Sales[[#This Row],[Quantity]]>15),"Offer Discount", "No Discount") -> No Discount
A21: ORD-10782 | B21: 44683 | C21: 44691 | D21: Standard Class | E21: Kemi | F21: Okafor | G21: kemi.okafor@hotmail.com | H21: 8033688598 | I21: Home Office | J21: South | K21: Port Harcourt | L21: Furniture | M21: Storage | N21: Filing Cabinet | O21: 13 | P21: 119126.56 | Q21: 5 | R21: 77432.26 | S21: 1471213 | T21: -1259.39 | U21: =PROPER(L21) -> Furniture | V21: =ABS(T21) -> 1259.39 | W21: =IF(Sales[[#This Row],[Quantity]]>=15, "Large","Small") -> Small | X21: =IF(Sales[[#This Row],[Quantity]]>=15,"Large",IF(Sales[[#This Row],[Quantity]]=14,"Medium","Small")) -> Small | Y21: =IF(AND(Sales[[#This Row],[Unit Price (₦)]]>68000,Sales[[#This Row],[Quantity]]>15),"Offer Discount", "No Discount") -> No Discount
A22: ORD-10567 | B22: 44686 | C22: 44692 | D22: Standard Class | E22: Ikenna | F22: Sanusi | G22: ikenna.sanusi@gmail.com | H22: 8108344141 | I22: Corporate | J22: East | K22: Onitsha | L22: Food & Beverages | M22: Cooking Oil | N22: Sunflower Oil 3L | O22: -1 | P22: 6301.17 | Q22: 10 | R22: 8191.52 | S22: 73723.69 | T22: -1905.41 | U22: =PROPER(L22) -> Food & Beverages | V22: =ABS(T22) -> 1905.41 | W22: =IF(Sales[[#This Row],[Quantity]]>=15, "Large","Small") -> Small | X22: =IF(Sales[[#This Row],[Quantity]]>=15,"Large",IF(Sales[[#This Row],[Quantity]]=14,"Medium","Small")) -> Small | Y22: =IF(AND(Sales[[#This Row],[Unit Price (₦)]]>68000,Sales[[#This Row],[Quantity]]>15),"Offer Discount", "No Discount") -> No Discount
A23: ORD-10173 | B23: 44685 | C23: 44693 | D23: Standard Class | E23: Dayo | F23: Eze | G23: dayo.eze@hotmail.com | H23: 7067749095 | I23: Consumer | J23: North | K23: Abuja | L23: Technology | M23: Printers | N23: HP LaserJet Pro | O23: 9 | P23: 282980.47 | Q23: 0 | R23: 0 | S23: 2546824.2 | T23: 91543.38 | U23: =PROPER(L23) -> Technology | V23: =ABS(T23) -> 91543.38 | W23: =IF(Sales[[#This Row],[Quantity]]>=15, "Large","Small") -> Small | X23: =IF(Sales[[#This Row],[Quantity]]>=15,"Large",IF(Sales[[#This Row],[Quantity]]=14,"Medium","Small")) -> Small | Y23: =IF(AND(Sales[[#This Row],[Unit Price (₦)]]>68000,Sales[[#This Row],[Quantity]]>15),"Offer Discount", "No Discount") -> No Discount
A24: ORD-10070 | B24: 44686 | C24: 44694 | D24: Standard Class | E24: Ikenna | F24: Ogundipe | G24: ikenna.ogundipe@gmail.com | H24: 8148441741 | I24: Home Office | J24: East | K24: Owerri | L24: Technology | M24: Laptops | N24: Dell Inspiron 15 | O24: 3 | P24: 279609.38 | Q24: 0 | R24: 0 | S24: 838828.14 | T24: 12590.47 | U24: =PROPER(L24) -> Technology | V24: =ABS(T24) -> 12590.47 | W24: =IF(Sales[[#This Row],[Quantity]]>=15, "Large","Small") -> Small | X24: =IF(Sales[[#This Row],[Quantity]]>=15,"Large",IF(Sales[[#This Row],[Quantity]]=14,"Medium","Small")) -> Small | Y24: =IF(AND(Sales[[#This Row],[Unit Price (₦)]]>68000,Sales[[#This Row],[Quantity]]>15),"Offer Discount", "No Discount") -> No Discount
A25: ORD-10587 | B25: 44695 | C25: 44701 | D25: Standard Class | E25: Deola | F25: Okonkwo | G25: deola.okonkwo@outlook.com | H25: 8134384399 | I25: Home Office | J25: East | K25: Onitsha | L25: Technology | M25: Phones | N25: Tecno Spark 10 | O25: 19 | P25: 51992.12 | Q25: 0 | R25: 0 | S25: 987850.28 | T25: 185956.49 | U25: =PROPER(L25) -> Technology | V25: =ABS(T25) -> 185956.49 | W25: =IF(Sales[[#This Row],[Quantity]]>=15, "Large","Small") -> Large | X25: =IF(Sales[[#This Row],[Quantity]]>=15,"Large",IF(Sales[[#This Row],[Quantity]]=14,"Medium","Small")) -> Large | Y25: =IF(AND(Sales[[#This Row],[Unit Price (₦)]]>68000,Sales[[#This Row],[Quantity]]>15),"Offer Discount", "No Discount") -> No Discount
A26: ORD-10886 | B26: 44698 | C26: 44704 | D26: Standard Class | E26: Tobi | F26: Sanusi | G26: tobi.sanusi@hotmail.com | H26: 8155648826 | I26: Corporate | J26: West | K26: Ado-Ekiti | L26: Food & Beverages | M26: Condiments | N26: Pepper Mix 200g | O26: 2 | P26: 1833.76 | Q26: 15 | R26: 550.13 | S26: 3117.39 | T26: 707.23 | U26: =PROPER(L26) -> Food & Beverages | V26: =ABS(T26) -> 707.23 | W26: =IF(Sales[[#This Row],[Quantity]]>=15, "Large","Small") -> Small | X26: =IF(Sales[[#This Row],[Quantity]]>=15,"Large",IF(Sales[[#This Row],[Quantity]]=14,"Medium","Small")) -> Small | Y26: =IF(AND(Sales[[#This Row],[Unit Price (₦)]]>68000,Sales[[#This Row],[Quantity]]>15),"Offer Discount", "No Discount") -> No Discount
... A38: ORD-10972 | B38: 44733 | C38: 44741 | D38: Standard Class | E38: Chisom | F38: Olawale | G38: chisom.olawale@gmail.com | H38: 8149400075 | I38: Home Office | J38: West | K38: Abeokuta | L38: Clothing | M38: Accessories | N38: Wallet Genuine Leather | O38: 1 | P38: 40348.43 | Q38: 0 | R38: 0 | S38: 40348.43 | T38: -999.75 | U38: =PROPER(L38) -> Clothing | V38: =ABS(T38) -> 999.75 | W38: =IF(Sales[[#This Row],[Quantity]]>=15, "Large","Small") -> Small | X38: =IF(Sales[[#This Row],[Quantity]]>=15,"Large",IF(Sales[[#This Row],[Quantity]]=14,"Medium","Small")) -> Small | Y38: =IF(AND(Sales[[#This Row],[Unit Price (₦)]]>68000,Sales[[#This Row],[Quantity]]>15),"Offer Discount", "No Discount") -> No Discount
A39: ORD-10266 | B39: 44748 | C39: 44754 | D39: Standard Class | E39: Kunle_Alakija | F39: =F38 -> Olawale | G39: kunle.alakija@hotmail.com | H39: 8062075091 | I39: Corporate | J39: North | K39: Kaduna | L39: office supplies | M39: Binders | N39: Clipboard | O39: 2 | P39: 2460.97 | Q39: 15 | R39: 738.29 | S39: 4183.65 | T39: 1708.65 | U39: =PROPER(L39) -> Office Supplies | V39: =ABS(T39) -> 1708.65 | W39: =IF(Sales[[#This Row],[Quantity]]>=15, "Large","Small") -> Small | X39: =IF(Sales[[#This Row],[Quantity]]>=15,"Large",IF(Sales[[#This Row],[Quantity]]=14,"Medium","Small")) -> Small | Y39: =IF(AND(Sales[[#This Row],[Unit Price (₦)]]>68000,Sales[[#This Row],[Quantity]]>15),"Offer Discount", "No Discount") -> No Discount
A40: ORD-10502 | B40: 44748 | C40: 44755 | D40: Standard Class | E40: =E41 -> Yemi | F40: =F39 -> Olawale | G40: adebayo.adebayo@outlook.com | H40: 7063938131 | I40: Corporate | J40: West | K40: Akure | L40: Clothing | M40: Trousers | N40: Women's Palazzo | O40: 14 | P40: 40698.48 | Q40: 20 | R40: 113955.74 | S40: 455822.98 | T40: 36830.04 | U40: =PROPER(L40) -> Clothing | V40: =ABS(T40) -> 36830.04 | W40: =IF(Sales[[#This Row],[Quantity]]>=15, "Large","Small") -> Small | X40: =IF(Sales[[#This Row],[Quantity]]>=15,"Large",IF(Sales[[#This Row],[Quantity]]=14,"Medium","Small")) -> Medium | Y40: =IF(AND(Sales[[#This Row],[Unit Price (₦)]]>68000,Sales[[#This Row],[Quantity]]>15),"Offer Discount", "No Discount") -> No Discount
A41: ORD-10936 | B41: 44755 | C41: 44760 | D41: Standard Class | E41: Yemi | F41: Sanusi | G41: yemi.sanusi@gmail.com | H41: 8147058725 | I41: Consumer | J41: East | K41: Enugu | L41: Clothing | M41: Accessories | N41: Belt Leather | O41: 19 | P41: 13364.14 | Q41: 25 | R41: 63479.66 | S41: 190439 | T41: 73702.69 | U41: =PROPER(L41) -> Clothing | V41: =ABS(T41) -> 73702.69 | W41: =IF(Sales[[#This Row],[Quantity]]>=15, "Large","Small") -> Large | X41: =IF(Sales[[#This Row],[Quantity]]>=15,"Large",IF(Sales[[#This Row],[Quantity]]=14,"Medium","Small")) -> Large | Y41: =IF(AND(Sales[[#This Row],[Unit Price (₦)]]>68000,Sales[[#This Row],[Quantity]]>15),"Offer Discount", "No Discount") -> No Discount
A42: ORD-10225 | B42: 44756 | C42: 44761 | D42: Standard Class | E42: Chidi | F42: Lawal | G42: chidi.lawal@yahoo.com | H42: 9073860721 | I42: Home Office | J42: East | K42: Owerri | L42: Office Supplies | M42: Pens & Pencils | N42: Whiteboard Markers | O42: 9 | P42: 23899.68 | Q42: 0 | R42: 0 | S42: 215097.12 | T42: 15825.4 | U42: =PROPER(L42) -> Office Supplies | V42: =ABS(T42) -> 15825.4 | W42: =IF(Sales[[#This Row],[Quantity]]>=15, "Large","Small") -> Small | X42: =IF(Sales[[#This Row],[Quantity]]>=15,"Large",IF(Sales[[#This Row],[Quantity]]=14,"Medium","Small")) -> Small | Y42: =IF(AND(Sales[[#This Row],[Unit Price (₦)]]>68000,Sales[[#This Row],[Quantity]]>15),"Offer Discount", "No Discount") -> No Discount
A43: ORD-10065 | B43: 45126 | C43: 44767 | D43: Standard Class | E43: Bukola | F43: Okafor | G43: unknown | H43: 8147224540 | I43: Corporate | J43: North | K43: Abuja | L43: Food & Beverages | M43: Cooking Oil | N43: Sunflower Oil 3L | O43: 5 | P43: 6015.47 | Q43: 15 | R43: 4511.6 | S43: 25565.75 | T43: 6211.28 | U43: =PROPER(L43) -> Food & Beverages | V43: =ABS(T43) -> 6211.28 | W43: =IF(Sales[[#This Row],[Quantity]]>=15, "Large","Small") -> Small | X43: =IF(Sales[[#This Row],[Quantity]]>=15,"Large",IF(Sales[[#This Row],[Quantity]]=14,"Medium","Small")) -> Small | Y43: =IF(AND(Sales[[#This Row],[Unit Price (₦)]]>68000,Sales[[#This Row],[Quantity]]>15),"Offer Discount", "No Discount") -> No Discount
A44: ORD-10506 | B44: 44767 | C44: 44773 | D44: Standard Class | E44: Nike | F44: Bello | G44: nike.bello@hotmail.com | H44: 8102301665 | I44: Consumer | J44: East | K44: Onitsha | L44: Technology | M44: Tablets | N44: Samsung Tab A8 | O44: 6 | P44: 206686.23 | Q44: 5 | R44: 62005.87 | S44: 1178111.5 | T44: 328277.67 | U44: =PROPER(L44) -> Technology | V44: =ABS(T44) -> 328277.67 | W44: =IF(Sales[[#This Row],[Quantity]]>=15, "Large","Small") -> Small | X44: =IF(Sales[[#This Row],[Quantity]]>=15,"Large",IF(Sales[[#This Row],[Quantity]]=14,"Medium","Small")) -> Small | Y44: =IF(AND(Sales[[#This Row],[Unit Price (₦)]]>68000,Sales[[#This Row],[Quantity]]>15),"Offer Discount", "No Discount") -> No Discount
A45: ORD-10224 | B45: 44769 | C45: 44776 | D45: Standard Class | E45: Zainab | F45: Fashola | G45: zainab.fashola@outlook.com | H45: 8168789281 | I45: Consumer | J45: West | K45: Ilorin | L45: Technology | M45: Laptops | N45: Lenovo IdeaPad 3 | O45: 10 | P45: 395251.1 | Q45: 10 | R45: 395251.1 | S45: 3557259.9 | T45: 1177302.4 | U45: =PROPER(L45) -> Technology | V45: =ABS(T45) -> 1177302.4 | W45: =IF(Sales[[#This Row],[Quantity]]>=15, "Large","Small") -> Small | X45: =IF(Sales[[#This Row],[Quantity]]>=15,"Large",IF(Sales[[#This Row],[Quantity]]=14,"Medium","Small")) -> Small | Y45: =IF(AND(Sales[[#This Row],[Unit Price (₦)]]>68000,Sales[[#This Row],[Quantity]]>15),"Offer Discount", "No Discount") -> No Discount
A46: ORD-10609 | B46: 44773 | C46: 44778 | D46: Standard Class | E46: Adebayo | F46: Alakija | G46: adebayo.alakija@gmail.com | H46: 8063379602 | I46: Consumer | J46: East | K46: Enugu | L46: Office Supplies | M46: Pens & Pencils | N46: Staedtler HB Pencils | O46: 16 | P46: 2773.04 | Q46: 10 | R46: 4436.86 | S46: 39931.78 | T46: 15878.13 | U46: =PROPER(L46) -> Office Supplies | V46: =ABS(T46) -> 15878.13 | W46: =IF(Sales[[#This Row],[Quantity]]>=15, "Large","Small") -> Large | X46: =IF(Sales[[#This Row],[Quantity]]>=15,"Large",IF(Sales[[#This Row],[Quantity]]=14,"Medium","Small")) -> Large | Y46: =IF(AND(Sales[[#This Row],[Unit Price (₦)]]>68000,Sales[[#This Row],[Quantity]]>15),"Offer Discount", "No Discount") -> No Discount
A47: ORD-10169 | B47: 44773 | C47: 44780 | D47: Standard Class | E47: Uchenna | F47: Eze | G47: unknown | H47: 7063233823 | I47: Consumer | J47: South | K47: Warri | L47: Furniture | M47: Chairs | N47: Gaming Chair | O47: 20 | P47: 104886.09 | Q47: 0 | R47: 0 | S47: 2097721.8 | T47: 239265.42 | U47: =PROPER(L47) -> Furniture | V47: =ABS(T47) -> 239265.42 | W47: =IF(Sales[[#This Row],[Quantity]]>=15, "Large","Small") -> Large | X47: =IF(Sales[[#This Row],[Quantity]]>=15,"Large",IF(Sales[[#This Row],[Quantity]]=14,"Medium","Small")) -> Large | Y47: =IF(AND(Sales[[#This Row],[Unit Price (₦)]]>68000,Sales[[#This Row],[Quantity]]>15),"Offer Discount", "No Discount") -> Offer Discount
A48: ORD-10444 | B48: 44772 | C48: 44780 | D48: Standard Class | E48: Chibundo | F48: Lawal | G48: chibundo.lawal@hotmail.com | H48: 9015878387 | I48: Corporate | J48: West | K48: Abeokuta | L48: Technology | M48: Accessories | N48: Silk Scarf | O48: 19 | P48: 226453.92 | Q48: 20 | R48: 860524.9 | S48: 3442099.6 | T48: -37369.25 | U48: =PROPER(L48) -> Technology | V48: =ABS(T48) -> 37369.25 | W48: =IF(Sales[[#This Row],[Quantity]]>=15, "Large","Small") -> Large | X48: =IF(Sales[[#This Row],[Quantity]]>=15,"Large",IF(Sales[[#This Row],[Quantity]]=14,"Medium","Small")) -> Large | Y48: =IF(AND(Sales[[#This Row],[Unit Price (₦)]]>68000,Sales[[#This Row],[Quantity]]>15),"Offer Discount", "No Discount") -> Offer Discount
A49: ORD-10351 | B49: 44790 | C49: 44796 | D49: Standard Class | E49: Lanre | F49: Atiku | G49: lanre.atiku@yahoo.com | H49: 9078493596 | I49: Corporate | J49: East | K49: Aba | L49: Office Supplies | M49: Art Supplies | N49: Acrylic Paint Kit | O49: 8 | P49: 6900.69 | Q49: 20 | R49: 11041.1 | S49: 44164.42 | T49: -1833.46 | U49: =PROPER(L49) -> Office Supplies | V49: =ABS(T49) -> 1833.46 | W49: =IF(Sales[[#This Row],[Quantity]]>=15, "Large","Small") -> Small | X49: =IF(Sales[[#This Row],[Quantity]]>=15,"Large",IF(Sales[[#This Row],[Quantity]]=14,"Medium","Small")) -> Small | Y49: =IF(AND(Sales[[#This Row],[Unit Price (₦)]]>68000,Sales[[#This Row],[Quantity]]>15),"Offer Discount", "No Discount") -> No Discount
A50: ORD-10655 | B50: 44789 | C50: 44797 | D50: Standard Class | E50: Tobi | F50: Tinubu | G50: tobi.tinubu@gmail.com | H50: 8036671458 | I50: Home Office | J50: East | K50: Owerri | L50: Office Supplies | M50: Shoes | N50: Women's Heels | O50: 2 | P50: 16385.27 | Q50: 0 | R50: 0 | S50: 32770.54 | T50: -899.88 | U50: =PROPER(L50) -> Office Supplies | V50: =ABS(T50) -> 899.88 | W50: =IF(Sales[[#This Row],[Quantity]]>=15, "Large","Small") -> Small | X50: =IF(Sales[[#This Row],[Quantity]]>=15,"Large",IF(Sales[[#This Row],[Quantity]]=14,"Medium","Small")) -> Small | Y50: =IF(AND(Sales[[#This Row],[Unit Price (₦)]]>68000,Sales[[#This Row],[Quantity]]>15),"Offer Discount", "No Discount") -> No Discount
A51: ORD-10860 | B51: 44792 | C51: 44797 | D51: Standard Class | E51: Hauwa | F51: Fashola | G51: hauwa.fashola@outlook.com | H51: 8161378476 | I51: Consumer | J51: North | K51: Sokoto | L51: Food & Beverages | M51: Cooking Oil | N51: Vegetable Oil 5L | O51: 5 | P51: 5932.04 | Q51: 5 | R51: 1483.01 | S51: 28177.19 | T51: -3125 | U51: =PROPER(L51) -> Food & Beverages | V51: =ABS(T51) -> 3125 | W51: =IF(Sales[[#This Row],[Quantity]]>=15, "Large","Small") -> Small | X51: =IF(Sales[[#This Row],[Quantity]]>=15,"Large",IF(Sales[[#This Row],[Quantity]]=14,"Medium","Small")) -> Small | Y51: =IF(AND(Sales[[#This Row],[Unit Price (₦)]]>68000,Sales[[#This Row],[Quantity]]>15),"Offer Discount", "No Discount") -> No Discount
A52: ORD-10763 | B52: 44792 | C52: 44798 | D52: Standard Class | E52: Dayo | F52: Lawal | G52: dayo.lawal@gmail.com | H52: 9058859233 | I52: Home Office | J52: North | K52: Kano | L52: Food & Beverages | M52: Snacks | N52: Digestive Biscuits | O52: 14 | P52: 6206.79 | Q52: 10 | R52: 8689.51 | S52: 78205.55 | T52: 10122.07 | U52: =PROPER(L52) -> Food & Beverages | V52: =ABS(T52) -> 10122.07 | W52: =IF(Sales[[#This Row],[Quantity]]>=15, "Large","Small") -> Small | X52: =IF(Sales[[#This Row],[Quantity]]>=15,"Large",IF(Sales[[#This Row],[Quantity]]=14,"Medium","Small")) -> Medium | Y52: =IF(AND(Sales[[#This Row],[Unit Price (₦)]]>68000,Sales[[#This Row],[Quantity]]>15),"Offer Discount", "No Discount") -> No Discount
... A64: ORD-10932 | B64: 44840 | C64: 44848 | D64: Standard Class | E64: Wale | F64: Otedola | G64: wale.otedola@outlook.com | H64: 8061544925 | I64: Home Office | J64: North | K64: Katsina | L64: Office Supplies | M64: Binders | N64: Clipboard | O64: 14 | P64: 13658.5 | Q64: 10 | R64: 19121.9 | S64: 172097.1 | T64: -21793.81 | U64: =PROPER(L64) -> Office Supplies | V64: =ABS(T64) -> 21793.81 | W64: =IF(Sales[[#This Row],[Quantity]]>=15, "Large","Small") -> Small | X64: =IF(Sales[[#This Row],[Quantity]]>=15,"Large",IF(Sales[[#This Row],[Quantity]]=14,"Medium","Small")) -> Medium | Y64: =IF(AND(Sales[[#This Row],[Unit Price (₦)]]>68000,Sales[[#This Row],[Quantity]]>15),"Offer Discount", "No Discount") -> No Discount
A65: ORD-10063 | B65: 44850 | C65: 44856 | D65: Standard Class | E65: Ikenna | F65: Lawal | G65: ikenna.lawal@outlook.com | H65: 8067619862 | I65: Corporate | J65: East | K65: Enugu | L65: Technology | M65: Tablets | N65: Amazon Fire HD 10 | O65: =O64 -> 14 | P65: 68761.1 | Q65: 10 | R65: 82513.32 | S65: 742619.88 | T65: 149070.59 | U65: =PROPER(L65) -> Technology | V65: =ABS(T65) -> 149070.59 | W65: =IF(Sales[[#This Row],[Quantity]]>=15, "Large","Small") -> Small | X65: =IF(Sales[[#This Row],[Quantity]]>=15,"Large",IF(Sales[[#This Row],[Quantity]]=14,"Medium","Small")) -> Medium | Y65: =IF(AND(Sales[[#This Row],[Unit Price (₦)]]>68000,Sales[[#This Row],[Quantity]]>15),"Offer Discount", "No Discount") -> No Discount
A66: ORD-10515 | B66: 44851 | C66: 44857 | D66: Standard Class | E66: Kemi | F66: Musa!! | G66: kemi.musa@yahoo.com | H66: 9054428815 | I66: Consumer | J66: West | K66: Abeokuta | L66: Furniture | M66: Sofas | N66: 3-Seater Sofa | O66: 15 | P66: 81313.25 | Q66: 10 | R66: 121969.88 | S66: 1097728.9 | T66: -56538.21 | U66: =PROPER(L66) -> Furniture | V66: =ABS(T66) -> 56538.21 | W66: =IF(Sales[[#This Row],[Quantity]]>=15, "Large","Small") -> Large | X66: =IF(Sales[[#This Row],[Quantity]]>=15,"Large",IF(Sales[[#This Row],[Quantity]]=14,"Medium","Small")) -> Large | Y66: =IF(AND(Sales[[#This Row],[Unit Price (₦)]]>68000,Sales[[#This Row],[Quantity]]>15),"Offer Discount", "No Discount") -> No Discount
A67: ORD-10181 | B67: 44853 | C67: 44860 | D67: Standard Class | E67: Sade | F67: Adeleke | G67: sade.adeleke@yahoo.com | H67: 8039720112 | I67: Corporate | J67: South | K67: Warri | L67: Clothing | M67: Shoes | N67: Leather Loafers | O67: 3 | P67: 43905.86 | Q67: 0 | R67: 0 | S67: 131717.58 | T67: 20186.6 | U67: =PROPER(L67) -> Clothing | V67: =ABS(T67) -> 20186.6 | W67: =IF(Sales[[#This Row],[Quantity]]>=15, "Large","Small") -> Small | X67: =IF(Sales[[#This Row],[Quantity]]>=15,"Large",IF(Sales[[#This Row],[Quantity]]=14,"Medium","Small")) -> Small | Y67: =IF(AND(Sales[[#This Row],[Unit Price (₦)]]>68000,Sales[[#This Row],[Quantity]]>15),"Offer Discount", "No Discount") -> No Discount
A68: ORD-10633 | B68: 44864 | C68: 44872 | D68: Standard Class | E68: Zainab | F68: Sowore | G68: zainab.sowore@yahoo.com | H68: 7039352238 | I68: Corporate | J68: West | K68: Abeokuta | L68: Technology | M68: Phones | N68: Xiaomi Redmi 12 | O68: 14 | P68: 337340.41 | Q68: 10 | R68: 472276.57 | S68: 4250489.2 | T68: -111428.65 | U68: =PROPER(L68) -> Technology | V68: =ABS(T68) -> 111428.65 | W68: =IF(Sales[[#This Row],[Quantity]]>=15, "Large","Small") -> Small | X68: =IF(Sales[[#This Row],[Quantity]]>=15,"Large",IF(Sales[[#This Row],[Quantity]]=14,"Medium","Small")) -> Medium | Y68: =IF(AND(Sales[[#This Row],[Unit Price (₦)]]>68000,Sales[[#This Row],[Quantity]]>15),"Offer Discount", "No Discount") -> No Discount
A69: ORD-10672 | B69: 44869 | C69: 44877 | D69: Standard Class | E69: Sade | F69: Musa | G69: sade.musa@yahoo.com | H69: 9059447259 | I69: Corporate | J69: East | K69: Onitsha | L69: Food & Beverages | M69: Condiments | N69: Pepper Mix 200g | O69: 4 | P69: 4450.05 | Q69: -10 | R69: 4450.05 | S69: 13350.15 | T69: 4391.18 | U69: =PROPER(L69) -> Food & Beverages | V69: =ABS(T69) -> 4391.18 | W69: =IF(Sales[[#This Row],[Quantity]]>=15, "Large","Small") -> Small | X69: =IF(Sales[[#This Row],[Quantity]]>=15,"Large",IF(Sales[[#This Row],[Quantity]]=14,"Medium","Small")) -> Small | Y69: =IF(AND(Sales[[#This Row],[Unit Price (₦)]]>68000,Sales[[#This Row],[Quantity]]>15),"Offer Discount", "No Discount") -> No Discount
A70: ORD-10391 | B70: 44877 | C70: 44884 | D70: Standard Class | E70: Gbenga_Tinubu | F70: =F69 -> Musa | G70: gbenga.tinubu@hotmail.com | H70: 8065826621 | I70: Consumer | J70: West | K70: Ilorin | L70: Clothing | M70: Trousers | N70: Formal Trousers | O70: 8 | P70: 40992.11 | Q70: 0 | R70: 0 | S70: 327936.88 | T70: -25706.05 | U70: =PROPER(L70) -> Clothing | V70: =ABS(T70) -> 25706.05 | W70: =IF(Sales[[#This Row],[Quantity]]>=15, "Large","Small") -> Small | X70: =IF(Sales[[#This Row],[Quantity]]>=15,"Large",IF(Sales[[#This Row],[Quantity]]=14,"Medium","Small")) -> Small | Y70: =IF(AND(Sales[[#This Row],[Unit Price (₦)]]>68000,Sales[[#This Row],[Quantity]]>15),"Offer Discount", "No Discount") -> No Discount
A71: ORD-10833 | B71: 44881 | C71: 44889 | D71: Standard Class | E71: Adaeze | F71: Sule | G71: user@@domain.com | H71: 9053046457 | I71: Home Office | J71: North | K71: Abuja | L71: Technology | M71: Phones | N71: iPhone 13 | O71: 3 | P71: 414330.94 | Q71: 0 | R71: 0 | S71: 1242992.8 | T71: -118056.56 | U71: =PROPER(L71) -> Technology | V71: =ABS(T71) -> 118056.56 | W71: =IF(Sales[[#This Row],[Quantity]]>=15, "Large","Small") -> Small | X71: =IF(Sales[[#This Row],[Quantity]]>=15,"Large",IF(Sales[[#This Row],[Quantity]]=14,"Medium","Small")) -> Small | Y71: =IF(AND(Sales[[#This Row],[Unit Price (₦)]]>68000,Sales[[#This Row],[Quantity]]>15),"Offer Discount", "No Discount") -> No Discount
A72: ORD-10954 | B72: 44884 | C72: 44890 | D72: Standard Class | E72: Tunde | F72: Okafor | G72: tunde.okafor@hotmail.com | H72: 8068291687 | I72: Consumer | J72: South | K72: Warri | L72: Furniture | M72: Tables | N72: Study Table | O72: 18 | P72: 130755.89 | Q72: 25 | R72: 588401.51 | S72: 1765204.5 | T72: 741350.81 | U72: =PROPER(L72) -> Furniture | V72: =ABS(T72) -> 741350.81 | W72: =IF(Sales[[#This Row],[Quantity]]>=15, "Large","Small") -> Large | X72: =IF(Sales[[#This Row],[Quantity]]>=15,"Large",IF(Sales[[#This Row],[Quantity]]=14,"Medium","Small")) -> Large | Y72: =IF(AND(Sales[[#This Row],[Unit Price (₦)]]>68000,Sales[[#This Row],[Quantity]]>15),"Offer Discount", "No Discount") -> Offer Discount
A73: ORD-10671 | B73: 44890 | C73: 44897 | D73: Standard Class | E73: Emeka | F73: Eze | G73: emeka.eze@yahoo.com | H73: 9051428411 | I73: Corporate | J73: East | K73: Owerri | L73: Technology | M73: Printers | N73: Canon PIXMA G3411 | O73: 17 | P73: 366494.88 | Q73: 25 | R73: 1557603.2 | S73: 4672809.7 | T73: 1495674.3 | U73: =PROPER(L73) -> Technology | V73: =ABS(T73) -> 1495674.3 | W73: =IF(Sales[[#This Row],[Quantity]]>=15, "Large","Small") -> Large | X73: =IF(Sales[[#This Row],[Quantity]]>=15,"Large",IF(Sales[[#This Row],[Quantity]]=14,"Medium","Small")) -> Large | Y73: =IF(AND(Sales[[#This Row],[Unit Price (₦)]]>68000,Sales[[#This Row],[Quantity]]>15),"Offer Discount", "No Discount") -> Offer Discount
A74: ORD-10768 | B74: 44895 | C74: 44901 | D74: Standard Class | E74: Bola | F74: Sanusi | G74: bola.sanusi@outlook.com | H74: 9016316357 | I74: Consumer | J74: North | K74: Kano | L74: Clothing | M74: Trousers | N74: Women's Palazzo | O74: 17 | P74: 44361.54 | Q74: 10 | R74: 75414.62 | S74: 678731.56 | T74: 92841.91 | U74: =PROPER(L74) -> Clothing | V74: =ABS(T74) -> 92841.91 | W74: =IF(Sales[[#This Row],[Quantity]]>=15, "Large","Small") -> Large | X74: =IF(Sales[[#This Row],[Quantity]]>=15,"Large",IF(Sales[[#This Row],[Quantity]]=14,"Medium","Small")) -> Large | Y74: =IF(AND(Sales[[#This Row],[Unit Price (₦)]]>68000,Sales[[#This Row],[Quantity]]>15),"Offer Discount", "No Discount") -> No Discount
A75: ORD-10036 | B75: 44897 | C75: 44904 | D75: Standard Class | E75: Yemi | F75: Danjuma | G75: spaces in@email.com | H75: 8167296605 | I75: Consumer | J75: East | K75: Aba | L75: Clothing | M75: Trousers | N75: Men's Chinos | O75: 8 | P75: 27460.21 | Q75: 0 | R75: 0 | S75: 219681.68 | T75: 58944.07 | U75: =PROPER(L75) -> Clothing | V75: =ABS(T75) -> 58944.07 | W75: =IF(Sales[[#This Row],[Quantity]]>=15, "Large","Small") -> Small | X75: =IF(Sales[[#This Row],[Quantity]]>=15,"Large",IF(Sales[[#This Row],[Quantity]]=14,"Medium","Small")) -> Small | Y75: =IF(AND(Sales[[#This Row],[Unit Price (₦)]]>68000,Sales[[#This Row],[Quantity]]>15),"Offer Discount", "No Discount") -> No Discount
A76: ORD-10630 | B76: 44903 | C76: 44909 | D76: Standard Class | E76: Adaeze | F76: Fashola | G76: adaeze.fashola@yahoo.com | H76: 8038962478 | I76: Corporate | J76: South | K76: Ibadan | L76: Clothing | M76: Shoes | N76: Men's Oxford Shoes | O76: 9 | P76: 9633.15 | Q76: 0 | R76: 0 | S76: 86698.35 | T76: -4123.8 | U76: =PROPER(L76) -> Clothing | V76: =ABS(T76) -> 4123.8 | W76: =IF(Sales[[#This Row],[Quantity]]>=15, "Large","Small") -> Small | X76: =IF(Sales[[#This Row],[Quantity]]>=15,"Large",IF(Sales[[#This Row],[Quantity]]=14,"Medium","Small")) -> Small | Y76: =IF(AND(Sales[[#This Row],[Unit Price (₦)]]>68000,Sales[[#This Row],[Quantity]]>15),"Offer Discount", "No Discount") -> No Discount
A77: ORD-10208 | B77: 44917 | C77: 44923 | D77: Standard Class | E77: Musa | F77: Gambo | G77: musa.gambo@gmail.com | H77: 8131554840 | I77: Home Office | J77: West | K77: Ilorin | L77: Clothing | M77: Shirts | N77: Corporate Shirt | O77: 9 | P77: 32299.26 | Q77: 10 | R77: 29069.33 | S77: 261624.01 | T77: 90025.81 | U77: =PROPER(L77) -> Clothing | V77: =ABS(T77) -> 90025.81 | W77: =IF(Sales[[#This Row],[Quantity]]>=15, "Large","Small") -> Small | X77: =IF(Sales[[#This Row],[Quantity]]>=15,"Large",IF(Sales[[#This Row],[Quantity]]=14,"Medium","Small")) -> Small | Y77: =IF(AND(Sales[[#This Row],[Unit Price (₦)]]>68000,Sales[[#This Row],[Quantity]]>15),"Offer Discount", "No Discount") -> No Discount
A78: ORD-10261 | B78: 44925 | C78: 44933 | D78: Standard Class | E78: Ayo | F78: Alakija | G78: ayo.alakija@gmail.com | H78: 9029915915 | I78: Home Office | J78: West | K78: Ilorin | L78: Food & Beverages | M78: Drinks | N78: Coca-Cola 24-Pack | O78: 5 | P78: 4013.26 | Q78: 25 | R78: 5016.58 | S78: 15049.72 | T78: 5214.92 | U78: =PROPER(L78) -> Food & Beverages | V78: =ABS(T78) -> 5214.92 | W78: =IF(Sales[[#This Row],[Quantity]]>=15, "Large","Small") -> Small | X78: =IF(Sales[[#This Row],[Quantity]]>=15,"Large",IF(Sales[[#This Row],[Quantity]]=14,"Medium","Small")) -> Small | Y78: =IF(AND(Sales[[#This Row],[Unit Price (₦)]]>68000,Sales[[#This Row],[Quantity]]>15),"Offer Discount", "No Discount") -> No Discount
A79: ORD-10405 | B79: 44928 | C79: 44936 | D79: Standard Class | E79: Deola | F79: Sowore | G79: deola.sowore@outlook.com | H79: 8106079345 | I79: Corporate | J79: North | K79: Kano | L79: Food & Beverages | M79: Condiments | N79: Tomato Paste 400g | O79: 17 | P79: 6153.32 | Q79: 20 | R79: 20921.29 | S79: 83685.15 | T79: 27251.14 | U79: =PROPER(L79) -> Food & Beverages | V79: =ABS(T79) -> 27251.14 | W79: =IF(Sales[[#This Row],[Quantity]]>=15, "Large","Small") -> Large | X79: =IF(Sales[[#This Row],[Quantity]]>=15,"Large",IF(Sales[[#This Row],[Quantity]]=14,"Medium","Small")) -> Large | Y79: =IF(AND(Sales[[#This Row],[Unit Price (₦)]]>68000,Sales[[#This Row],[Quantity]]>15),"Offer Discount", "No Discount") -> No Discount
A80: ORD-10368 | B80: 44930 | C80: 44938 | D80: Standard Class | E80: Ayo | F80: Musa | G80: ayo.musa@outlook.com | H80: 7038026061 | I80: Home Office | J80: South | K80: Ibadan | L80: Technology | M80: Printers | N80: Canon PIXMA G3411 | O80: 17 | P80: 98477.74 | Q80: 0 | R80: 0 | S80: 1674121.6 | T80: 370571.1 | U80: =PROPER(L80) -> Technology | V80: =ABS(T80) -> 370571.1 | W80: =IF(Sales[[#This Row],[Quantity]]>=15, "Large","Small") -> Large | X80: =IF(Sales[[#This Row],[Quantity]]>=15,"Large",IF(Sales[[#This Row],[Quantity]]=14,"Medium","Small")) -> Large | Y80: =IF(AND(Sales[[#This Row],[Unit Price (₦)]]>68000,Sales[[#This Row],[Quantity]]>15),"Offer Discount", "No Discount") -> Offer Discount
A81: ORD-10984 | B81: 44940 | C81: 44946 | D81: Standard Class | E81: Nike | F81: Buhari | G81: nike.buhari@yahoo.com | H81: 9028212098 | I81: CONSUMER | J81: South | K81: Ibadan | L81: Technology | M81: Accessories | N81: Wallet Genuine Leather | O81: 2 | P81: 43307.01 | Q81: 15 | R81: 12992.1 | S81: 73621.92 | T81: 16442.04 | U81: =PROPER(L81) -> Technology | V81: =ABS(T81) -> 16442.04 | W81: =IF(Sales[[#This Row],[Quantity]]>=15, "Large","Small") -> Small | X81: =IF(Sales[[#This Row],[Quantity]]>=15,"Large",IF(Sales[[#This Row],[Quantity]]=14,"Medium","Small")) -> Small | Y81: =IF(AND(Sales[[#This Row],[Unit Price (₦)]]>68000,Sales[[#This Row],[Quantity]]>15),"Offer Discount", "No Discount") -> No Discount
A82: ORD-10311 | B82: 44943 | C82: 44949 | D82: Standard Class | E82: Dayo | F82: Fashola | G82: dayo.fashola@gmail.com | H82: 8035150551 | I82: Corporate | J82: North | K82: Abuja | L82: Food & Beverages | M82: Grains | N82: Garri 10kg | O82: 6 | P82: 4072.48 | Q82: 0 | R82: 0 | S82: 24434.88 | T82: 1418.88 | U82: =PROPER(L82) -> Food & Beverages | V82: =ABS(T82) -> 1418.88 | W82: =IF(Sales[[#This Row],[Quantity]]>=15, "Large","Small") -> Small | X82: =IF(Sales[[#This Row],[Quantity]]>=15,"Large",IF(Sales[[#This Row],[Quantity]]=14,"Medium","Small")) -> Small | Y82: =IF(AND(Sales[[#This Row],[Unit Price (₦)]]>68000,Sales[[#This Row],[Quantity]]>15),"Offer Discount", "No Discount") -> No Discount
... A97: ORD-10612 | B97: 45006 | C97: 45011 | D97: Standard Class | E97: Chisom | F97: Okafor | G97: chisom.okafor@yahoo.com | H97: 8063123664 | I97: Corporate | J97: South | K97: Ibadan | L97: Office Supplies | M97: Pens & Pencils | N97: Whiteboard Markers | O97: 3 | P97: 5381.32 | Q97: 10 | R97: 1614.4 | S97: 14529.56 | T97: 3993.45 | U97: =PROPER(L97) -> Office Supplies | V97: =ABS(T97) -> 3993.45 | W97: =IF(Sales[[#This Row],[Quantity]]>=15, "Large","Small") -> Small | X97: =IF(Sales[[#This Row],[Quantity]]>=15,"Large",IF(Sales[[#This Row],[Quantity]]=14,"Medium","Small")) -> Small | Y97: =IF(AND(Sales[[#This Row],[Unit Price (₦)]]>68000,Sales[[#This Row],[Quantity]]>15),"Offer Discount", "No Discount") -> No Discount
A98: ORD-10232 | B98: 45016 | C98: 45021 | D98: Standard Class | E98: Adaeze | F98: Adebayo | G98: adaeze.adebayo@outlook.com | H98: 8159757456 | I98: Consumer | J98: East | K98: Owerri | L98: Office Supplies | M98: Fasteners | N98: Stapler + Staples | O98: 6 | P98: 1621.56 | Q98: 20 | R98: 1945.87 | S98: 7783.49 | T98: =T97 -> 3993.45 | U98: =PROPER(L98) -> Office Supplies | V98: =ABS(T98) -> 3993.45 | W98: =IF(Sales[[#This Row],[Quantity]]>=15, "Large","Small") -> Small | X98: =IF(Sales[[#This Row],[Quantity]]>=15,"Large",IF(Sales[[#This Row],[Quantity]]=14,"Medium","Small")) -> Small | Y98: =IF(AND(Sales[[#This Row],[Unit Price (₦)]]>68000,Sales[[#This Row],[Quantity]]>15),"Offer Discount", "No Discount") -> No Discount
A99: ORD-10818 | B99: 45021 | C99: 45026 | D99: Standard Class | E99: Kehinde | F99: Otedola | G99: kehinde.otedola@gmail.com | H99: 8038993139 | I99: Home Office | J99: North | K99: Sokoto | L99: Food & Beverages | M99: Cooking Oil | N99: Groundnut Oil 3L | O99: 13 | P99: 5579.2 | Q99: 20 | R99: 14505.92 | S99: 58023.68 | T99: 22985.77 | U99: =PROPER(L99) -> Food & Beverages | V99: =ABS(T99) -> 22985.77 | W99: =IF(Sales[[#This Row],[Quantity]]>=15, "Large","Small") -> Small | X99: =IF(Sales[[#This Row],[Quantity]]>=15,"Large",IF(Sales[[#This Row],[Quantity]]=14,"Medium","Small")) -> Small | Y99: =IF(AND(Sales[[#This Row],[Unit Price (₦)]]>68000,Sales[[#This Row],[Quantity]]>15),"Offer Discount", "No Discount") -> No Discount
A100: ORD-10669 | B100: 45028 | C100: 45033 | D100: Standard Class | E100: Tobi | F100: Chukwu | G100: tobi.chukwu@gmail.com | H100: 9076927978 | I100: Corporate | J100: West | K100: Ado-Ekiti | L100: Food & Beverages | M100: Drinks | N100: Energy Drink 4-Pack | O100: 4 | P100: 2107.17 | Q100: 0 | R100: 0 | S100: 8428.68 | T100: 1299.39 | U100: =PROPER(L100) -> Food & Beverages | V100: =ABS(T100) -> 1299.39 | W100: =IF(Sales[[#This Row],[Quantity]]>=15, "Large","Small") -> Small | X100: =IF(Sales[[#This Row],[Quantity]]>=15,"Large",IF(Sales[[#This Row],[Quantity]]=14,"Medium","Small")) -> Small | Y100: =IF(AND(Sales[[#This Row],[Unit Price (₦)]]>68000,Sales[[#This Row],[Quantity]]>15),"Offer Discount", "No Discount") -> No Discount
A101: ORD-10177 | B101: 45029 | C101: 45034 | D101: Standard Class | E101: Emeka | F101: Lawal | G101: unknown | H101: 8131771442 | I101: Home Office | J101: East | K101: Enugu | L101: Clothing | M101: Shoes | N101: Leather Loafers | O101: 6 | P101: 41569.74 | Q101: 0 | R101: 0 | S101: 249418.44 | T101: 45324.04 | U101: =PROPER(L101) -> Clothing | V101: =ABS(T101) -> 45324.04 | W101: =IF(Sales[[#This Row],[Quantity]]>=15, "Large","Small") -> Small | X101: =IF(Sales[[#This Row],[Quantity]]>=15,"Large",IF(Sales[[#This Row],[Quantity]]=14,"Medium","Small")) -> Small | Y101: =IF(AND(Sales[[#This Row],[Unit Price (₦)]]>68000,Sales[[#This Row],[Quantity]]>15),"Offer Discount", "No Discount") -> No Discount
A102: ORD-10659 | B102: 45027 | C102: 45035 | D102: Standard Class | E102: Bukola | F102: Danjuma | G102: bukola.danjuma@gmail.com | H102: 9021249956 | I102: Consumer | J102: South | K102: Ibadan | L102: Furniture | M102: Chairs | N102: Executive Chair | O102: 15 | P102: 17744.59 | Q102: 0 | R102: 0 | S102: 266168.85 | T102: 5205.62 | U102: =PROPER(L102) -> Furniture | V102: =ABS(T102) -> 5205.62 | W102: =IF(Sales[[#This Row],[Quantity]]>=15, "Large","Small") -> Large | X102: =IF(Sales[[#This Row],[Quantity]]>=15,"Large",IF(Sales[[#This Row],[Quantity]]=14,"Medium","Small")) -> Large | Y102: =IF(AND(Sales[[#This Row],[Unit Price (₦)]]>68000,Sales[[#This Row],[Quantity]]>15),"Offer Discount", "No Discount") -> No Discount
A103: ORD-10011 | B103: 45033 | C103: 45039 | D103: Standard Class | E103: Chidi | F103: Musa | G103: chidi.musa@gmail.com | H103: +234 803 123 4567 | I103: Corporate | J103: South | K103: Lagos | L103: Technology | M103: Tablets | N103: iPad 10th Gen | O103: 9 | P103: 238657.91 | Q103: 20 | R103: 429584.24 | S103: 1718336.9 | T103: -36871.93 | U103: =PROPER(L103) -> Technology | V103: =ABS(T103) -> 36871.93 | W103: =IF(Sales[[#This Row],[Quantity]]>=15, "Large","Small") -> Small | X103: =IF(Sales[[#This Row],[Quantity]]>=15,"Large",IF(Sales[[#This Row],[Quantity]]=14,"Medium","Small")) -> Small | Y103: =IF(AND(Sales[[#This Row],[Unit Price (₦)]]>68000,Sales[[#This Row],[Quantity]]>15),"Offer Discount", "No Discount") -> No Discount
A104: ORD-10940 | B104: 45034 | C104: 45040 | D104: Standard Class | E104: Emeka | F104: Atiku | G104: emeka.atiku@gmail.com | H104: 9077622282 | I104: Consumer | J104: North | K104: Kaduna | L104: Furniture | M104: Tables | N104: Study Table | O104: 19 | P104: 173016.77 | Q104: 0 | R104: 0 | S104: 3287318.6 | T104: 792611.31 | U104: =PROPER(L104) -> Furniture | V104: =ABS(T104) -> 792611.31 | W104: =IF(Sales[[#This Row],[Quantity]]>=15, "Large","Small") -> Large | X104: =IF(Sales[[#This Row],[Quantity]]>=15,"Large",IF(Sales[[#This Row],[Quantity]]=14,"Medium","Small")) -> Large | Y104: =IF(AND(Sales[[#This Row],[Unit Price (₦)]]>68000,Sales[[#This Row],[Quantity]]>15),"Offer Discount", "No Discount") -> Offer Discount
A105: ORD-10512 | B105: 45038 | C105: 45043 | D105: Standard Class | E105: Ayo | F105: Buhari | G105: ayo.buhari@gmail.com | H105: 8164966072 | I105: Home Office | J105: South | K105: Port Harcourt | L105: Clothing | M105: Trousers | N105: Jeans Straight Cut | O105: 5 | P105: 5413.75 | Q105: 10 | R105: 2706.88 | S105: 24361.87 | T105: 3635.67 | U105: =PROPER(L105) -> Clothing | V105: =ABS(T105) -> 3635.67 | W105: =IF(Sales[[#This Row],[Quantity]]>=15, "Large","Small") -> Small | X105: =IF(Sales[[#This Row],[Quantity]]>=15,"Large",IF(Sales[[#This Row],[Quantity]]=14,"Medium","Small")) -> Small | Y105: =IF(AND(Sales[[#This Row],[Unit Price (₦)]]>68000,Sales[[#This Row],[Quantity]]>15),"Offer Discount", "No Discount") -> No Discount
A106: ORD-10681 | B106: 45036 | C106: 45043 | D106: Standard Class | E106: Seun | F106: Bello | G106: seun.bello@yahoo.com | H106: 8159534539 | I106: Corporate | J106: South | K106: Benin City | L106: Furniture | M106: Chairs | N106: Gaming Chair | O106: 18 | P106: 163237.1 | Q106: 25 | R106: 734566.95 | S106: 2203700.9 | T106: 725888.48 | U106: =PROPER(L106) -> Furniture | V106: =ABS(T106) -> 725888.48 | W106: =IF(Sales[[#This Row],[Quantity]]>=15, "Large","Small") -> Large | X106: =IF(Sales[[#This Row],[Quantity]]>=15,"Large",IF(Sales[[#This Row],[Quantity]]=14,"Medium","Small")) -> Large | Y106: =IF(AND(Sales[[#This Row],[Unit Price (₦)]]>68000,Sales[[#This Row],[Quantity]]>15),"Offer Discount", "No Discount") -> Offer Discount
A107: ORD-10016 | B107: 45043 | C107: 45051 | D107: Standard Class | E107: Bola | F107: Danjuma | G107: bola.danjuma@yahoo.com | H107: 9051666754 | I107: CONSUMER | J107: North | K107: Kaduna | L107: Food & Beverages | M107: Drinks | N107: Fruit Juice 1L | O107: 19 | P107: 5361.77 | Q107: 25 | R107: 25468.41 | S107: 76405.22 | T107: 3042.6 | U107: =PROPER(L107) -> Food & Beverages | V107: =ABS(T107) -> 3042.6 | W107: =IF(Sales[[#This Row],[Quantity]]>=15, "Large","Small") -> Large | X107: =IF(Sales[[#This Row],[Quantity]]>=15,"Large",IF(Sales[[#This Row],[Quantity]]=14,"Medium","Small")) -> Large | Y107: =IF(AND(Sales[[#This Row],[Unit Price (₦)]]>68000,Sales[[#This Row],[Quantity]]>15),"Offer Discount", "No Discount") -> No Discount
A108: ORD-10254 | B108: 45051 | C108: 45057 | D108: Standard Class | E108: Dayo | F108: Okafor | G108: dayo.okafor@hotmail.com | H108: 8104005557 | I108: Corporate | J108: North | K108: Sokoto | L108: Food & Beverages | M108: Condiments | N108: Maggi Cubes 100pk | O108: 16 | P108: 5966.58 | Q108: 10 | R108: 9546.53 | S108: 85918.75 | T108: -10804.12 | U108: =PROPER(L108) -> Food & Beverages | V108: =ABS(T108) -> 10804.12 | W108: =IF(Sales[[#This Row],[Quantity]]>=15, "Large","Small") -> Large | X108: =IF(Sales[[#This Row],[Quantity]]>=15,"Large",IF(Sales[[#This Row],[Quantity]]=14,"Medium","Small")) -> Large | Y108: =IF(AND(Sales[[#This Row],[Unit Price (₦)]]>68000,Sales[[#This Row],[Quantity]]>15),"Offer Discount", "No Discount") -> No Discount
A109: ORD-10957 | B109: 45056 | C109: 45061 | D109: Standard Class | E109: Adaeze | F109: Dangote | G109: adaeze.dangote@gmail.com | H109: 8165381205 | I109: Consumer | J109: South | K109: Ibadan | L109: Office Supplies | M109: Labels | N109: Round Stickers | O109: 2 | P109: 20788.7 | Q109: 15 | R109: 6236.61 | S109: 35340.79 | T109: 5099.85 | U109: =PROPER(L109) -> Office Supplies | V109: =ABS(T109) -> 5099.85 | W109: =IF(Sales[[#This Row],[Quantity]]>=15, "Large","Small") -> Small | X109: =IF(Sales[[#This Row],[Quantity]]>=15,"Large",IF(Sales[[#This Row],[Quantity]]=14,"Medium","Small")) -> Small | Y109: =IF(AND(Sales[[#This Row],[Unit Price (₦)]]>68000,Sales[[#This Row],[Quantity]]>15),"Offer Discount", "No Discount") -> No Discount
A110: ORD-10209 | B110: 45057 | C110: 45064 | D110: Standard Class | E110: Wale | F110: Alakija | G110: wale.alakija@hotmail.com | H110: 8108962169 | I110: Home Office | J110: West | K110: Abeokuta | L110: Food & Beverages | M110: Condiments | N110: Soy Sauce 500ml | O110: 9 | P110: 2950.72 | Q110: 0 | R110: 0 | S110: 26556.48 | T110: 558.79 | U110: =PROPER(L110) -> Food & Beverages | V110: =ABS(T110) -> 558.79 | W110: =IF(Sales[[#This Row],[Quantity]]>=15, "Large","Small") -> Small | X110: =IF(Sales[[#This Row],[Quantity]]>=15,"Large",IF(Sales[[#This Row],[Quantity]]=14,"Medium","Small")) -> Small | Y110: =IF(AND(Sales[[#This Row],[Unit Price (₦)]]>68000,Sales[[#This Row],[Quantity]]>15),"Offer Discount", "No Discount") -> No Discount
A111: ORD-10713 | B111: 45067 | C111: 45074 | D111: Standard Class | E111: Musa | F111: Atiku | G111: musa.atiku@yahoo.com | H111: 8161894817 | I111: Corporate | J111: South | K111: Benin City | L111: Clothing | M111: Shoes | N111: Women's Heels | O111: 19 | P111: 13995.43 | Q111: 10 | R111: 26591.32 | S111: 239321.85 | T111: 23546.8 | U111: =PROPER(L111) -> Clothing | V111: =ABS(T111) -> 23546.8 | W111: =IF(Sales[[#This Row],[Quantity]]>=15, "Large","Small") -> Large | X111: =IF(Sales[[#This Row],[Quantity]]>=15,"Large",IF(Sales[[#This Row],[Quantity]]=14,"Medium","Small")) -> Large | Y111: =IF(AND(Sales[[#This Row],[Unit Price (₦)]]>68000,Sales[[#This Row],[Quantity]]>15),"Offer Discount", "No Discount") -> No Discount
A112: ORD-10890 | B112: 45066 | C112: 45074 | D112: Standard Class | E112: Zainab | F112: Abubakar | G112: zainab.abubakar@hotmail.com | H112: 9053779020 | I112: Consumer | J112: East | K112: Owerri | L112: Furniture | M112: Tables | N112: Study Table | O112: 8 | P112: 26470.55 | Q112: 10 | R112: 21176.44 | S112: 190587.96 | T112: =T111 -> 23546.8 | U112: =PROPER(L112) -> Furniture | V112: =ABS(T112) -> 23546.8 | W112: =IF(Sales[[#This Row],[Quantity]]>=15, "Large","Small") -> Small | X112: =IF(Sales[[#This Row],[Quantity]]>=15,"Large",IF(Sales[[#This Row],[Quantity]]=14,"Medium","Small")) -> Small | Y112: =IF(AND(Sales[[#This Row],[Unit Price (₦)]]>68000,Sales[[#This Row],[Quantity]]>15),"Offer Discount", "No Discount") -> No Discount
A113: ORD-10250 | B113: 45075 | C113: 45080 | D113: Standard Class | E113: Musa | F113: Atiku | G113: musa.atiku@hotmail.com | H113: 7036991787 | I113: Home Office | J113: North | K113: Abuja | L113: Furniture | M113: Tables | N113: Office Desk 120cm | O113: =O112 -> 8 | P113: 57043.59 | Q113: 5 | R113: 8556.54 | S113: 162574.23 | T113: 6612.15 | U113: =PROPER(L113) -> Furniture | V113: =ABS(T113) -> 6612.15 | W113: =IF(Sales[[#This Row],[Quantity]]>=15, "Large","Small") -> Small | X113: =IF(Sales[[#This Row],[Quantity]]>=15,"Large",IF(Sales[[#This Row],[Quantity]]=14,"Medium","Small")) -> Small | Y113: =IF(AND(Sales[[#This Row],[Unit Price (₦)]]>68000,Sales[[#This Row],[Quantity]]>15),"Offer Discount", "No Discount") -> No Discount
A114: ORD-10034 | B114: 45094 | C114: 45102 | D114: Standard Class | E114: Chisom | F114: Nwosu | G114: chisom.nwosu@hotmail.com | H114: 7036662319 | I114: Consumer | J114: South | K114: Warri | L114: Clothing | M114: Shoes | N114: Leather Loafers | O114: 3 | P114: 12847.68 | Q114: 20 | R114: 7708.61 | S114: 30834.43 | T114: -4266.56 | U114: =PROPER(L114) -> Clothing | V114: =ABS(T114) -> 4266.56 | W114: =IF(Sales[[#This Row],[Quantity]]>=15, "Large","Small") -> Small | X114: =IF(Sales[[#This Row],[Quantity]]>=15,"Large",IF(Sales[[#This Row],[Quantity]]=14,"Medium","Small")) -> Small | Y114: =IF(AND(Sales[[#This Row],[Unit Price (₦)]]>68000,Sales[[#This Row],[Quantity]]>15),"Offer Discount", "No Discount") -> No Discount
A115: ORD-10123 | B115: 45097 | C115: 45104 | D115: Standard Class | E115: Hauwa | F115: Adeleke | G115: hauwa.adeleke@gmail.com | H115: 8146147356 | I115: Home Office | J115: East | K115: Awka | L115: Furniture | M115: Storage | N115: Wardrobe 3-Door | O115: 10 | P115: 166774.23 | Q115: 0 | R115: 0 | S115: 1667742.3 | T115: 388962.19 | U115: =PROPER(L115) -> Furniture | V115: =ABS(T115) -> 388962.19 | W115: =IF(Sales[[#This Row],[Quantity]]>=15, "Large","Small") -> Small | X115: =IF(Sales[[#This Row],[Quantity]]>=15,"Large",IF(Sales[[#This Row],[Quantity]]=14,"Medium","Small")) -> Small | Y115: =IF(AND(Sales[[#This Row],[Unit Price (₦)]]>68000,Sales[[#This Row],[Quantity]]>15),"Offer Discount", "No Discount") -> No Discount
A116: ORD-10638 | B116: 45097 | C116: 45104 | D116: Standard Class | E116: Deola | F116: Eze | G116: deola.eze@yahoo.com | H116: 9058311783 | I116: Corporate | J116: West | K116: Akure | L116: Office Supplies | M116: Art Supplies | N116: Craft Scissors | O116: 7 | P116: 3909.82 | Q116: 10 | R116: 2736.87 | S116: 24631.87 | T116: -1689.39 | U116: =PROPER(L116) -> Office Supplies | V116: =ABS(T116) -> 1689.39 | W116: =IF(Sales[[#This Row],[Quantity]]>=15, "Large","Small") -> Small | X116: =IF(Sales[[#This Row],[Quantity]]>=15,"Large",IF(Sales[[#This Row],[Quantity]]=14,"Medium","Small")) -> Small | Y116: =IF(AND(Sales[[#This Row],[Unit Price (₦)]]>68000,Sales[[#This Row],[Quantity]]>15),"Offer Discount", "No Discount") -> No Discount
A117: ORD-10623 | B117: 45102 | C117: 45109 | D117: Standard Class | E117: Sade | F117: Adebayo | G117: sade.adebayo@yahoo.com | H117: 9074454281 | I117: Consumer | J117: East | K117: Owerri | L117: Technology | M117: Laptops | N117: Asus VivoBook 14 | O117: 1 | P117: 41216.11 | Q117: 5 | R117: 2060.81 | S117: 39155.3 | T117: 5125.05 | U117: =PROPER(L117) -> Technology | V117: =ABS(T117) -> 5125.05 | W117: =IF(Sales[[#This Row],[Quantity]]>=15, "Large","Small") -> Small | X117: =IF(Sales[[#This Row],[Quantity]]>=15,"Large",IF(Sales[[#This Row],[Quantity]]=14,"Medium","Small")) -> Small | Y117: =IF(AND(Sales[[#This Row],[Unit Price (₦)]]>68000,Sales[[#This Row],[Quantity]]>15),"Offer Discount", "No Discount") -> No Discount
A118: ORD-10106 | B118: 45104 | C118: 45110 | D118: Standard Class | E118: Kehinde | F118: Ogundipe | G118: kehinde.ogundipe@gmail.com | H118: 8145859883 | I118: Consumer | J118: North | K118: Kano | L118: Office Supplies | M118: Envelopes | N118: Bubble Mailers | O118: 13 | P118: 20214.86 | Q118: 10 | R118: 26279.32 | S118: 236513.86 | T118: 28884.61 | U118: =PROPER(L118) -> Office Supplies | V118: =ABS(T118) -> 28884.61 | W118: =IF(Sales[[#This Row],[Quantity]]>=15, "Large","Small") -> Small | X118: =IF(Sales[[#This Row],[Quantity]]>=15,"Large",IF(Sales[[#This Row],[Quantity]]=14,"Medium","Small")) -> Small | Y118: =IF(AND(Sales[[#This Row],[Unit Price (₦)]]>68000,Sales[[#This Row],[Quantity]]>15),"Offer Discount", "No Discount") -> No Discount
A119: ORD-10546 | B119: 45113 | C119: 45119 | D119: Standard Class | E119: Uchenna | F119: Danjuma | G119: uchenna.danjuma@yahoo.com | H119: 7063575158 | I119: Consumer | J119: South | K119: Port Harcourt | L119: Office Supplies | M119: Art Supplies | N119: Coloured Pencils 24 | O119: 20 | P119: 9784.08 | Q119: 5 | R119: 9784.08 | S119: 185897.52 | T119: -19237.65 | U119: =PROPER(L119) -> Office Supplies | V119: =ABS(T119) -> 19237.65 | W119: =IF(Sales[[#This Row],[Quantity]]>=15, "Large","Small") -> Large | X119: =IF(Sales[[#This Row],[Quantity]]>=15,"Large",IF(Sales[[#This Row],[Quantity]]=14,"Medium","Small")) -> Large | Y119: =IF(AND(Sales[[#This Row],[Unit Price (₦)]]>68000,Sales[[#This Row],[Quantity]]>15),"Offer Discount", "No Discount") -> No Discount
A120: ORD-10708 | B120: 45121 | C120: 45126 | D120: Standard Class | E120: Femi | F120: Tinubu | G120: femi.tinubu@hotmail.com | H120: 7061736811 | I120: Home Office | J120: East | K120: Aba | L120: Office Supplies | M120: Pens & Pencils | N120: Bic Ballpoint Pack | O120: 1 | P120: 24292.95 | Q120: 20 | R120: 4858.59 | S120: 19434.36 | T120: 8713.18 | U120: =PROPER(L120) -> Office Supplies | V120: =ABS(T120) -> 8713.18 | W120: =IF(Sales[[#This Row],[Quantity]]>=15, "Large","Small") -> Small | X120: =IF(Sales[[#This Row],[Quantity]]>=15,"Large",IF(Sales[[#This Row],[Quantity]]=14,"Medium","Small")) -> Small | Y120: =IF(AND(Sales[[#This Row],[Unit Price (₦)]]>68000,Sales[[#This Row],[Quantity]]>15),"Offer Discount", "No Discount") -> No Discount
A121: ORD-10535 | B121: 45122 | C121: 45130 | D121: Standard Class | E121: Ibrahim | F121: Sanusi | G121: ibrahim.sanusi@outlook.com | H121: 9017320122 | I121: HOME OFFICE | J121: East | K121: Awka | L121: Technology | M121: Tablets | N121: Samsung Tab A8 | O121: 7 | P121: 375129.84 | Q121: 5 | R121: 131295.44 | S121: 2494613.4 | T121: 674155.43 | U121: =PROPER(L121) -> Technology | V121: =ABS(T121) -> 674155.43 | W121: =IF(Sales[[#This Row],[Quantity]]>=15, "Large","Small") -> Small | X121: =IF(Sales[[#This Row],[Quantity]]>=15,"Large",IF(Sales[[#This Row],[Quantity]]=14,"Medium","Small")) -> Small | Y121: =IF(AND(Sales[[#This Row],[Unit Price (₦)]]>68000,Sales[[#This Row],[Quantity]]>15),"Offer Discount", "No Discount") -> No Discount
A122: ORD-10597 | B122: 45122 | C122: 45130 | D122: Standard Class | E122: Sade | F122: Eze | G122: sade.eze@hotmail.com | H122: 8038041764 | I122: Consumer | J122: South | K122: Abia | L122: Food & Beverages | M122: Snacks | N122: Chin Chin 500g | O122: 2 | P122: 1717.4 | Q122: 0 | R122: 0 | S122: 3434.8 | T122: 1329.18 | U122: =PROPER(L122) -> Food & Beverages | V122: =ABS(T122) -> 1329.18 | W122: =IF(Sales[[#This Row],[Quantity]]>=15, "Large","Small") -> Small | X122: =IF(Sales[[#This Row],[Quantity]]>=15,"Large",IF(Sales[[#This Row],[Quantity]]=14,"Medium","Small")) -> Small | Y122: =IF(AND(Sales[[#This Row],[Unit Price (₦)]]>68000,Sales[[#This Row],[Quantity]]>15),"Offer Discount", "No Discount") -> No Discount
A123: ORD-10634 | B123: 45122 | C123: 45130 | D123: Standard Class | E123: Ronke | F123: Adeyemi | G123: ronke.adeyemi@outlook.com | H123: 9076852648 | I123: Corporate | J123: North | K123: Kaduna | L123: Office Supplies | M123: Envelopes | N123: C5 Envelopes | O123: 9 | P123: 10723.71 | Q123: 10 | R123: 9651.34 | S123: 86862.05 | T123: -3097.19 | U123: =PROPER(L123) -> Office Supplies | V123: =ABS(T123) -> 3097.19 | W123: =IF(Sales[[#This Row],[Quantity]]>=15, "Large","Small") -> Small | X123: =IF(Sales[[#This Row],[Quantity]]>=15,"Large",IF(Sales[[#This Row],[Quantity]]=14,"Medium","Small")) -> Small | Y123: =IF(AND(Sales[[#This Row],[Unit Price (₦)]]>68000,Sales[[#This Row],[Quantity]]>15),"Offer Discount", "No Discount") -> No Discount
A124: ORD-10770 | B124: 45124 | C124: 45131 | D124: Standard Class | E124: Emeka | F124: Okafor | G124: emeka.okafor@yahoo.com | H124: 8101155591 | I124: Corporate | J124: North | K124: Sokoto | L124: Furniture | M124: Sofas | N124: L-Shaped Sectional | O124: 16 | P124: 32117.9 | Q124: 0 | R124: 0 | S124: 513886.4 | T124: -58218.77 | U124: =PROPER(L124) -> Furniture | V124: =ABS(T124) -> 58218.77 | W124: =IF(Sales[[#This Row],[Quantity]]>=15, "Large","Small") -> Large | X124: =IF(Sales[[#This Row],[Quantity]]>=15,"Large",IF(Sales[[#This Row],[Quantity]]=14,"Medium","Small")) -> Large | Y124: =IF(AND(Sales[[#This Row],[Unit Price (₦)]]>68000,Sales[[#This Row],[Quantity]]>15),"Offer Discount", "No Discount") -> No Discount
A125: ORD-10952 | B125: 45125 | C125: 45131 | D125: Standard Class | E125: Fatima | F125: Gambo | G125: fatima.gambo@yahoo.com | H125: 8131758400 | I125: Home Office | J125: North | K125: Kano | L125: Furniture | M125: Tables | N125: Conference Table | O125: 10 | P125: 41994.88 | Q125: 20 | R125: 83989.76 | S125: 335959.04 | T125: -38042.29 | U125: =PROPER(L125) -> Furniture | V125: =ABS(T125) -> 38042.29 | W125: =IF(Sales[[#This Row],[Quantity]]>=15, "Large","Small") -> Small | X125: =IF(Sales[[#This Row],[Quantity]]>=15,"Large",IF(Sales[[#This Row],[Quantity]]=14,"Medium","Small")) -> Small | Y125: =IF(AND(Sales[[#This Row],[Unit Price (₦)]]>68000,Sales[[#This Row],[Quantity]]>15),"Offer Discount", "No Discount") -> No Discount
... A131: ORD-10142 | B131: 45136 | C131: 45141 | D131: Standard Class | E131: Fatima | F131: Lawal | G131: fatima.lawal@outlook.com | H131: 8034475536 | I131: Consumer | J131: West | K131: Osogbo | L131: Food & Beverages | M131: Snacks | N131: Popcorn 6-Pack | O131: 10 | P131: 7452.34 | Q131: 0 | R131: 0 | S131: 74523.4 | T131: 14038.34 | U131: =PROPER(L131) -> Food & Beverages | V131: =ABS(T131) -> 14038.34 | W131: =IF(Sales[[#This Row],[Quantity]]>=15, "Large","Small") -> Small | X131: =IF(Sales[[#This Row],[Quantity]]>=15,"Large",IF(Sales[[#This Row],[Quantity]]=14,"Medium","Small")) -> Small | Y131: =IF(AND(Sales[[#This Row],[Unit Price (₦)]]>68000,Sales[[#This Row],[Quantity]]>15),"Offer Discount", "No Discount") -> No Discount
A132: ORD-10875 | B132: 45133 | C132: 45141 | D132: Standard Class | E132: Taiwo | F132: Obi | G132: taiwo.obi@hotmail.com | H132: 00000000000 | I132: Corporate | J132: North | K132: Sokoto | L132: Technology | M132: Tablets | N132: Lenovo Tab M10 | O132: 17 | P132: 221462.1 | Q132: 5 | R132: 188242.79 | S132: 3576612.9 | T132: 1409077.3 | U132: =PROPER(L132) -> Technology | V132: =ABS(T132) -> 1409077.3 | W132: =IF(Sales[[#This Row],[Quantity]]>=15, "Large","Small") -> Large | X132: =IF(Sales[[#This Row],[Quantity]]>=15,"Large",IF(Sales[[#This Row],[Quantity]]=14,"Medium","Small")) -> Large | Y132: =IF(AND(Sales[[#This Row],[Unit Price (₦)]]>68000,Sales[[#This Row],[Quantity]]>15),"Offer Discount", "No Discount") -> Offer Discount
A133: ORD-10043 | B133: 45144 | C133: 45152 | D133: Standard Class | E133: Kunle | F133: Fashola | G133: kunle.fashola@outlook.com | H133: 8101861958 | I133: Consumer | J133: South | K133: Warri | L133: Office Supplies | M133: Art Supplies | N133: Coloured Pencils 24 | O133: 3 | P133: 3295.13 | Q133: 15 | R133: 1482.81 | S133: 8402.58 | T133: 1218.78 | U133: =PROPER(L133) -> Office Supplies | V133: =ABS(T133) -> 1218.78 | W133: =IF(Sales[[#This Row],[Quantity]]>=15, "Large","Small") -> Small | X133: =IF(Sales[[#This Row],[Quantity]]>=15,"Large",IF(Sales[[#This Row],[Quantity]]=14,"Medium","Small")) -> Small | Y133: =IF(AND(Sales[[#This Row],[Unit Price (₦)]]>68000,Sales[[#This Row],[Quantity]]>15),"Offer Discount", "No Discount") -> No Discount
A134: ORD-10584 | B134: 45149 | C134: 45154 | D134: Standard Class | E134: Seun | F134: Adeleke | G134: seun.adeleke@gmail.com | H134: 9053912192 | I134: Home Office | J134: East | K134: Owerri | L134: Food & Beverages | M134: Snacks | N134: Digestive Biscuits | O134: 14 | P134: 3352.21 | Q134: 20 | R134: 9386.19 | S134: 37544.75 | T134: 6851.67 | U134: =PROPER(L134) -> Food & Beverages | V134: =ABS(T134) -> 6851.67 | W134: =IF(Sales[[#This Row],[Quantity]]>=15, "Large","Small") -> Small | X134: =IF(Sales[[#This Row],[Quantity]]>=15,"Large",IF(Sales[[#This Row],[Quantity]]=14,"Medium","Small")) -> Medium | Y134: =IF(AND(Sales[[#This Row],[Unit Price (₦)]]>68000,Sales[[#This Row],[Quantity]]>15),"Offer Discount", "No Discount") -> No Discount
A135: ORD-10687 | B135: 45150 | C135: 45158 | D135: Standard Class | E135: Olumide | F135: Osei | G135: olumide.osei@yahoo.com | H135: 9078128056 | I135: Consumer | J135: East | K135: Enugu | L135: Technology | M135: Phones | N135: Infinix Note 30 | O135: 4 | P135: 430997.25 | Q135: 10 | R135: 172398.9 | S135: 1551590.1 | T135: 416107.21 | U135: =PROPER(L135) -> Technology | V135: =ABS(T135) -> 416107.21 | W135: =IF(Sales[[#This Row],[Quantity]]>=15, "Large","Small") -> Small | X135: =IF(Sales[[#This Row],[Quantity]]>=15,"Large",IF(Sales[[#This Row],[Quantity]]=14,"Medium","Small")) -> Small | Y135: =IF(AND(Sales[[#This Row],[Unit Price (₦)]]>68000,Sales[[#This Row],[Quantity]]>15),"Offer Discount", "No Discount") -> No Discount
A136: ORD-10810 | B136: 45156 | C136: 45161 | D136: Standard Class | E136: Hauwa | F136: Sowore | G136: unknown | H136: 8107541701 | I136: Home Office | J136: West | K136: Ilorin | L136: furniture | M136: Bookcases | N136: Corner Bookshelf | O136: 5 | P136: 15698.17 | Q136: 5 | R136: 3924.54 | S136: 74566.31 | T136: 16632.63 | U136: =PROPER(L136) -> Furniture | V136: =ABS(T136) -> 16632.63 | W136: =IF(Sales[[#This Row],[Quantity]]>=15, "Large","Small") -> Small | X136: =IF(Sales[[#This Row],[Quantity]]>=15,"Large",IF(Sales[[#This Row],[Quantity]]=14,"Medium","Small")) -> Small | Y136: =IF(AND(Sales[[#This Row],[Unit Price (₦)]]>68000,Sales[[#This Row],[Quantity]]>15),"Offer Discount", "No Discount") -> No Discount
A137: ORD-10247 | B137: 45155 | C137: 45162 | D137: Standard Class | E137: Deola | F137: Musa | G137: deola.musa@outlook.com | H137: 9028342987 | I137: Home Office | J137: North | K137: Abuja | L137: Clothing | M137: Bags | N137: Laptop Backpack | O137: 18 | P137: 22381.47 | Q137: 5 | R137: 20143.32 | S137: 382723.14 | T137: -26090.67 | U137: =PROPER(L137) -> Clothing | V137: =ABS(T137) -> 26090.67 | W137: =IF(Sales[[#This Row],[Quantity]]>=15, "Large","Small") -> Large | X137: =IF(Sales[[#This Row],[Quantity]]>=15,"Large",IF(Sales[[#This Row],[Quantity]]=14,"Medium","Small")) -> Large | Y137: =IF(AND(Sales[[#This Row],[Unit Price (₦)]]>68000,Sales[[#This Row],[Quantity]]>15),"Offer Discount", "No Discount") -> No Discount
A138: ORD-10636 | B138: 45165 | C138: 45170 | D138: Standard Class | E138: Adebayo | F138: Adeleke | G138: adebayo.adeleke@yahoo.com | H138: 8163070908 | I138: Corporate | J138: East | K138: Owerri | L138: Technology | M138: Accessories | N138: Wristwatch | O138: 12 | P138: 17214.26 | Q138: 0 | R138: 0 | S138: 206571.12 | T138: -24800.68 | U138: =PROPER(L138) -> Technology | V138: =ABS(T138) -> 24800.68 | W138: =IF(Sales[[#This Row],[Quantity]]>=15, "Large","Small") -> Small | X138: =IF(Sales[[#This Row],[Quantity]]>=15,"Large",IF(Sales[[#This Row],[Quantity]]=14,"Medium","Small")) -> Small | Y138: =IF(AND(Sales[[#This Row],[Unit Price (₦)]]>68000,Sales[[#This Row],[Quantity]]>15),"Offer Discount", "No Discount") -> No Discount
A139: ORD-10868 | B139: 45167 | C139: 45172 | D139: Standard Class | E139: Ibrahim | F139: Adeyemi | G139: ibrahim.adeyemi@gmail.com | H139: 8065251915 | I139: Consumer | J139: South | K139: Lagos | L139: Clothing | M139: Shirts | N139: T-Shirt 3-Pack | O139: 13 | P139: 42629.61 | Q139: 0 | R139: 0 | S139: 554184.93 | T139: 148904.56 | U139: =PROPER(L139) -> Clothing | V139: =ABS(T139) -> 148904.56 | W139: =IF(Sales[[#This Row],[Quantity]]>=15, "Large","Small") -> Small | X139: =IF(Sales[[#This Row],[Quantity]]>=15,"Large",IF(Sales[[#This Row],[Quantity]]=14,"Medium","Small")) -> Small | Y139: =IF(AND(Sales[[#This Row],[Unit Price (₦)]]>68000,Sales[[#This Row],[Quantity]]>15),"Offer Discount", "No Discount") -> No Discount
A140: ORD-10794 | B140: 45169 | C140: 45175 | D140: Standard Class | E140: Amara | F140: Lawal | G140: amara.lawal@hotmail.com | H140: 8038364357 | I140: Consumer | J140: West | K140: Ilorin | L140: Clothing | M140: Accessories | N140: Wallet Genuine Leather | O140: 7 | P140: 44930.02 | Q140: 15 | R140: 47176.52 | S140: 267333.62 | T140: -10256.3 | U140: =PROPER(L140) -> Clothing | V140: =ABS(T140) -> 10256.3 | W140: =IF(Sales[[#This Row],[Quantity]]>=15, "Large","Small") -> Small | X140: =IF(Sales[[#This Row],[Quantity]]>=15,"Large",IF(Sales[[#This Row],[Quantity]]=14,"Medium","Small")) -> Small | Y140: =IF(AND(Sales[[#This Row],[Unit Price (₦)]]>68000,Sales[[#This Row],[Quantity]]>15),"Offer Discount", "No Discount") -> No Discount
A141: ORD-10639 | B141: 45170 | C141: 45178 | D141: Standard Class | E141: =E142 -> Obinna | F141: =F140 -> Lawal | G141: bukola.adeyemi@hotmail.com | H141: 9028329845 | I141: Corporate | J141: South | K141: Benin City | L141: Technology | M141: Phones | N141: Xiaomi Redmi 12 | O141: 11 | P141: 207227.08 | Q141: 25 | R141: 569874.47 | S141: 1709623.4 | T141: 702531.94 | U141: =PROPER(L141) -> Technology | V141: =ABS(T141) -> 702531.94 | W141: =IF(Sales[[#This Row],[Quantity]]>=15, "Large","Small") -> Small | X141: =IF(Sales[[#This Row],[Quantity]]>=15,"Large",IF(Sales[[#This Row],[Quantity]]=14,"Medium","Small")) -> Small | Y141: =IF(AND(Sales[[#This Row],[Unit Price (₦)]]>68000,Sales[[#This Row],[Quantity]]>15),"Offer Discount", "No Discount") -> No Discount
...

Sheet Sheet2

Sheet Pivot Tables_Dash
A2: Region | B2: Sum of Sales (₦) | C2: Sum of Profit (₦)
A3: East | B3: 1.3663859e+08 | C3: 17563180
A4: North | B4: 1.5817512e+08 | C4: 25803412
A5: South | B5: 1.5602081e+08 | C5: 23823356
A6: West | B6: 1.8080754e+08 | C6: 25524221
A7: Grand Total | B7: 6.3164206e+08 | C7: 92714169
A11: Segment | B11: Sum of Sales (₦)
A12: Consumer | B12: 2.1019938e+08
A13: Corporate | B13: 2.1105589e+08
A14: Home Office | B14: 2.1038679e+08
A15: Grand Total | B15: 6.3164206e+08
A18: Segment | B18: Sum of Profit (₦)
A19: Consumer | B19: 0.32881072
A20: Corporate | B20: 0.39656557
A21: Home Office | B21: 0.27462372
A22: Grand Total | B22: 1
A26: Segment | B26: Sum of Sales (₦)
A27: Lenovo Tab M10 | B27: 16227715
A28: Epson EcoTank | B28: 17780907
A29: Tecno Spark 10 | B29: 17800951
A30: Silk Scarf | B30: 17823078
A31: HP LaserJet Pro | B31: 18345488
A32: Dell Inspiron 15 | B32: 18349679
A33: iPad 10th Gen | B33: 18973365
A34: Infinix Note 30 | B34: 21390308
A35: Xiaomi Redmi 12 | B35: 23949166
A36: Lenovo IdeaPad 3 | B36: 30402493
A37: Grand Total | B37: 2.0104315e+08
A40: Segment | B40: Sum of Profit (₦)
A41: Epson EcoTank | B41: 2494964.6
A42: Belt Leather | B42: 2698327.2
A43: Canon PIXMA G3411 | B43: 2916771.3
A44: Samsung Tab A8 | B44: 2996877.6
A45: Wristwatch | B45: 3370942.5
A46: Sunglasses UV400 | B46: 3741308.4
A47: Brother HL-L2350DW | B47: 3750595.6
A48: Silk Scarf | B48: 3794707.1
A49: Wallet Genuine Leather | B49: 4263666.7
A50: Lenovo IdeaPad 3 | B50: 5234113.8
A51: Grand Total | B51: 35262275
A55: Row Labels | B55: Sum of Sales (₦)
A56: Abuja | B56: 29430778
A57: Awka | B57: 31418383
A58: Ado-Ekiti | B58: 31636825
A59: Osogbo | B59: 37891363
A60: Kaduna | B60: 39122901
A61: Sokoto | B61: 39312243
A62: Ilorin | B62: 40699028
A63: Akure | B63: 40865108
A64: Benin City | B64: 42376983
A65: Onitsha | B65: 45282027
A66: Grand Total | B66: 3.7803564e+08
A70: Year | B70: Total Sales | C70: Total Profit
A71: 2022 | B71: 2.122587e+08 | C71: 31235026
A72: 2023 | B72: 2.4386327e+08 | C72: 34648154
A73: 2024 | B73: 1.7552009e+08 | C73: 26830989
A74: Grand Total | B74: 6.3164206e+08 | C74: 92714169
A77: Year | B77: Total Sales
A78: 2022
A79: Jan | B79: 21317449
A80: Feb | B80: 11003259
A81: Mar | B81: 17494630
A82: Apr | B82: 19856214
A83: May | B83: 22724582
A84: Jun | B84: 12254963
A85: Jul | B85: 20289988
A86: Aug | B86: 10051073
A87: Sep | B87: 15121861
A88: Oct | B88: 24503636
A89: Nov | B89: 25069210
A90: Dec | B90: 12571836
A91: 2023
A92: Jan | B92: 18481577
A93: Feb | B93: 19432828
A94: Mar | B94: 24032916
A95: Apr | B95: 17747149
A96: May | B96: 18888651
A97: Jun | B97: 13450579
A98: Jul | B98: 29834523
A99: Aug | B99: 22317901
A100: Sep | B100: 20481222
A101: Oct | B101: 14378859
A102: Nov | B102: 25224602
A103: Dec | B103: 19592467
A104: 2024
A105: Jan | B105: 13545065
A106: Feb | B106: 20880964
A107: Mar | B107: 16042460
A108: Apr | B108: 24825942
A109: May | B109: 21385249
A110: Jun | B110: 8972923.8
A111: Jul | B111: 19054102
A112: Aug | B112: 11576786
A113: Sep | B113: 15800323
A114: Oct | B114: 7207009.2
A115: Nov | B115: 8118647.7
A116: Dec | B116: 8110617.6
A117: Grand Total | B117: 6.3164206e+08

Sheet Pivot Tables
B2: Region | C2: Total Sales (₦) | D2: Total Profit (₦)
B3: West | C3: 1.8080754e+08 | D3: 25524221
B4: North | C4: 1.5817512e+08 | D4: 25803412
B5: South | C5: 1.5602081e+08 | D5: 23823356
B6: East | C6: 1.3663859e+08 | D6: 17563180
B7: Grand Total | C7: 6.3164206e+08 | D7: 92714169
B11: Sum of Sales (₦) | C11: Column Labels
B12: Segment | C12: East | D12: North | E12: South | F12: West | G12: Grand Total
B13: Consumer | C13: 33572062 | D13: 79501042 | E13: 49303178 | F13: 47823101 | G13: 2.1019938e+08
B14: Corporate | C14: 55802235 | D14: 37780042 | E14: 44428501 | F14: 73045107 | G14: 2.1105589e+08
B15: Home Office | C15: 47264289 | D15: 40894033 | E15: 62289136 | F15: 59939336 | G15: 2.1038679e+08
B16: Grand Total | C16: 1.3663859e+08 | D16: 1.5817512e+08 | E16: 1.5602081e+08 | F16: 1.8080754e+08 | G16: 6.3164206e+08
B20: Region | C20: (All)
B22: Year | C22: Sum of Sales (₦)
B23: 2022 | C23: 2.122587e+08
B24: 2023 | C24: 2.4386327e+08
B25: 2024 | C25: 1.7552009e+08
B26: Grand Total | C26: 6.3164206e+08
B29: Segment | C29: Category | D29: Sum of Sales (₦)
B30: Consumer | C30: Clothing | D30: 18516085
B31: Consumer | C31: Food & Beverages | D31: 4509040.8
B32: Consumer | C32: Furniture | D32: 57404282
B33: Consumer | C33: Office Supplies | D33: 10418374
B34: Consumer | C34: Office Supply | D34: 31699.51
B35: Consumer | C35: Technology | D35: 1.193199e+08
B36: Consumer Total | D36: 2.1019938e+08
B37: Corporate | C37: Clothing | D37: 13158930
B38: Corporate | C38: Food & Beverages | D38: 2733263.4
B39: Corporate | C39: Furniture | D39: 56285678
B40: Corporate | C40: Office Supplies | D40: 7924002.9
B41: Corporate | C41: Technology | D41: 1.3095401e+08
B42: Corporate Total | D42: 2.1105589e+08
B43: Home Office | C43: Clothing | D43: 19604096
B44: Home Office | C44: Food & Beverages | D44: 8991697.8
B45: Home Office | C45: Furniture | D45: 57580267
B46: Home Office | C46: Office Supplies | D46: 7182681.8
B47: Home Office | C47: Technology | D47: 1.1702805e+08
B48: Home Office Total | D48: 2.1038679e+08

Sheet LOOKUP FUNCTIONS
A2: VLOOKUP | E2: Order ID | F2: Products | G2: Sales | H2: Profit
E3: ORD-10002 | F3: =VLOOKUP(A24,Sales[],14,FALSE) -> Vegetable Oil 5L | G3: =VLOOKUP(A24,Sales[],19,0) -> 3520.78 | H3: =VLOOKUP(E3,Sales[],17,FALSE) -> 0
A4: Enter Order ID → | B4: ORD-10001 | C4: ORD-10002 | E4: ORD-10003 | F4: =VLOOKUP(A25,Sales[],14,FALSE) -> Padded Envelopes | G4: =VLOOKUP(A25,Sales[],19,0) -> 36279.7 | H4: =VLOOKUP(E4,Sales[],17,FALSE) -> 0
A5: First Name | B5: =VLOOKUP(B4,'Raw Data'!1:1048576,5,FALSE) -> Kemi | C5: =VLOOKUP(C4,'Raw Data'!1:1048576,5,FALSE) -> Lanre | E5: ORD-10004 | F5: =VLOOKUP(A26,Sales[],14,FALSE) -> Beans 5kg | G5: =VLOOKUP(A26,Sales[],19,0) -> 6928 | H5: =VLOOKUP(E5,Sales[],17,FALSE) -> 0
A6: Region | B6: =VLOOKUP(B4,Sales[],9,FALSE) -> Home Office | E6: ORD-10005 | F6: =VLOOKUP(A27,Sales[],14,FALSE) -> Brother HL-L2350DW | G6: =VLOOKUP(A27,Sales[],19,0) -> 1739828.4 | H6: =VLOOKUP(E6,Sales[],17,FALSE) -> 10
A7: Category | B7: =VLOOKUP(B4,Sales[],12,0) -> Food & Beverages | E7: ORD-10006 | F7: =VLOOKUP(A28,Sales[],14,FALSE) -> Filing Cabinet | G7: =VLOOKUP(A28,Sales[],19,0) -> 1622405.2 | H7: =VLOOKUP(E7,Sales[],17,FALSE) -> 25
A8: Product Name | B8: =VLOOKUP(B4,Sales[],14,0) -> Vegetable Oil 5L
A9: Sales Amount (₦) | B9: =VLOOKUP(B4,Sales[],19,0) -> 3520.78
A10: Profit (₦)
A11: Ship Mode
A12: Order Date
A15: HLOOKUP
A16: Enter Order ID → | B16: ORD-10813 | C16: ORD-10815
A17: Customer Name | B17: =HLOOKUP('LOOKUP FUNCTIONS'!B16,'hlookup data'!1:1048576,5,0) -> Yemi | C17: =HLOOKUP(C16,'hlookup data'!1:1048576,5,0) -> Seun
A18: Ship Mode | B18: =HLOOKUP(B16,'hlookup data'!1:1048576,4,0) -> First Class
A19: Category
A22: XLOOKUP
A23: Order ID | B23: First Name | C23: ShipMode | D23: Category | E23: Unit Price (₦)
A24: ORD-10001 | B24: =_xlfn.XLOOKUP(A24,'Raw Data'!A:A,'Raw Data'!E:E,"Not found",0) -> Kemi | C24: =_xlfn.XLOOKUP(A24,'Raw Data'!A:A,'Raw Data'!D:D) -> First Class | D24: =_xlfn.XLOOKUP(A24,'Raw Data'!A:A,'Raw Data'!L:L,"Not Found",0) -> Food & Beverages | E24: =_xlfn.XLOOKUP(A24,'Raw Data'!A:A,'Raw Data'!P:P) -> 529.44
A25: ORD-10005 | B25: =_xlfn.XLOOKUP(A25,'Raw Data'!A:A,'Raw Data'!E:E,"Not found",0) -> Chisom | C25: =_xlfn.XLOOKUP(A25,'Raw Data'!A:A,'Raw Data'!D:D) -> Same Day | D25: =_xlfn.XLOOKUP(A25,'Raw Data'!A:A,'Raw Data'!L:L,"Not Found",0) -> Office Supplies | E25: =_xlfn.XLOOKUP(A25,'Raw Data'!A:A,'Raw Data'!P:P) -> 2121.62
A26: ORD-10007 | B26: =_xlfn.XLOOKUP(A26,'Raw Data'!A:A,'Raw Data'!E:E,"Not found",0) -> Tunde | C26: =_xlfn.XLOOKUP(A26,'Raw Data'!A:A,'Raw Data'!D:D) -> Second Class | D26: =_xlfn.XLOOKUP(A26,'Raw Data'!A:A,'Raw Data'!L:L,"Not Found",0) -> Food & Beverages | E26: =_xlfn.XLOOKUP(A26,'Raw Data'!A:A,'Raw Data'!P:P) -> 6928
A27: ORD-10813 | B27: =_xlfn.XLOOKUP(A27,'Raw Data'!A:A,'Raw Data'!E:E,"Not found",0) -> Yemi | C27: =_xlfn.XLOOKUP(A27,'Raw Data'!A:A,'Raw Data'!D:D) -> First Class | D27: =_xlfn.XLOOKUP(A27,'Raw Data'!A:A,'Raw Data'!L:L,"Not Found",0) -> Technology | E27: =_xlfn.XLOOKUP(A27,'Raw Data'!A:A,'Raw Data'!P:P) -> 102342.85
A28: ORD-10902 | B28: =_xlfn.XLOOKUP(A28,'Raw Data'!A:A,'Raw Data'!E:E,"Not found",0) -> Chisom | C28: =_xlfn.XLOOKUP(A28,'Raw Data'!A:A,'Raw Data'!D:D) -> First Class | D28: =_xlfn.XLOOKUP(A28,'Raw Data'!A:A,'Raw Data'!L:L,"Not Found",0) -> Furniture | E28: =_xlfn.XLOOKUP(A28,'Raw Data'!A:A,'Raw Data'!P:P) -> 85389.75
A32: INDEX FUNCTION | D32: MATCH
A33: =INDEX('Raw Data'!I:I,20) -> Home Office | B33: =INDEX('Raw Data'!E:E,10) -> Wale | D33: Wale | E33: =MATCH(D33,'Raw Data'!E:E,0) -> 10
A34: =INDEX('Raw Data'!1:1048576,20,4) -> Standard Class | B34: =INDEX('Raw Data'!1:1048576,7,4) -> Standard Class | D34: Chisom | E34: =MATCH(D34,'Raw Data'!E:E,0) -> 8
D35: Tunde | E35: =MATCH(D35,'Raw Data'!E:E,0) -> 28
A38: INDEX AND MATCH
A39: Order ID | B39: Sales | C39: Discount
A40: ORD-10001 | B40: =INDEX('Raw Data'!S:S,MATCH('LOOKUP FUNCTIONS'!A40,'Raw Data'!A:A,0)) -> 3520.78 | C40: =INDEX('Raw Data'!R:R,MATCH(A40,'Raw Data'!A:A,0)) -> 185.3
A41: ORD-10005 | B41: =INDEX('Raw Data'!S:S,MATCH('LOOKUP FUNCTIONS'!A41,'Raw Data'!A:A,0)) -> 36279.7 | C41: =INDEX('Raw Data'!R:R,MATCH(A41,'Raw Data'!A:A,0)) -> 4031.08
A42: ORD-10007 | B42: =INDEX('Raw Data'!S:S,MATCH('LOOKUP FUNCTIONS'!A42,'Raw Data'!A:A,0)) -> 6928 | C42: =INDEX('Raw Data'!R:R,MATCH(A42,'Raw Data'!A:A,0)) -> 0
A43: ORD-10813 | B43: =INDEX('Raw Data'!S:S,MATCH('LOOKUP FUNCTIONS'!A43,'Raw Data'!A:A,0)) -> 1739828.4 | C43: =INDEX('Raw Data'!R:R,MATCH(A43,'Raw Data'!A:A,0)) -> 0
A44: ORD-10902 | B44: =INDEX('Raw Data'!S:S,MATCH('LOOKUP FUNCTIONS'!A44,'Raw Data'!A:A,0)) -> 1622405.2 | C44: =INDEX('Raw Data'!R:R,MATCH(A44,'Raw Data'!A:A,0)) -> 0
A48: FILTER FUNCTION
A50: {=_xlfn._xlws.FILTER(Sales[#All],(Sales[[#All],[Region]]="East")*(Sales[[#All],[Quantity]]>10))} -> ORD-10852 | B50: 44611 | C50: 44616 | D50: Standard Class | E50: Zainab | F50: Sanusi | G50: zainab.sanusi@gmail.com | H50: 8034674225 | I50: Consumer | J50: East | K50: Onitsha | L50: Furniture | M50: Tables | N50: Conference Table | O50: 11 | P50: 94100.43 | Q50: 15 | R50: 155265.71 | S50: 879839.02 | T50: 267099.63 | U50: Furniture | V50: 267099.63 | W50: Small | X50: Small | Y50: No Discount
A51: ORD-10092 | B51: 44659 | C51: 44665 | D51: Standard Class | E51: Amara | F51: Okonkwo | G51: chibundo.tinubu@hotmail.com | H51: 8062859886 | I51: Corporate | J51: East | K51: Onitsha | L51: Clothing | M51: Accessories | N51: Wallet Genuine Leather | O51: 17 | P51: 2706.72 | Q51: 5 | R51: 2300.71 | S51: 43713.53 | T51: 12289.04 | U51: Clothing | V51: 12289.04 | W51: Large | X51: Large | Y51: No Discount
A52: ORD-10587 | B52: 44695 | C52: 44701 | D52: Standard Class | E52: Deola | F52: Okonkwo | G52: deola.okonkwo@outlook.com | H52: 8134384399 | I52: Home Office | J52: East | K52: Onitsha | L52: Technology | M52: Phones | N52: Tecno Spark 10 | O52: 19 | P52: 51992.12 | Q52: 0 | R52: 0 | S52: 987850.28 | T52: 185956.49 | U52: Technology | V52: 185956.49 | W52: Large | X52: Large | Y52: No Discount
A53: ORD-10273 | B53: 44722 | C53: 44730 | D53: Standard Class | E53: Ayo | F53: Okonkwo | G53: ayo.okonkwo@gmail.com | H53: 8039091518 | I53: Consumer | J53: East | K53: Onitsha | L53: Office Supplies | M53: Labels | N53: Price Tag Labels | O53: 19 | P53: 12562.34 | Q53: 10 | R53: 23868.45 | S53: 214816.01 | T53: 31037.31 | U53: Office Supplies | V53: 31037.31 | W53: Large | X53: Large | Y53: No Discount
A54: ORD-10936 | B54: 44755 | C54: 44760 | D54: Standard Class | E54: Yemi | F54: Sanusi | G54: yemi.sanusi@gmail.com | H54: 8147058725 | I54: Consumer | J54: East | K54: Enugu | L54: Clothing | M54: Accessories | N54: Belt Leather | O54: 19 | P54: 13364.14 | Q54: 25 | R54: 63479.66 | S54: 190439 | T54: 73702.69 | U54: Clothing | V54: 73702.69 | W54: Large | X54: Large | Y54: No Discount
A55: ORD-10609 | B55: 44773 | C55: 44778 | D55: Standard Class | E55: Adebayo | F55: Alakija | G55: adebayo.alakija@gmail.com | H55: 8063379602 | I55: Consumer | J55: East | K55: Enugu | L55: Office Supplies | M55: Pens & Pencils | N55: Staedtler HB Pencils | O55: 16 | P55: 2773.04 | Q55: 10 | R55: 4436.86 | S55: 39931.78 | T55: 15878.13 | U55: Office Supplies | V55: 15878.13 | W55: Large | X55: Large | Y55: No Discount
A56: ORD-10980 | B56: 44799 | C56: 44805 | D56: Standard Class | E56: Gbenga | F56: Otedola | G56: gbenga.otedola@gmail.com | H56: 9029855180 | I56: Home Office | J56: East | K56: Aba | L56: Clothing | M56: Trousers | N56: Joggers | O56: 16 | P56: 14832.93 | Q56: 25 | R56: 59331.72 | S56: 177995.16 | T56: 51973.67 | U56: Clothing | V56: 51973.67 | W56: Large | X56: Large | Y56: No Discount
A57: ORD-10492 | B57: 44837 | C57: 44842 | D57: Standard Class | E57: Nike | F57: Fashola | G57: nike.fashola@outlook.com | H57: 8131690263 | I57: Home Office | J57: East | K57: Aba | L57: Clothing | M57: Accessories | N57: Wallet Genuine Leather | O57: 15 | P57: 16464.08 | Q57: 20 | R57: 49392.24 | S57: 197568.96 | T57: 21634.47 | U57: Clothing | V57: 21634.47 | W57: Large | X57: Large | Y57: No Discount
A58: ORD-10063 | B58: 44850 | C58: 44856 | D58: Standard Class | E58: Ikenna | F58: Lawal | G58: ikenna.lawal@outlook.com | H58: 8067619862 | I58: Corporate | J58: East | K58: Enugu | L58: Technology | M58: Tablets | N58: Amazon Fire HD 10 | O58: 14 | P58: 68761.1 | Q58: 10 | R58: 82513.32 | S58: 742619.88 | T58: 149070.59 | U58: Technology | V58: 149070.59 | W58: Small | X58: Medium | Y58: No Discount
A59: ORD-10671 | B59: 44890 | C59: 44897 | D59: Standard Class | E59: Emeka | F59: Eze | G59: emeka.eze@yahoo.com | H59: 9051428411 | I59: Corporate | J59: East | K59: Owerri | L59: Technology | M59: Printers | N59: Canon PIXMA G3411 | O59: 17 | P59: 366494.88 | Q59: 25 | R59: 1557603.2 | S59: 4672809.7 | T59: 1495674.3 | U59: Technology | V59: 1495674.3 | W59: Large | X59: Large | Y59: Offer Discount
A60: ORD-10150 | B60: 44971 | C60: 44977 | D60: Standard Class | E60: Taiwo | F60: Okonkwo | G60: taiwo.okonkwo@hotmail.com | H60: 9014517316 | I60: Corporate | J60: East | K60: Owerri | L60: Clothing | M60: Shoes | N60: Men's Oxford Shoes | O60: 14 | P60: 37215.52 | Q60: 20 | R60: 104203.46 | S60: 416813.82 | T60: -27715 | U60: Clothing | V60: 27715 | W60: Small | X60: Medium | Y60: No Discount
A61: ORD-10680 | B61: 44993 | C61: 45001 | D61: Standard Class | E61: Ronke | F61: Chukwu | G61: ronke.chukwu@outlook.com | H61: 8066827492 | I61: Consumer | J61: East | K61: Onitsha | L61: Office Supplies | M61: Binders | N61: Ring Binder A4 | O61: 16 | P61: 7552.16 | Q61: 20 | R61: 24166.91 | S61: 96667.65 | T61: -1529.28 | U61: Office Supplies | V61: 1529.28 | W61: Large | X61: Large | Y61: No Discount
A62: ORD-10584 | B62: 45149 | C62: 45154 | D62: Standard Class | E62: Seun | F62: Adeleke | G62: seun.adeleke@gmail.com | H62: 9053912192 | I62: Home Office | J62: East | K62: Owerri | L62: Food & Beverages | M62: Snacks | N62: Digestive Biscuits | O62: 14 | P62: 3352.21 | Q62: 20 | R62: 9386.19 | S62: 37544.75 | T62: 6851.67 | U62: Food & Beverages | V62: 6851.67 | W62: Small | X62: Medium | Y62: No Discount
... A101: ORD-10716 | B101: 45535 | C101: 45538 | D101: Second Class | E101: Adebayo | F101: Danjuma | G101: adebayo.danjuma@outlook.com | H101: 7037340280 | I101: Consumer | J101: East | K101: Enugu | L101: Food & Beverages | M101: Drinks | N101: Water 5L x6 | O101: 12 | P101: 5699.92 | Q101: 0 | R101: 0 | S101: 68399.04 | T101: -3744.83 | U101: Food & Beverages | V101: 3744.83 | W101: Small | X101: Small | Y101: No Discount
A102: ORD-10790 | B102: 45585 | C102: 45588 | D102: Second Class | E102: Adaeze | F102: Adebayo | G102: adaeze.adebayo@yahoo.com | H102: 1234567890 | I102: Corporate | J102: East | K102: Owerri | L102: Technology | M102: Laptops | N102: Asus VivoBook 14 | O102: 16 | P102: 151122.09 | Q102: 0 | R102: 0 | S102: 2417953.4 | T102: 734909.59 | U102: Technology | V102: 734909.59 | W102: Large | X102: Large | Y102: Offer Discount
A103: ORD-10131 | B103: 45629 | C103: 45632 | D103: Second Class | E103: Chibundo | F103: Eze | G103: chibundo.eze@outlook.com | H103: 8033938247 | I103: Corporate | J103: East | K103: Onitsha | L103: Clothing | M103: Accessories | N103: Silk Scarf | O103: 12 | P103: 4016.02 | Q103: 15 | R103: 7228.84 | S103: 40963.4 | T103: 13169.03 | U103: Clothing | V103: 13169.03 | W103: Small | X103: Small | Y103: No Discount
A104: ORD-10455 | B104: 45627 | C104: 45632 | D104: Second Class | E104: Nike | F104: Nwosu | G104: nike.nwosu@gmail.com | H104: 8156238726 | I104: Home Office | J104: East | K104: Owerri | L104: Food & Beverages | M104: Grains | N104: Semolina 5kg | O104: 18 | P104: 480.35 | Q104: 10 | R104: 864.63 | S104: 7781.67 | T104: -40.43 | U104: Food & Beverages | V104: 40.43 | W104: Large | X104: Large | Y104: No Discount
A105: ORD-10862 | B105: 44565 | C105: 44565 | D105: Same Day | E105: Kehinde | F105: Gambo | G105: kehinde.gambo@hotmail.com | H105: 8159196133 | I105: Consumer | J105: East | K105: Onitsha | L105: Furniture | M105: Chairs | N105: Visitor Chair | O105: 20 | P105: 70613.98 | Q105: 10 | R105: 141227.96 | S105: 1271051.6 | T105: 157298.35 | U105: Furniture | V105: 157298.35 | W105: Large | X105: Large | Y105: Offer Discount
A106: ORD-10288 | B106: 44578 | C106: 44578 | D106: Same Day | E106: Sade | F106: Okafor | G106: sade.okafor@gmail.com | H106: 8144643811 | I106: Consumer | J106: East | K106: Aba | L106: Office Supplies | M106: Envelopes | N106: Padded Envelopes | O106: 16 | P106: 19750.27 | Q106: 10 | R106: 31600.43 | S106: 284403.89 | T106: 36463.62 | U106: Office Supplies | V106: 36463.62 | W106: Large | X106: Large | Y106: No Discount
A107: ORD-10363 | B107: 44595 | C107: 44595 | D107: Same Day | E107: Adaeze | F107: Adeleke | G107: adaeze.adeleke@outlook.com | H107: 9021718308 | I107: Home Office | J107: East | K107: Owerri | L107: Clothing | M107: Shirts | N107: Women's Blouse | O107: 17 | P107: 36705.46 | Q107: 20 | R107: 124798.56 | S107: 499194.26 | T107: 206693.32 | U107: Clothing | V107: 206693.32 | W107: Large | X107: Large | Y107: No Discount
A108: ORD-10881 | B108: 44625 | C108: 44626 | D108: Same Day | E108: Tunde | F108: Otedola | G108: tunde.otedola@gmail.com | H108: 9013442155 | I108: Consumer | J108: East | K108: Owerri | L108: Technology | M108: Tablets | N108: Lenovo Tab M10 | O108: 15 | P108: 186071.29 | Q108: 10 | R108: 279106.93 | S108: 2511962.4 | T108: 80629.3 | U108: Technology | V108: 80629.3 | W108: Large | X108: Large | Y108: No Discount
A109: ORD-10280 | B109: 44708 | C109: 44708 | D109: Same Day | E109: Aisha | F109: Osei | G109: aisha.osei@yahoo.com | H109: 7036316334 | I109: Home Office | J109: East | K109: Owerri | L109: Office Supplies | M109: Fasteners | N109: Binder Clips Asst. | O109: 13 | P109: 15331.93 | Q109: 10 | R109: 19931.51 | S109: 179383.58 | T109: 68634.86 | U109: Office Supplies | V109: 68634.86 | W109: Small | X109: Small | Y109: No Discount
A110: ORD-10052 | B110: 44752 | C110: 44752 | D110: Same Day | E110: Bola | F110: Fashola | G110: bola.fashola@gmail.com | H110: 9073583206 | I110: Consumer | J110: East | K110: Awka | L110: Clothing | M110: Shoes | N110: Sandals | O110: 14 | P110: 32332.7 | Q110: 20 | R110: 90531.56 | S110: 362126.24 | T110: 158664.45 | U110: Clothing | V110: 158664.45 | W110: Small | X110: Medium | Y110: No Discount
A111: ORD-10149 | B111: 44840 | C111: 44841 | D111: Same Day | E111: Chisom | F111: Alakija | G111: chisom.alakija@yahoo.com | H111: 8146271120 | I111: Corporate | J111: East | K111: Owerri | L111: Furniture | M111: Storage | N111: Plastic Drawers | O111: 16 | P111: 58129.08 | Q111: 5 | R111: 46503.26 | S111: 883562.02 | T111: 40230.12 | U111: Furniture | V111: 40230.12 | W111: Large | X111: Large | Y111: No Discount
A112: ORD-10385 | B112: 44894 | C112: 44895 | D112: Same Day | E112: Bola | F112: Okonkwo | G112: bola.okonkwo@hotmail.com | H112: 8143439136 | I112: Corporate | J112: East | K112: Onitsha | L112: Clothing | M112: Shoes | N112: Women's Heels | O112: 18 | P112: 2184.66 | Q112: 25 | R112: 9830.97 | S112: 29492.91 | T112: 1438.32 | U112: Clothing | V112: 1438.32 | W112: Large | X112: Large | Y112: No Discount
A113: ORD-10062 | B113: 44921 | C113: 44921 | D113: Same Day | E113: Kemi | F113: Sule | G113: kemi.sule@outlook.com | H113: 8159418719 | I113: Home Office | J113: East | K113: Aba | L113: Office Supplies | M113: Art Supplies | N113: Acrylic Paint Kit | O113: 16 | P113: 6795.77 | Q113: 10 | R113: 10873.23 | S113: 97859.09 | T113: 29155.71 | U113: Office Supplies | V113: 29155.71 | W113: Large | X113: Large | Y113: No Discount
A114: ORD-10206 | B114: 45112 | C114: 45113 | D114: Same Day | E114: Amara | F114: Osei | G114: amara.osei@outlook.com | H114: 8165703436 | I114: Consumer | J114: East | K114: Onitsha | L114: CLOTHING | M114: Shirts | N114: Women's Blouse | O114: 15 | P114: 7778.58 | Q114: 10 | R114: 11667.87 | S114: 105010.83 | T114: 1223.58 | U114: Clothing | V114: 1223.58 | W114: Large | X114: Large | Y114: No Discount
... A116: ORD-10110 | B116: 45147 | C116: 45147 | D116: Same Day | E116: Yemi | F116: Ogundipe | G116: yemi.ogundipe@yahoo.com | H116: 8167136730 | I116: Home Office | J116: East | K116: Owerri | L116: Clothing | M116: Shoes | N116: Men's Oxford Shoes | O116: 19 | P116: 19225.01 | Q116: 25 | R116: 91318.8 | S116: 273956.39 | T116: -9097.22 | U116: Clothing | V116: 9097.22 | W116: Large | X116: Large | Y116: No Discount
A117: ORD-10402 | B117: 45157 | C117: 45158 | D117: Same Day | E117: Musa | F117: Lawal | G117: musa.lawal@gmail.com | H117: 0803-123-4567 | I117: Consumer | J117: East | K117: Owerri | L117: OFFICE SUPPLIES | M117: Binders | N117: Ring Binder A4 | O117: 16 | P117: 24968.72 | Q117: 0 | R117: 0 | S117: 399499.52 | T117: 35084.79 | U117: Office Supplies | V117: 35084.79 | W117: Large | X117: Large | Y117: No Discount
A118: ORD-10472 | B118: 45234 | C118: 45234 | D118: Same Day | E118: Kemi | F118: Tinubu | G118: kemi.tinubu@gmail.com | H118: 9058994829 | I118: Consumer | J118: East | K118: Aba | L118: Technology | M118: Laptops | N118: Lenovo IdeaPad 3 | O118: 16 | P118: 194725.92 | Q118: 15 | R118: 467342.21 | S118: 2648272.5 | T118: 457830.36 | U118: Technology | V118: 457830.36 | W118: Large | X118: Large | Y118: Offer Discount
A119: ORD-10928 | B119: 45253 | C119: 45253 | D119: Same Day | E119: Dayo | F119: Buhari | G119: dayo.buhari@hotmail.com | H119: 8153048456 | I119: Consumer | J119: East | K119: Onitsha | L119: Clothing | M119: Accessories | N119: Wristwatch | O119: 12 | P119: 35776.37 | Q119: 0 | R119: 0 | S119: 429316.44 | T119: 26593.62 | U119: Clothing | V119: 26593.62 | W119: Small | X119: Small | Y119: No Discount
A120: ORD-10388 | B120: 45319 | C120: 45320 | D120: Same Day | E120: Uchenna | F120: Okonkwo | G120: uchenna.okonkwo@outlook.com | H120: 7036894759 | I120: Consumer | J120: East | K120: Owerri | L120: Office Supplies | M120: Envelopes | N120: C5 Envelopes | O120: 15 | P120: 2646.17 | Q120: 15 | R120: 5953.88 | S120: 33738.67 | T120: 11208.37 | U120: Office Supplies | V120: 11208.37 | W120: Large | X120: Large | Y120: No Discount
A121: ORD-10822 | B121: 45329 | C121: 45330 | D121: Same Day | E121: Ibrahim | F121: Olawale | G121: ibrahim.olawale@yahoo.com | H121: 8142822847 | I121: Home Office | J121: East | K121: Owerri | L121: Food & Beverages | M121: Cooking Oil | N121: Groundnut Oil 3L | O121: 20 | P121: 7266.01 | Q121: 15 | R121: 21798.03 | S121: 123522.17 | T121: -14757.02 | U121: Food & Beverages | V121: 14757.02 | W121: Large | X121: Large | Y121: No Discount
